Workbook

Sheet Ficha de datos
A1: Valor de Inversión | B1: % | C1: ROI | D1: % | E1: Facilidad de Implementación | F1: % | G1: Impacto | H1: % MIN-MAX
A2: <=10,000,000$ | B2: 1 | C2: <3 MESES | D2: 1 | E2: A (Facil) | F2: 1 | G2: Ambiental | H2: 0-25%
A3: >10,000,000$ <=20,000,000$ | B3: 0.6 | C3: >3 MESES<6 MESES | D3: 0.75 | E3: B (Intermedio) | F3: 0.5 | G3: Económico | H3: 0-25%
A4: >20,000,000$ | B4: 0.2 | C4: > 6 MESES | D4: 0.25 | E4: C (Dificil) | F4: 0.2 | G4: SST | H4: 0-20%
G5: Productividad | H5: 0-25%
A6: Máximo por idea | B6: 22000 | G6: Orden y aseo | H6: 0-5%
B8: 0.1 | D8: 0.1 | F8: 0.1 | H8: 0.7
A9: 1 | B9: =$B$6*B8*B2 -> 2200 | C9: 1 | D9: =$B$6*D8*D2 -> 2200 | E9: 1 | F9: =$B$6*F8*F2 -> 2200 | G9: 0 | H9: =+$H$15*G9 -> 0 | I9: Ambiental
A10: 0.6 | B10: =B6*0.1*B3 -> 1320 | C10: 0.75 | D10: =C10*D9 -> 1650 | E10: 0.5 | F10: =F9*E10 -> 1100 | G10: 0.25 | H10: =+$H$15*G10 -> 3850 | I10: Económico
A11: 0.2 | B11: =$B$6*0.1*B4 -> 440 | C11: 0.25 | D11: =D9*C11 -> 550 | E11: 0.2 | F11: =F9*E11 -> 440 | G11: 0 | H11: =+$H$15*G11 -> 0 | I11: SST
G12: 0.25 | H12: =+$H$15*G12 -> 3850 | I12: Productividad
G13: 0 | H13: =+$H$15*G13 -> 0 | I13: Orden y aseo
H15: =B6*H8 -> 15400

Sheet Tabla Calif. Puntos
C1: CALIFICACIÓN PLAN DE PUNTOS | Y1: CÓDIGO: FO-SDG-28 VERSIÓN: 01 FECHA: 19/07/2024
A3: FASE 1 CALIFICACIÓN | N3: 0.1 | O3: 0.1 | P3: 0.1 | Q3: 0.7 | R3: 1 | T3: FASE 2 IMPLEMENTACIÓN
A4: DOCUMENTO | B4: NOMBRE | C4: RADICADO | D4: PROCESO | E4: ESTADO | F4: VALOR INVERSIÓN | G4: ROI (MESES) | H4: FACILIDAD IMPLEM. | I4: IMPACTO AMBIENTAL (Máx. 25%) | J4: IMPACTO ECONÓMICO (Máx. 25%) | K4: IMPACTO SST (Máx. 20%) | L4: IMPACTO PRODUCTIVIDAD (Máx. 25%) | M4: IMPACTO ORDEN Y ASEO (Máx. 5%) | N4: PUNTOS VALOR INVERSIÓN | O4: PUNTOS ROI | P4: PUNTOS FACILIDAD IMPLEM. | Q4: PUNTOS IMPACTO | R4: PUNTOS TOTALES | S4: OBSERVACIONES | T4: CLASIFICACIÓN | U4: PRIORIDAD | V4: RESUMEN IDEA | W4: OBSERVACIONES | X4: RESPONSABLE | Y4: ESTADO IMPLEMENTACIÓN
A5: 1001812262 | B5: José Julián Betancur Estrada | C5: 501 | D5: Producción | E5: Descartada | N5: =IF(Tabla5[[#This Row],[VALOR INVERSIÓN]]="","",IF(Tabla5[[#This Row],[VALOR INVERSIÓN]]<=10000000,100%*10%*22000,IF(AND(Tabla5[[#This Row],[VALOR INVERSIÓN]]>10000000,Tabla5[[#This Row],[VALOR INVERSIÓN]]<=20000000),60%*10%*22000,20%*10%*22000))) | O5: =IF(Tabla5[[#This Row],[ROI (MESES)]]="","",IF(Tabla5[[#This Row],[ROI (MESES)]]="N/A","0",IF(Tabla5[[#This Row],[ROI (MESES)]]="<=3",100%*10%*22000,IF(Tabla5[[#This Row],[ROI (MESES)]]=">3<=6",75%*10%*22000,25%*10%*22000)))) | P5: =IF(Tabla5[[#This Row],[FACILIDAD IMPLEM.]]="","",IF(Tabla5[[#This Row],[FACILIDAD IMPLEM.]]="A",100%*10%*22000,IF(AND(Tabla5[[#This Row],[FACILIDAD IMPLEM.]]="B"),50%*10%*22000,20%*10%*22000))) | Q5: =Tabla5[[#This Row],[IMPACTO AMBIENTAL (Máx. 25%)]]*70%*22000+Tabla5[[#This Row],[IMPACTO ECONÓMICO (Máx. 25%)]]*70%*22000+Tabla5[[#This Row],[IMPACTO SST (Máx. 20%)]]*70%*22000+Tabla5[[#This Row],[IMPACTO PRODUCTIVIDAD (Máx. 25%)]]*70%*22000+Tabla5[[#This Row],[IMPACTO ORDEN Y ASEO (Máx. 5%)]]*70%*22000 -> 0 | R5: =IFERROR(Tabla5[[#This Row],[PUNTOS VALOR INVERSIÓN]]+Tabla5[[#This Row],[PUNTOS ROI ]]+Tabla5[[#This Row],[PUNTOS FACILIDAD IMPLEM. ]]+Tabla5[[#This Row],[PUNTOS IMPACTO ]],"")
A6: 59834499 | B6: Victoria Arciniegas Arteaga | C6: 502 | D6: G.Administrativa | E6: Descartada | N6: =IF(Tabla5[[#This Row],[VALOR INVERSIÓN]]="","",IF(Tabla5[[#This Row],[VALOR INVERSIÓN]]<=10000000,100%*10%*22000,IF(AND(Tabla5[[#This Row],[VALOR INVERSIÓN]]>10000000,Tabla5[[#This Row],[VALOR INVERSIÓN]]<=20000000),60%*10%*22000,20%*10%*22000))) | O6: =IF(Tabla5[[#This Row],[ROI (MESES)]]="","",IF(Tabla5[[#This Row],[ROI (MESES)]]="N/A","0",IF(Tabla5[[#This Row],[ROI (MESES)]]="<=3",100%*10%*22000,IF(Tabla5[[#This Row],[ROI (MESES)]]=">3<=6",75%*10%*22000,25%*10%*22000)))) | P6: =IF(Tabla5[[#This Row],[FACILIDAD IMPLEM.]]="","",IF(Tabla5[[#This Row],[FACILIDAD IMPLEM.]]="A",100%*10%*22000,IF(AND(Tabla5[[#This Row],[FACILIDAD IMPLEM.]]="B"),50%*10%*22000,20%*10%*22000))) | Q6: =Tabla5[[#This Row],[IMPACTO AMBIENTAL (Máx. 25%)]]*70%*22000+Tabla5[[#This Row],[IMPACTO ECONÓMICO (Máx. 25%)]]*70%*22000+Tabla5[[#This Row],[IMPACTO SST (Máx. 20%)]]*70%*22000+Tabla5[[#This Row],[IMPACTO PRODUCTIVIDAD (Máx. 25%)]]*70%*22000+Tabla5[[#This Row],[IMPACTO ORDEN Y ASEO (Máx. 5%)]]*70%*22000 -> 0 | R6: =IFERROR(Tabla5[[#This Row],[PUNTOS VALOR INVERSIÓN]]+Tabla5[[#This Row],[PUNTOS ROI ]]+Tabla5[[#This Row],[PUNTOS FACILIDAD IMPLEM. ]]+Tabla5[[#This Row],[PUNTOS IMPACTO ]],"")
A7: 1001812262 | B7: José Julián Betancur Estrada | C7: 532 | D7: Producción | E7: Descartada | N7: =IF(Tabla5[[#This Row],[VALOR INVERSIÓN]]="","",IF(Tabla5[[#This Row],[VALOR INVERSIÓN]]<=10000000,100%*10%*22000,IF(AND(Tabla5[[#This Row],[VALOR INVERSIÓN]]>10000000,Tabla5[[#This Row],[VALOR INVERSIÓN]]<=20000000),60%*10%*22000,20%*10%*22000))) | O7: =IF(Tabla5[[#This Row],[ROI (MESES)]]="","",IF(Tabla5[[#This Row],[ROI (MESES)]]="N/A","0",IF(Tabla5[[#This Row],[ROI (MESES)]]="<=3",100%*10%*22000,IF(Tabla5[[#This Row],[ROI (MESES)]]=">3<=6",75%*10%*22000,25%*10%*22000)))) | P7: =IF(Tabla5[[#This Row],[FACILIDAD IMPLEM.]]="","",IF(Tabla5[[#This Row],[FACILIDAD IMPLEM.]]="A",100%*10%*22000,IF(AND(Tabla5[[#This Row],[FACILIDAD IMPLEM.]]="B"),50%*10%*22000,20%*10%*22000))) | Q7: =Tabla5[[#This Row],[IMPACTO AMBIENTAL (Máx. 25%)]]*70%*22000+Tabla5[[#This Row],[IMPACTO ECONÓMICO (Máx. 25%)]]*70%*22000+Tabla5[[#This Row],[IMPACTO SST (Máx. 20%)]]*70%*22000+Tabla5[[#This Row],[IMPACTO PRODUCTIVIDAD (Máx. 25%)]]*70%*22000+Tabla5[[#This Row],[IMPACTO ORDEN Y ASEO (Máx. 5%)]]*70%*22000 -> 0 | R7: =IFERROR(Tabla5[[#This Row],[PUNTOS VALOR INVERSIÓN]]+Tabla5[[#This Row],[PUNTOS ROI ]]+Tabla5[[#This Row],[PUNTOS FACILIDAD IMPLEM. ]]+Tabla5[[#This Row],[PUNTOS IMPACTO ]],"")
A8: 1037572152 | B8: Jorge Andrés Carvajal | C8: 851 | D8: Producción | E8: Descartada | N8: =IF(Tabla5[[#This Row],[VALOR INVERSIÓN]]="","",IF(Tabla5[[#This Row],[VALOR INVERSIÓN]]<=10000000,100%*10%*22000,IF(AND(Tabla5[[#This Row],[VALOR INVERSIÓN]]>10000000,Tabla5[[#This Row],[VALOR INVERSIÓN]]<=20000000),60%*10%*22000,20%*10%*22000))) | O8: =IF(Tabla5[[#This Row],[ROI (MESES)]]="","",IF(Tabla5[[#This Row],[ROI (MESES)]]="N/A","0",IF(Tabla5[[#This Row],[ROI (MESES)]]="<=3",100%*10%*22000,IF(Tabla5[[#This Row],[ROI (MESES)]]=">3<=6",75%*10%*22000,25%*10%*22000)))) | P8: =IF(Tabla5[[#This Row],[FACILIDAD IMPLEM.]]="","",IF(Tabla5[[#This Row],[FACILIDAD IMPLEM.]]="A",100%*10%*22000,IF(AND(Tabla5[[#This Row],[FACILIDAD IMPLEM.]]="B"),50%*10%*22000,20%*10%*22000))) | Q8: =Tabla5[[#This Row],[IMPACTO AMBIENTAL (Máx. 25%)]]*70%*22000+Tabla5[[#This Row],[IMPACTO ECONÓMICO (Máx. 25%)]]*70%*22000+Tabla5[[#This Row],[IMPACTO SST (Máx. 20%)]]*70%*22000+Tabla5[[#This Row],[IMPACTO PRODUCTIVIDAD (Máx. 25%)]]*70%*22000+Tabla5[[#This Row],[IMPACTO ORDEN Y ASEO (Máx. 5%)]]*70%*22000 -> 0 | R8: =IFERROR(Tabla5[[#This Row],[PUNTOS VALOR INVERSIÓN]]+Tabla5[[#This Row],[PUNTOS ROI ]]+Tabla5[[#This Row],[PUNTOS FACILIDAD IMPLEM. ]]+Tabla5[[#This Row],[PUNTOS IMPACTO ]],"")
A9: 1193219755 | B9: Valentina Caruso Alian | C9: 862 | D9: SIG | E9: Descartada | N9: =IF(Tabla5[[#This Row],[VALOR INVERSIÓN]]="","",IF(Tabla5[[#This Row],[VALOR INVERSIÓN]]<=10000000,100%*10%*22000,IF(AND(Tabla5[[#This Row],[VALOR INVERSIÓN]]>10000000,Tabla5[[#This Row],[VALOR INVERSIÓN]]<=20000000),60%*10%*22000,20%*10%*22000))) | O9: =IF(Tabla5[[#This Row],[ROI (MESES)]]="","",IF(Tabla5[[#This Row],[ROI (MESES)]]="N/A","0",IF(Tabla5[[#This Row],[ROI (MESES)]]="<=3",100%*10%*22000,IF(Tabla5[[#This Row],[ROI (MESES)]]=">3<=6",75%*10%*22000,25%*10%*22000)))) | P9: =IF(Tabla5[[#This Row],[FACILIDAD IMPLEM.]]="","",IF(Tabla5[[#This Row],[FACILIDAD IMPLEM.]]="A",100%*10%*22000,IF(AND(Tabla5[[#This Row],[FACILIDAD IMPLEM.]]="B"),50%*10%*22000,20%*10%*22000))) | Q9: =Tabla5[[#This Row],[IMPACTO AMBIENTAL (Máx. 25%)]]*70%*22000+Tabla5[[#This Row],[IMPACTO ECONÓMICO (Máx. 25%)]]*70%*22000+Tabla5[[#This Row],[IMPACTO SST (Máx. 20%)]]*70%*22000+Tabla5[[#This Row],[IMPACTO PRODUCTIVIDAD (Máx. 25%)]]*70%*22000+Tabla5[[#This Row],[IMPACTO ORDEN Y ASEO (Máx. 5%)]]*70%*22000 -> 0 | R9: =IFERROR(Tabla5[[#This Row],[PUNTOS VALOR INVERSIÓN]]+Tabla5[[#This Row],[PUNTOS ROI ]]+Tabla5[[#This Row],[PUNTOS FACILIDAD IMPLEM. ]]+Tabla5[[#This Row],[PUNTOS IMPACTO ]],"")
A10: 78078872 | B10: Ivan Dario Babilonia Cordero | C10: 894 | D10: Producción | E10: Calificada | F10: 5000000 | G10: N/A | H10: C | I10: 0 | J10: 0.01 | K10: 0 | L10: 0.02 | M10: 0 | N10: =IF(Tabla5[[#This Row],[VALOR INVERSIÓN]]="","",IF(Tabla5[[#This Row],[VALOR INVERSIÓN]]<=10000000,100%*10%*22000,IF(AND(Tabla5[[#This Row],[VALOR INVERSIÓN]]>10000000,Tabla5[[#This Row],[VALOR INVERSIÓN]]<=20000000),60%*10%*22000,20%*10%*22000))) -> 2200 | O10: =IF(Tabla5[[#This Row],[ROI (MESES)]]="","",IF(Tabla5[[#This Row],[ROI (MESES)]]="N/A","0",IF(Tabla5[[#This Row],[ROI (MESES)]]="<=3",100%*10%*22000,IF(Tabla5[[#This Row],[ROI (MESES)]]=">3<=6",75%*10%*22000,25%*10%*22000)))) -> 0 | P10: =IF(Tabla5[[#This Row],[FACILIDAD IMPLEM.]]="","",IF(Tabla5[[#This Row],[FACILIDAD IMPLEM.]]="A",100%*10%*22000,IF(AND(Tabla5[[#This Row],[FACILIDAD IMPLEM.]]="B"),50%*10%*22000,20%*10%*22000))) -> 440 | Q10: =Tabla5[[#This Row],[IMPACTO AMBIENTAL (Máx. 25%)]]*70%*22000+Tabla5[[#This Row],[IMPACTO ECONÓMICO (Máx. 25%)]]*70%*22000+Tabla5[[#This Row],[IMPACTO SST (Máx. 20%)]]*70%*22000+Tabla5[[#This Row],[IMPACTO PRODUCTIVIDAD (Máx. 25%)]]*70%*22000+Tabla5[[#This Row],[IMPACTO ORDEN Y ASEO (Máx. 5%)]]*70%*22000 -> 462 | R10: =IFERROR(Tabla5[[#This Row],[PUNTOS VALOR INVERSIÓN]]+Tabla5[[#This Row],[PUNTOS ROI ]]+Tabla5[[#This Row],[PUNTOS FACILIDAD IMPLEM. ]]+Tabla5[[#This Row],[PUNTOS IMPACTO ]],"") -> 3102 | T10: Técnica G2 | U10: Baja | V10: Cambiar grapas de montaje por sistema fijo | W10: Pendiente pruebas | X10: No viable | Y10: Descartada
A11: 78078872 | B11: Ivan Dario Babilonia Cordero | C11: 895 | D11: Producción | E11: Descartada | N11: =IF(Tabla5[[#This Row],[VALOR INVERSIÓN]]="","",IF(Tabla5[[#This Row],[VALOR INVERSIÓN]]<=10000000,100%*10%*22000,IF(AND(Tabla5[[#This Row],[VALOR INVERSIÓN]]>10000000,Tabla5[[#This Row],[VALOR INVERSIÓN]]<=20000000),60%*10%*22000,20%*10%*22000))) | O11: =IF(Tabla5[[#This Row],[ROI (MESES)]]="","",IF(Tabla5[[#This Row],[ROI (MESES)]]="N/A","0",IF(Tabla5[[#This Row],[ROI (MESES)]]="<=3",100%*10%*22000,IF(Tabla5[[#This Row],[ROI (MESES)]]=">3<=6",75%*10%*22000,25%*10%*22000)))) | P11: =IF(Tabla5[[#This Row],[FACILIDAD IMPLEM.]]="","",IF(Tabla5[[#This Row],[FACILIDAD IMPLEM.]]="A",100%*10%*22000,IF(AND(Tabla5[[#This Row],[FACILIDAD IMPLEM.]]="B"),50%*10%*22000,20%*10%*22000))) | Q11: =Tabla5[[#This Row],[IMPACTO AMBIENTAL (Máx. 25%)]]*70%*22000+Tabla5[[#This Row],[IMPACTO ECONÓMICO (Máx. 25%)]]*70%*22000+Tabla5[[#This Row],[IMPACTO SST (Máx. 20%)]]*70%*22000+Tabla5[[#This Row],[IMPACTO PRODUCTIVIDAD (Máx. 25%)]]*70%*22000+Tabla5[[#This Row],[IMPACTO ORDEN Y ASEO (Máx. 5%)]]*70%*22000 -> 0 | R11: =IFERROR(Tabla5[[#This Row],[PUNTOS VALOR INVERSIÓN]]+Tabla5[[#This Row],[PUNTOS ROI ]]+Tabla5[[#This Row],[PUNTOS FACILIDAD IMPLEM. ]]+Tabla5[[#This Row],[PUNTOS IMPACTO ]],"")
A12: 1110570952 | B12: Andrés Felipe Ortega Rodríguez | C12: 949 | D12: Producción | E12: Descartada | N12: =IF(Tabla5[[#This Row],[VALOR INVERSIÓN]]="","",IF(Tabla5[[#This Row],[VALOR INVERSIÓN]]<=10000000,100%*10%*22000,IF(AND(Tabla5[[#This Row],[VALOR INVERSIÓN]]>10000000,Tabla5[[#This Row],[VALOR INVERSIÓN]]<=20000000),60%*10%*22000,20%*10%*22000))) | O12: =IF(Tabla5[[#This Row],[ROI (MESES)]]="","",IF(Tabla5[[#This Row],[ROI (MESES)]]="N/A","0",IF(Tabla5[[#This Row],[ROI (MESES)]]="<=3",100%*10%*22000,IF(Tabla5[[#This Row],[ROI (MESES)]]=">3<=6",75%*10%*22000,25%*10%*22000)))) | P12: =IF(Tabla5[[#This Row],[FACILIDAD IMPLEM.]]="","",IF(Tabla5[[#This Row],[FACILIDAD IMPLEM.]]="A",100%*10%*22000,IF(AND(Tabla5[[#This Row],[FACILIDAD IMPLEM.]]="B"),50%*10%*22000,20%*10%*22000))) | Q12: =Tabla5[[#This Row],[IMPACTO AMBIENTAL (Máx. 25%)]]*70%*22000+Tabla5[[#This Row],[IMPACTO ECONÓMICO (Máx. 25%)]]*70%*22000+Tabla5[[#This Row],[IMPACTO SST (Máx. 20%)]]*70%*22000+Tabla5[[#This Row],[IMPACTO PRODUCTIVIDAD (Máx. 25%)]]*70%*22000+Tabla5[[#This Row],[IMPACTO ORDEN Y ASEO (Máx. 5%)]]*70%*22000 -> 0 | R12: =IFERROR(Tabla5[[#This Row],[PUNTOS VALOR INVERSIÓN]]+Tabla5[[#This Row],[PUNTOS ROI ]]+Tabla5[[#This Row],[PUNTOS FACILIDAD IMPLEM. ]]+Tabla5[[#This Row],[PUNTOS IMPACTO ]],"")
A13: 71690439 | B13: Jhon Jairo Villamizar Gutierrez | C13: 963 | D13: Mantenimiento | E13: Calificada | F13: 1000000 | G13: N/A | H13: A | I13: 0 | J13: 0.025 | K13: 0 | L13: 0 | M13: 0 | N13: =IF(Tabla5[[#This Row],[VALOR INVERSIÓN]]="","",IF(Tabla5[[#This Row],[VALOR INVERSIÓN]]<=10000000,100%*10%*22000,IF(AND(Tabla5[[#This Row],[VALOR INVERSIÓN]]>10000000,Tabla5[[#This Row],[VALOR INVERSIÓN]]<=20000000),60%*10%*22000,20%*10%*22000))) -> 2200 | O13: =IF(Tabla5[[#This Row],[ROI (MESES)]]="","",IF(Tabla5[[#This Row],[ROI (MESES)]]="N/A","0",IF(Tabla5[[#This Row],[ROI (MESES)]]="<=3",100%*10%*22000,IF(Tabla5[[#This Row],[ROI (MESES)]]=">3<=6",75%*10%*22000,25%*10%*22000)))) -> 0 | P13: =IF(Tabla5[[#This Row],[FACILIDAD IMPLEM.]]="","",IF(Tabla5[[#This Row],[FACILIDAD IMPLEM.]]="A",100%*10%*22000,IF(AND(Tabla5[[#This Row],[FACILIDAD IMPLEM.]]="B"),50%*10%*22000,20%*10%*22000))) -> 2200 | Q13: =Tabla5[[#This Row],[IMPACTO AMBIENTAL (Máx. 25%)]]*70%*22000+Tabla5[[#This Row],[IMPACTO ECONÓMICO (Máx. 25%)]]*70%*22000+Tabla5[[#This Row],[IMPACTO SST (Máx. 20%)]]*70%*22000+Tabla5[[#This Row],[IMPACTO PRODUCTIVIDAD (Máx. 25%)]]*70%*22000+Tabla5[[#This Row],[IMPACTO ORDEN Y ASEO (Máx. 5%)]]*70%*22000 -> 385 | R13: =IFERROR(Tabla5[[#This Row],[PUNTOS VALOR INVERSIÓN]]+Tabla5[[#This Row],[PUNTOS ROI ]]+Tabla5[[#This Row],[PUNTOS FACILIDAD IMPLEM. ]]+Tabla5[[#This Row],[PUNTOS IMPACTO ]],"") -> 4785 | T13: Técnica G2 | U13: Baja | V13: Gancho de sostenimiento de botonera de diferencial de estación B en flama | W13: Ya se está implementando. | X13: Juan Manuel Aguinaga | Y13: En proceso
A14: 71690439 | B14: Jhon Jairo Villamizar Gutierrez | C14: 964 | D14: Mantenimiento | E14: Calificada | F14: 1000000 | G14: N/A | H14: B | I14: 0 | J14: 0.05 | K14: 0.12 | L14: 0 | M14: 0 | N14: =IF(Tabla5[[#This Row],[VALOR INVERSIÓN]]="","",IF(Tabla5[[#This Row],[VALOR INVERSIÓN]]<=10000000,100%*10%*22000,IF(AND(Tabla5[[#This Row],[VALOR INVERSIÓN]]>10000000,Tabla5[[#This Row],[VALOR INVERSIÓN]]<=20000000),60%*10%*22000,20%*10%*22000))) -> 2200 | O14: =IF(Tabla5[[#This Row],[ROI (MESES)]]="","",IF(Tabla5[[#This Row],[ROI (MESES)]]="N/A","0",IF(Tabla5[[#This Row],[ROI (MESES)]]="<=3",100%*10%*22000,IF(Tabla5[[#This Row],[ROI (MESES)]]=">3<=6",75%*10%*22000,25%*10%*22000)))) -> 0 | P14: =IF(Tabla5[[#This Row],[FACILIDAD IMPLEM.]]="","",IF(Tabla5[[#This Row],[FACILIDAD IMPLEM.]]="A",100%*10%*22000,IF(AND(Tabla5[[#This Row],[FACILIDAD IMPLEM.]]="B"),50%*10%*22000,20%*10%*22000))) -> 1100 | Q14: =Tabla5[[#This Row],[IMPACTO AMBIENTAL (Máx. 25%)]]*70%*22000+Tabla5[[#This Row],[IMPACTO ECONÓMICO (Máx. 25%)]]*70%*22000+Tabla5[[#This Row],[IMPACTO SST (Máx. 20%)]]*70%*22000+Tabla5[[#This Row],[IMPACTO PRODUCTIVIDAD (Máx. 25%)]]*70%*22000+Tabla5[[#This Row],[IMPACTO ORDEN Y ASEO (Máx. 5%)]]*70%*22000 -> 2618 | R14: =IFERROR(Tabla5[[#This Row],[PUNTOS VALOR INVERSIÓN]]+Tabla5[[#This Row],[PUNTOS ROI ]]+Tabla5[[#This Row],[PUNTOS FACILIDAD IMPLEM. ]]+Tabla5[[#This Row],[PUNTOS IMPACTO ]],"") -> 5918 | T14: Técnica G1 | U14: Baja | V14: Cambio de puerto de carga chisperos | W14: Al momento se tiene usa solucion temporal mientras se implementa el proceso HQ en todas las maquinas, Don Gustavo Ossa profundizara con Don Jhon Villamizar sobre el proceso del chispero | X14: No viable | Y14: Descartada
A15: 1047413742 | B15: Andrés Coneo | C15: 972 | D15: Mantenimiento | E15: Calificada | F15: 10000000 | G15: >6 | H15: C | I15: 0 | J15: 0.05 | K15: 0 | L15: 0 | M15: 0 | N15: =IF(Tabla5[[#This Row],[VALOR INVERSIÓN]]="","",IF(Tabla5[[#This Row],[VALOR INVERSIÓN]]<=10000000,100%*10%*22000,IF(AND(Tabla5[[#This Row],[VALOR INVERSIÓN]]>10000000,Tabla5[[#This Row],[VALOR INVERSIÓN]]<=20000000),60%*10%*22000,20%*10%*22000))) -> 2200 | O15: =IF(Tabla5[[#This Row],[ROI (MESES)]]="","",IF(Tabla5[[#This Row],[ROI (MESES)]]="N/A","0",IF(Tabla5[[#This Row],[ROI (MESES)]]="<=3",100%*10%*22000,IF(Tabla5[[#This Row],[ROI (MESES)]]=">3<=6",75%*10%*22000,25%*10%*22000)))) -> 550 | P15: =IF(Tabla5[[#This Row],[FACILIDAD IMPLEM.]]="","",IF(Tabla5[[#This Row],[FACILIDAD IMPLEM.]]="A",100%*10%*22000,IF(AND(Tabla5[[#This Row],[FACILIDAD IMPLEM.]]="B"),50%*10%*22000,20%*10%*22000))) -> 440 | Q15: =Tabla5[[#This Row],[IMPACTO AMBIENTAL (Máx. 25%)]]*70%*22000+Tabla5[[#This Row],[IMPACTO ECONÓMICO (Máx. 25%)]]*70%*22000+Tabla5[[#This Row],[IMPACTO SST (Máx. 20%)]]*70%*22000+Tabla5[[#This Row],[IMPACTO PRODUCTIVIDAD (Máx. 25%)]]*70%*22000+Tabla5[[#This Row],[IMPACTO ORDEN Y ASEO (Máx. 5%)]]*70%*22000 -> 770 | R15: =IFERROR(Tabla5[[#This Row],[PUNTOS VALOR INVERSIÓN]]+Tabla5[[#This Row],[PUNTOS ROI ]]+Tabla5[[#This Row],[PUNTOS FACILIDAD IMPLEM. ]]+Tabla5[[#This Row],[PUNTOS IMPACTO ]],"") -> 3960 | T15: Técnica G2 | U15: No Viable | V15: Control inalambrico para diferenciales | W15: Tiende a desaparecer con proyecto HQ | Y15: Descartada
A16: 1110570952 | B16: Andrés Felipe Ortega Rodríguez | C16: 977 | D16: Producción | E16: Descartada | N16: =IF(Tabla5[[#This Row],[VALOR INVERSIÓN]]="","",IF(Tabla5[[#This Row],[VALOR INVERSIÓN]]<=10000000,100%*10%*22000,IF(AND(Tabla5[[#This Row],[VALOR INVERSIÓN]]>10000000,Tabla5[[#This Row],[VALOR INVERSIÓN]]<=20000000),60%*10%*22000,20%*10%*22000))) | O16: =IF(Tabla5[[#This Row],[ROI (MESES)]]="","",IF(Tabla5[[#This Row],[ROI (MESES)]]="N/A","0",IF(Tabla5[[#This Row],[ROI (MESES)]]="<=3",100%*10%*22000,IF(Tabla5[[#This Row],[ROI (MESES)]]=">3<=6",75%*10%*22000,25%*10%*22000)))) | P16: =IF(Tabla5[[#This Row],[FACILIDAD IMPLEM.]]="","",IF(Tabla5[[#This Row],[FACILIDAD IMPLEM.]]="A",100%*10%*22000,IF(AND(Tabla5[[#This Row],[FACILIDAD IMPLEM.]]="B"),50%*10%*22000,20%*10%*22000))) | Q16: =Tabla5[[#This Row],[IMPACTO AMBIENTAL (Máx. 25%)]]*70%*22000+Tabla5[[#This Row],[IMPACTO ECONÓMICO (Máx. 25%)]]*70%*22000+Tabla5[[#This Row],[IMPACTO SST (Máx. 20%)]]*70%*22000+Tabla5[[#This Row],[IMPACTO PRODUCTIVIDAD (Máx. 25%)]]*70%*22000+Tabla5[[#This Row],[IMPACTO ORDEN Y ASEO (Máx. 5%)]]*70%*22000 -> 0 | R16: =IFERROR(Tabla5[[#This Row],[PUNTOS VALOR INVERSIÓN]]+Tabla5[[#This Row],[PUNTOS ROI ]]+Tabla5[[#This Row],[PUNTOS FACILIDAD IMPLEM. ]]+Tabla5[[#This Row],[PUNTOS IMPACTO ]],"")
A17: 1001812262 | B17: José Julián Betancur Estrada | C17: 4866 | D17: Producción | E17: Descartada | N17: =IF(Tabla5[[#This Row],[VALOR INVERSIÓN]]="","",IF(Tabla5[[#This Row],[VALOR INVERSIÓN]]<=10000000,100%*10%*22000,IF(AND(Tabla5[[#This Row],[VALOR INVERSIÓN]]>10000000,Tabla5[[#This Row],[VALOR INVERSIÓN]]<=20000000),60%*10%*22000,20%*10%*22000))) | O17: =IF(Tabla5[[#This Row],[ROI (MESES)]]="","",IF(Tabla5[[#This Row],[ROI (MESES)]]="N/A","0",IF(Tabla5[[#This Row],[ROI (MESES)]]="<=3",100%*10%*22000,IF(Tabla5[[#This Row],[ROI (MESES)]]=">3<=6",75%*10%*22000,25%*10%*22000)))) | P17: =IF(Tabla5[[#This Row],[FACILIDAD IMPLEM.]]="","",IF(Tabla5[[#This Row],[FACILIDAD IMPLEM.]]="A",100%*10%*22000,IF(AND(Tabla5[[#This Row],[FACILIDAD IMPLEM.]]="B"),50%*10%*22000,20%*10%*22000))) | Q17: =Tabla5[[#This Row],[IMPACTO AMBIENTAL (Máx. 25%)]]*70%*22000+Tabla5[[#This Row],[IMPACTO ECONÓMICO (Máx. 25%)]]*70%*22000+Tabla5[[#This Row],[IMPACTO SST (Máx. 20%)]]*70%*22000+Tabla5[[#This Row],[IMPACTO PRODUCTIVIDAD (Máx. 25%)]]*70%*22000+Tabla5[[#This Row],[IMPACTO ORDEN Y ASEO (Máx. 5%)]]*70%*22000 -> 0 | R17: =IFERROR(Tabla5[[#This Row],[PUNTOS VALOR INVERSIÓN]]+Tabla5[[#This Row],[PUNTOS ROI ]]+Tabla5[[#This Row],[PUNTOS FACILIDAD IMPLEM. ]]+Tabla5[[#This Row],[PUNTOS IMPACTO ]],"") | S17: 24/07/2024 Descartada. Es algo implementado y que se encuentra en proceso. 27/08/2024 03:46 pm Se habló con colaborador explicandole los motivos por los que no se tuvo en cuenta su idea, se contó con apoyo de Cristian Alzate
A18: 1001415647 | B18: Wilder Duvan Atehortua Iral | C18: 7424 | D18: Producción | E18: Calificada | F18: 3000000 | G18: >6 | H18: A | I18: 0 | J18: 0 | K18: 0.12 | L18: 0 | M18: 0.02 | N18: =IF(Tabla5[[#This Row],[VALOR INVERSIÓN]]="","",IF(Tabla5[[#This Row],[VALOR INVERSIÓN]]<=10000000,100%*10%*22000,IF(AND(Tabla5[[#This Row],[VALOR INVERSIÓN]]>10000000,Tabla5[[#This Row],[VALOR INVERSIÓN]]<=20000000),60%*10%*22000,20%*10%*22000))) -> 2200 | O18: =IF(Tabla5[[#This Row],[ROI (MESES)]]="","",IF(Tabla5[[#This Row],[ROI (MESES)]]="N/A","0",IF(Tabla5[[#This Row],[ROI (MESES)]]="<=3",100%*10%*22000,IF(Tabla5[[#This Row],[ROI (MESES)]]=">3<=6",75%*10%*22000,25%*10%*22000)))) -> 550 | P18: =IF(Tabla5[[#This Row],[FACILIDAD IMPLEM.]]="","",IF(Tabla5[[#This Row],[FACILIDAD IMPLEM.]]="A",100%*10%*22000,IF(AND(Tabla5[[#This Row],[FACILIDAD IMPLEM.]]="B"),50%*10%*22000,20%*10%*22000))) -> 2200 | Q18: =Tabla5[[#This Row],[IMPACTO AMBIENTAL (Máx. 25%)]]*70%*22000+Tabla5[[#This Row],[IMPACTO ECONÓMICO (Máx. 25%)]]*70%*22000+Tabla5[[#This Row],[IMPACTO SST (Máx. 20%)]]*70%*22000+Tabla5[[#This Row],[IMPACTO PRODUCTIVIDAD (Máx. 25%)]]*70%*22000+Tabla5[[#This Row],[IMPACTO ORDEN Y ASEO (Máx. 5%)]]*70%*22000 -> 2156 | R18: =IFERROR(Tabla5[[#This Row],[PUNTOS VALOR INVERSIÓN]]+Tabla5[[#This Row],[PUNTOS ROI ]]+Tabla5[[#This Row],[PUNTOS FACILIDAD IMPLEM. ]]+Tabla5[[#This Row],[PUNTOS IMPACTO ]],"") -> 7106 | T18: Técnica G1 | U18: Alta | V18: Lampara LED en forma de ARO | W18: Se va a validar luz tipo minero, hablar con SST | X18: Marcela Rios | Y18: En proceso
A19: 1026132871 | B19: Lyda Sorany Montoya Castaño | C19: 8060 | D19: Comercial | E19: Calificada | F19: 5000000 | G19: >6 | H19: B | I19: 0 | J19: 0.04 | K19: 0 | L19: 0 | M19: 0 | N19: =IF(Tabla5[[#This Row],[VALOR INVERSIÓN]]="","",IF(Tabla5[[#This Row],[VALOR INVERSIÓN]]<=10000000,100%*10%*22000,IF(AND(Tabla5[[#This Row],[VALOR INVERSIÓN]]>10000000,Tabla5[[#This Row],[VALOR INVERSIÓN]]<=20000000),60%*10%*22000,20%*10%*22000))) -> 2200 | O19: =IF(Tabla5[[#This Row],[ROI (MESES)]]="","",IF(Tabla5[[#This Row],[ROI (MESES)]]="N/A","0",IF(Tabla5[[#This Row],[ROI (MESES)]]="<=3",100%*10%*22000,IF(Tabla5[[#This Row],[ROI (MESES)]]=">3<=6",75%*10%*22000,25%*10%*22000)))) -> 550 | P19: =IF(Tabla5[[#This Row],[FACILIDAD IMPLEM.]]="","",IF(Tabla5[[#This Row],[FACILIDAD IMPLEM.]]="A",100%*10%*22000,IF(AND(Tabla5[[#This Row],[FACILIDAD IMPLEM.]]="B"),50%*10%*22000,20%*10%*22000))) -> 1100 | Q19: =Tabla5[[#This Row],[IMPACTO AMBIENTAL (Máx. 25%)]]*70%*22000+Tabla5[[#This Row],[IMPACTO ECONÓMICO (Máx. 25%)]]*70%*22000+Tabla5[[#This Row],[IMPACTO SST (Máx. 20%)]]*70%*22000+Tabla5[[#This Row],[IMPACTO PRODUCTIVIDAD (Máx. 25%)]]*70%*22000+Tabla5[[#This Row],[IMPACTO ORDEN Y ASEO (Máx. 5%)]]*70%*22000 -> 616 | R19: =IFERROR(Tabla5[[#This Row],[PUNTOS VALOR INVERSIÓN]]+Tabla5[[#This Row],[PUNTOS ROI ]]+Tabla5[[#This Row],[PUNTOS FACILIDAD IMPLEM. ]]+Tabla5[[#This Row],[PUNTOS IMPACTO ]],"") -> 4466 | S19: Reactivar bebedero caballo | T19: Comercial | U19: Alta | V19: Reactivar bebedero para caballo | W19: Revisar flotadores para relanzamiento de producto | X19: JuanDavid Rojas | Y19: En proceso
A20: 71175113 | B20: Diego León Vásques Cortés | C20: 4951 | D20: Producción | E20: Calificada | F20: 500000 | G20: <=3 | H20: A | I20: 0 | J20: 0 | K20: 0.08 | L20: 0 | M20: 0 | N20: =IF(Tabla5[[#This Row],[VALOR INVERSIÓN]]="","",IF(Tabla5[[#This Row],[VALOR INVERSIÓN]]<=10000000,100%*10%*22000,IF(AND(Tabla5[[#This Row],[VALOR INVERSIÓN]]>10000000,Tabla5[[#This Row],[VALOR INVERSIÓN]]<=20000000),60%*10%*22000,20%*10%*22000))) -> 2200 | O20: =IF(Tabla5[[#This Row],[ROI (MESES)]]="","",IF(Tabla5[[#This Row],[ROI (MESES)]]="N/A","0",IF(Tabla5[[#This Row],[ROI (MESES)]]="<=3",100%*10%*22000,IF(Tabla5[[#This Row],[ROI (MESES)]]=">3<=6",75%*10%*22000,25%*10%*22000)))) -> 2200 | P20: =IF(Tabla5[[#This Row],[FACILIDAD IMPLEM.]]="","",IF(Tabla5[[#This Row],[FACILIDAD IMPLEM.]]="A",100%*10%*22000,IF(AND(Tabla5[[#This Row],[FACILIDAD IMPLEM.]]="B"),50%*10%*22000,20%*10%*22000))) -> 2200 | Q20: =Tabla5[[#This Row],[IMPACTO AMBIENTAL (Máx. 25%)]]*70%*22000+Tabla5[[#This Row],[IMPACTO ECONÓMICO (Máx. 25%)]]*70%*22000+Tabla5[[#This Row],[IMPACTO SST (Máx. 20%)]]*70%*22000+Tabla5[[#This Row],[IMPACTO PRODUCTIVIDAD (Máx. 25%)]]*70%*22000+Tabla5[[#This Row],[IMPACTO ORDEN Y ASEO (Máx. 5%)]]*70%*22000 -> 1232 | R20: =IFERROR(Tabla5[[#This Row],[PUNTOS VALOR INVERSIÓN]]+Tabla5[[#This Row],[PUNTOS ROI ]]+Tabla5[[#This Row],[PUNTOS FACILIDAD IMPLEM. ]]+Tabla5[[#This Row],[PUNTOS IMPACTO ]],"") -> 7832 | S20: 24/07/2024 Puntuada | T20: Técnica G1 | U20: Alta | V20: Caja para evitar desconexión de herramientas | W20: Realizar un diseño y entregarselo al personal de ensamble/soldadura para que realicen las demas, hacer un inventario de cuantas se requieren (Diego Vasquez) | X20: Juan David Rojas - Gustavo Ossa | Y20: Implementada
A21: 1035913083 | B21: Maria Teresa Ríos Zapata | C21: 5469 | D21: Producción | E21: Calificada | F21: 1000000 | G21: N/A | H21: A | I21: 0 | J21: 0 | K21: 0.03 | L21: 0 | M21: 0 | N21: =IF(Tabla5[[#This Row],[VALOR INVERSIÓN]]="","",IF(Tabla5[[#This Row],[VALOR INVERSIÓN]]<=10000000,100%*10%*22000,IF(AND(Tabla5[[#This Row],[VALOR INVERSIÓN]]>10000000,Tabla5[[#This Row],[VALOR INVERSIÓN]]<=20000000),60%*10%*22000,20%*10%*22000))) -> 2200 | O21: =IF(Tabla5[[#This Row],[ROI (MESES)]]="","",IF(Tabla5[[#This Row],[ROI (MESES)]]="N/A","0",IF(Tabla5[[#This Row],[ROI (MESES)]]="<=3",100%*10%*22000,IF(Tabla5[[#This Row],[ROI (MESES)]]=">3<=6",75%*10%*22000,25%*10%*22000)))) -> 0 | P21: =IF(Tabla5[[#This Row],[FACILIDAD IMPLEM.]]="","",IF(Tabla5[[#This Row],[FACILIDAD IMPLEM.]]="A",100%*10%*22000,IF(AND(Tabla5[[#This Row],[FACILIDAD IMPLEM.]]="B"),50%*10%*22000,20%*10%*22000))) -> 2200 | Q21: =Tabla5[[#This Row],[IMPACTO AMBIENTAL (Máx. 25%)]]*70%*22000+Tabla5[[#This Row],[IMPACTO ECONÓMICO (Máx. 25%)]]*70%*22000+Tabla5[[#This Row],[IMPACTO SST (Máx. 20%)]]*70%*22000+Tabla5[[#This Row],[IMPACTO PRODUCTIVIDAD (Máx. 25%)]]*70%*22000+Tabla5[[#This Row],[IMPACTO ORDEN Y ASEO (Máx. 5%)]]*70%*22000 -> 462 | R21: =IFERROR(Tabla5[[#This Row],[PUNTOS VALOR INVERSIÓN]]+Tabla5[[#This Row],[PUNTOS ROI ]]+Tabla5[[#This Row],[PUNTOS FACILIDAD IMPLEM. ]]+Tabla5[[#This Row],[PUNTOS IMPACTO ]],"") -> 4862 | S21: 31/07/2024 Puntuada | T21: Técnica G2 | U21: No Viable | V21: Interruptor individual para los tomas de las herramientas. | W21: No es justificable la implememtación. | Y21: Descartada
A22: 1110570952 | B22: Andrés Felipe Ortega Rodríguez | C22: 5470 | D22: Producción | E22: Calificada | F22: 4000000 | G22: N/A | H22: A | I22: 0 | J22: 0 | K22: 0.07 | L22: 0 | M22: 0 | N22: =IF(Tabla5[[#This Row],[VALOR INVERSIÓN]]="","",IF(Tabla5[[#This Row],[VALOR INVERSIÓN]]<=10000000,100%*10%*22000,IF(AND(Tabla5[[#This Row],[VALOR INVERSIÓN]]>10000000,Tabla5[[#This Row],[VALOR INVERSIÓN]]<=20000000),60%*10%*22000,20%*10%*22000))) -> 2200 | O22: =IF(Tabla5[[#This Row],[ROI (MESES)]]="","",IF(Tabla5[[#This Row],[ROI (MESES)]]="N/A","0",IF(Tabla5[[#This Row],[ROI (MESES)]]="<=3",100%*10%*22000,IF(Tabla5[[#This Row],[ROI (MESES)]]=">3<=6",75%*10%*22000,25%*10%*22000)))) -> 0 | P22: =IF(Tabla5[[#This Row],[FACILIDAD IMPLEM.]]="","",IF(Tabla5[[#This Row],[FACILIDAD IMPLEM.]]="A",100%*10%*22000,IF(AND(Tabla5[[#This Row],[FACILIDAD IMPLEM.]]="B"),50%*10%*22000,20%*10%*22000))) -> 2200 | Q22: =Tabla5[[#This Row],[IMPACTO AMBIENTAL (Máx. 25%)]]*70%*22000+Tabla5[[#This Row],[IMPACTO ECONÓMICO (Máx. 25%)]]*70%*22000+Tabla5[[#This Row],[IMPACTO SST (Máx. 20%)]]*70%*22000+Tabla5[[#This Row],[IMPACTO PRODUCTIVIDAD (Máx. 25%)]]*70%*22000+Tabla5[[#This Row],[IMPACTO ORDEN Y ASEO (Máx. 5%)]]*70%*22000 -> 1078 | R22: =IFERROR(Tabla5[[#This Row],[PUNTOS VALOR INVERSIÓN]]+Tabla5[[#This Row],[PUNTOS ROI ]]+Tabla5[[#This Row],[PUNTOS FACILIDAD IMPLEM. ]]+Tabla5[[#This Row],[PUNTOS IMPACTO ]],"") -> 5478 | S22: 31/07/2024 Puntuada | T22: Comercial | U22: Media | V22: Rampa en caseta de control de ingreso | W22: Revisar con Jhon Jairo Henao para mejorar la entrada por la caseta de control aprovechando la pavimentación | X22: No Implementar | Y22: Descartada
A23: 71311035 | B23: Duverney Oquendo | C23: 7546 | D23: Producción | E23: Calificada | F23: 10000000 | G23: >6 | H23: B | I23: 0 | J23: 0.1 | K23: 0.07 | L23: 0.1 | M23: 0.02 | N23: =IF(Tabla5[[#This Row],[VALOR INVERSIÓN]]="","",IF(Tabla5[[#This Row],[VALOR INVERSIÓN]]<=10000000,100%*10%*22000,IF(AND(Tabla5[[#This Row],[VALOR INVERSIÓN]]>10000000,Tabla5[[#This Row],[VALOR INVERSIÓN]]<=20000000),60%*10%*22000,20%*10%*22000))) -> 2200 | O23: =IF(Tabla5[[#This Row],[ROI (MESES)]]="","",IF(Tabla5[[#This Row],[ROI (MESES)]]="N/A","0",IF(Tabla5[[#This Row],[ROI (MESES)]]="<=3",100%*10%*22000,IF(Tabla5[[#This Row],[ROI (MESES)]]=">3<=6",75%*10%*22000,25%*10%*22000)))) -> 550 | P23: =IF(Tabla5[[#This Row],[FACILIDAD IMPLEM.]]="","",IF(Tabla5[[#This Row],[FACILIDAD IMPLEM.]]="A",100%*10%*22000,IF(AND(Tabla5[[#This Row],[FACILIDAD IMPLEM.]]="B"),50%*10%*22000,20%*10%*22000))) -> 1100 | Q23: =Tabla5[[#This Row],[IMPACTO AMBIENTAL (Máx. 25%)]]*70%*22000+Tabla5[[#This Row],[IMPACTO ECONÓMICO (Máx. 25%)]]*70%*22000+Tabla5[[#This Row],[IMPACTO SST (Máx. 20%)]]*70%*22000+Tabla5[[#This Row],[IMPACTO PRODUCTIVIDAD (Máx. 25%)]]*70%*22000+Tabla5[[#This Row],[IMPACTO ORDEN Y ASEO (Máx. 5%)]]*70%*22000 -> 4466 | R23: =IFERROR(Tabla5[[#This Row],[PUNTOS VALOR INVERSIÓN]]+Tabla5[[#This Row],[PUNTOS ROI ]]+Tabla5[[#This Row],[PUNTOS FACILIDAD IMPLEM. ]]+Tabla5[[#This Row],[PUNTOS IMPACTO ]],"") -> 8316 | T23: Técnica G1 | U23: Alta | V23: Aislante para moldes de casillas | W23: Liderar Juan David Rojas y comercial, con el apoyo del proceso técnico. | X23: Juan David Rojas - Cristian Cardona | Y23: Implementada
A24: 1059704792 | B24: Jorge Eliecer Calderón Reyes | C24: 5918 | D24: G.Técnica | E24: Calificada | F24: 1500000 | G24: >3<=6 | H24: A | I24: 0.03 | J24: 0.09 | K24: 0 | L24: 0.03 | M24: 0 | N24: =IF(Tabla5[[#This Row],[VALOR INVERSIÓN]]="","",IF(Tabla5[[#This Row],[VALOR INVERSIÓN]]<=10000000,100%*10%*22000,IF(AND(Tabla5[[#This Row],[VALOR INVERSIÓN]]>10000000,Tabla5[[#This Row],[VALOR INVERSIÓN]]<=20000000),60%*10%*22000,20%*10%*22000))) -> 2200 | O24: =IF(Tabla5[[#This Row],[ROI (MESES)]]="","",IF(Tabla5[[#This Row],[ROI (MESES)]]="N/A","0",IF(Tabla5[[#This Row],[ROI (MESES)]]="<=3",100%*10%*22000,IF(Tabla5[[#This Row],[ROI (MESES)]]=">3<=6",75%*10%*22000,25%*10%*22000)))) -> 1650 | P24: =IF(Tabla5[[#This Row],[FACILIDAD IMPLEM.]]="","",IF(Tabla5[[#This Row],[FACILIDAD IMPLEM.]]="A",100%*10%*22000,IF(AND(Tabla5[[#This Row],[FACILIDAD IMPLEM.]]="B"),50%*10%*22000,20%*10%*22000))) -> 2200 | Q24: =Tabla5[[#This Row],[IMPACTO AMBIENTAL (Máx. 25%)]]*70%*22000+Tabla5[[#This Row],[IMPACTO ECONÓMICO (Máx. 25%)]]*70%*22000+Tabla5[[#This Row],[IMPACTO SST (Máx. 20%)]]*70%*22000+Tabla5[[#This Row],[IMPACTO PRODUCTIVIDAD (Máx. 25%)]]*70%*22000+Tabla5[[#This Row],[IMPACTO ORDEN Y ASEO (Máx. 5%)]]*70%*22000 -> 2310 | R24: =IFERROR(Tabla5[[#This Row],[PUNTOS VALOR INVERSIÓN]]+Tabla5[[#This Row],[PUNTOS ROI ]]+Tabla5[[#This Row],[PUNTOS FACILIDAD IMPLEM. ]]+Tabla5[[#This Row],[PUNTOS IMPACTO ]],"") -> 8360 | S24: 14/08/2024 Puntuada | T24: Técnica G1 | U24: Media | V24: Filtros para las flautas | W24: Hacer un rollo de malla que sirva de filtro dentro de la tuberia, para que la limalla no entre al racor | X24: Sebastián Ossa | Y24: En proceso
A25: 4116903 | B25: Luis Eduardo Perdomo Rojas | C25: 5919 | D25: Producción | E25: Descartada | N25: =IF(Tabla5[[#This Row],[VALOR INVERSIÓN]]="","",IF(Tabla5[[#This Row],[VALOR INVERSIÓN]]<=10000000,100%*10%*22000,IF(AND(Tabla5[[#This Row],[VALOR INVERSIÓN]]>10000000,Tabla5[[#This Row],[VALOR INVERSIÓN]]<=20000000),60%*10%*22000,20%*10%*22000))) | O25: =IF(Tabla5[[#This Row],[ROI (MESES)]]="","",IF(Tabla5[[#This Row],[ROI (MESES)]]="N/A","0",IF(Tabla5[[#This Row],[ROI (MESES)]]="<=3",100%*10%*22000,IF(Tabla5[[#This Row],[ROI (MESES)]]=">3<=6",75%*10%*22000,25%*10%*22000)))) | P25: =IF(Tabla5[[#This Row],[FACILIDAD IMPLEM.]]="","",IF(Tabla5[[#This Row],[FACILIDAD IMPLEM.]]="A",100%*10%*22000,IF(AND(Tabla5[[#This Row],[FACILIDAD IMPLEM.]]="B"),50%*10%*22000,20%*10%*22000))) | Q25: =Tabla5[[#This Row],[IMPACTO AMBIENTAL (Máx. 25%)]]*70%*22000+Tabla5[[#This Row],[IMPACTO ECONÓMICO (Máx. 25%)]]*70%*22000+Tabla5[[#This Row],[IMPACTO SST (Máx. 20%)]]*70%*22000+Tabla5[[#This Row],[IMPACTO PRODUCTIVIDAD (Máx. 25%)]]*70%*22000+Tabla5[[#This Row],[IMPACTO ORDEN Y ASEO (Máx. 5%)]]*70%*22000 -> 0 | R25: =IFERROR(Tabla5[[#This Row],[PUNTOS VALOR INVERSIÓN]]+Tabla5[[#This Row],[PUNTOS ROI ]]+Tabla5[[#This Row],[PUNTOS FACILIDAD IMPLEM. ]]+Tabla5[[#This Row],[PUNTOS IMPACTO ]],"") | S25: 14/08/2024 Descartada. 20/08/2024 09:20am Se habló con colaborador, se invitó a replantear ambas ideas, se contó con apoyo de Cristian Alzate
A26: 1000751888 | B26: Juan Camilo Agudelo Muñoz | C26: 5983 | D26: TI | E26: Calificada | F26: 6000000 | G26: >6 | H26: B | I26: 0 | J26: 0.14 | K26: 0 | L26: 0.06 | M26: 0 | N26: =IF(Tabla5[[#This Row],[VALOR INVERSIÓN]]="","",IF(Tabla5[[#This Row],[VALOR INVERSIÓN]]<=10000000,100%*10%*22000,IF(AND(Tabla5[[#This Row],[VALOR INVERSIÓN]]>10000000,Tabla5[[#This Row],[VALOR INVERSIÓN]]<=20000000),60%*10%*22000,20%*10%*22000))) -> 2200 | O26: =IF(Tabla5[[#This Row],[ROI (MESES)]]="","",IF(Tabla5[[#This Row],[ROI (MESES)]]="N/A","0",IF(Tabla5[[#This Row],[ROI (MESES)]]="<=3",100%*10%*22000,IF(Tabla5[[#This Row],[ROI (MESES)]]=">3<=6",75%*10%*22000,25%*10%*22000)))) -> 550 | P26: =IF(Tabla5[[#This Row],[FACILIDAD IMPLEM.]]="","",IF(Tabla5[[#This Row],[FACILIDAD IMPLEM.]]="A",100%*10%*22000,IF(AND(Tabla5[[#This Row],[FACILIDAD IMPLEM.]]="B"),50%*10%*22000,20%*10%*22000))) -> 1100 | Q26: =Tabla5[[#This Row],[IMPACTO AMBIENTAL (Máx. 25%)]]*70%*22000+Tabla5[[#This Row],[IMPACTO ECONÓMICO (Máx. 25%)]]*70%*22000+Tabla5[[#This Row],[IMPACTO SST (Máx. 20%)]]*70%*22000+Tabla5[[#This Row],[IMPACTO PRODUCTIVIDAD (Máx. 25%)]]*70%*22000+Tabla5[[#This Row],[IMPACTO ORDEN Y ASEO (Máx. 5%)]]*70%*22000 -> 3080 | R26: =IFERROR(Tabla5[[#This Row],[PUNTOS VALOR INVERSIÓN]]+Tabla5[[#This Row],[PUNTOS ROI ]]+Tabla5[[#This Row],[PUNTOS FACILIDAD IMPLEM. ]]+Tabla5[[#This Row],[PUNTOS IMPACTO ]],"") -> 6930 | S26: 21/08/2024 Pendiente evaluar costos de reposición de equipos con TI | T26: Técnica G1 | U26: Media | V26: Sistema Android para lectura de codigos en estampación | X26: Camilo Agudelo - Julián Giraldo | Y26: Sin empezar
A27: 71216235 | B27: Jorge Andrés Aguilar | C27: 5984 | D27: Producción | E27: Descartada | N27: =IF(Tabla5[[#This Row],[VALOR INVERSIÓN]]="","",IF(Tabla5[[#This Row],[VALOR INVERSIÓN]]<=10000000,100%*10%*22000,IF(AND(Tabla5[[#This Row],[VALOR INVERSIÓN]]>10000000,Tabla5[[#This Row],[VALOR INVERSIÓN]]<=20000000),60%*10%*22000,20%*10%*22000))) | O27: =IF(Tabla5[[#This Row],[ROI (MESES)]]="","",IF(Tabla5[[#This Row],[ROI (MESES)]]="N/A","0",IF(Tabla5[[#This Row],[ROI (MESES)]]="<=3",100%*10%*22000,IF(Tabla5[[#This Row],[ROI (MESES)]]=">3<=6",75%*10%*22000,25%*10%*22000)))) | P27: =IF(Tabla5[[#This Row],[FACILIDAD IMPLEM.]]="","",IF(Tabla5[[#This Row],[FACILIDAD IMPLEM.]]="A",100%*10%*22000,IF(AND(Tabla5[[#This Row],[FACILIDAD IMPLEM.]]="B"),50%*10%*22000,20%*10%*22000))) | Q27: =Tabla5[[#This Row],[IMPACTO AMBIENTAL (Máx. 25%)]]*70%*22000+Tabla5[[#This Row],[IMPACTO ECONÓMICO (Máx. 25%)]]*70%*22000+Tabla5[[#This Row],[IMPACTO SST (Máx. 20%)]]*70%*22000+Tabla5[[#This Row],[IMPACTO PRODUCTIVIDAD (Máx. 25%)]]*70%*22000+Tabla5[[#This Row],[IMPACTO ORDEN Y ASEO (Máx. 5%)]]*70%*22000 -> 0 | R27: =IFERROR(Tabla5[[#This Row],[PUNTOS VALOR INVERSIÓN]]+Tabla5[[#This Row],[PUNTOS ROI ]]+Tabla5[[#This Row],[PUNTOS FACILIDAD IMPLEM. ]]+Tabla5[[#This Row],[PUNTOS IMPACTO ]],"") | S27: 21/08/2024 Debe ampliar el concepto y validarse con SST, realizar pruebas.
A28: 1005346180 | B28: Diego Uribe Castellanos | C28: 6026 | D28: G.Técnica | E28: Calificada | F28: 1000000 | G28: <=3 | H28: A | I28: 0.16 | J28: 0.17 | K28: 0 | L28: 0.07 | M28: 0.03 | N28: =IF(Tabla5[[#This Row],[VALOR INVERSIÓN]]="","",IF(Tabla5[[#This Row],[VALOR INVERSIÓN]]<=10000000,100%*10%*22000,IF(AND(Tabla5[[#This Row],[VALOR INVERSIÓN]]>10000000,Tabla5[[#This Row],[VALOR INVERSIÓN]]<=20000000),60%*10%*22000,20%*10%*22000))) -> 2200 | O28: =IF(Tabla5[[#This Row],[ROI (MESES)]]="","",IF(Tabla5[[#This Row],[ROI (MESES)]]="N/A","0",IF(Tabla5[[#This Row],[ROI (MESES)]]="<=3",100%*10%*22000,IF(Tabla5[[#This Row],[ROI (MESES)]]=">3<=6",75%*10%*22000,25%*10%*22000)))) -> 2200 | P28: =IF(Tabla5[[#This Row],[FACILIDAD IMPLEM.]]="","",IF(Tabla5[[#This Row],[FACILIDAD IMPLEM.]]="A",100%*10%*22000,IF(AND(Tabla5[[#This Row],[FACILIDAD IMPLEM.]]="B"),50%*10%*22000,20%*10%*22000))) -> 2200 | Q28: =Tabla5[[#This Row],[IMPACTO AMBIENTAL (Máx. 25%)]]*70%*22000+Tabla5[[#This Row],[IMPACTO ECONÓMICO (Máx. 25%)]]*70%*22000+Tabla5[[#This Row],[IMPACTO SST (Máx. 20%)]]*70%*22000+Tabla5[[#This Row],[IMPACTO PRODUCTIVIDAD (Máx. 25%)]]*70%*22000+Tabla5[[#This Row],[IMPACTO ORDEN Y ASEO (Máx. 5%)]]*70%*22000 -> 6622 | R28: =IFERROR(Tabla5[[#This Row],[PUNTOS VALOR INVERSIÓN]]+Tabla5[[#This Row],[PUNTOS ROI ]]+Tabla5[[#This Row],[PUNTOS FACILIDAD IMPLEM. ]]+Tabla5[[#This Row],[PUNTOS IMPACTO ]],"") -> 13222 | S28: 21/08/2024 Puntuada. 24/02/2025 R. Jhon R | T28: Técnica G1 | U28: Baja | V28: Limpieza profunda de flautas y toberas | W28: Pendiente, no aplica realizar en la parada autonoma, sino en el plan de mantenimiento para realizarse por parte del operario y el MT. | X28: Sebastián Ossa | Y28: Sin empezar
A29: 1045047014 | B29: Juan Carlos Cano Ocampo | C29: 6057 | D29: Producción | E29: Descartada | N29: =IF(Tabla5[[#This Row],[VALOR INVERSIÓN]]="","",IF(Tabla5[[#This Row],[VALOR INVERSIÓN]]<=10000000,100%*10%*22000,IF(AND(Tabla5[[#This Row],[VALOR INVERSIÓN]]>10000000,Tabla5[[#This Row],[VALOR INVERSIÓN]]<=20000000),60%*10%*22000,20%*10%*22000))) | O29: =IF(Tabla5[[#This Row],[ROI (MESES)]]="","",IF(Tabla5[[#This Row],[ROI (MESES)]]="N/A","0",IF(Tabla5[[#This Row],[ROI (MESES)]]="<=3",100%*10%*22000,IF(Tabla5[[#This Row],[ROI (MESES)]]=">3<=6",75%*10%*22000,25%*10%*22000)))) | P29: =IF(Tabla5[[#This Row],[FACILIDAD IMPLEM.]]="","",IF(Tabla5[[#This Row],[FACILIDAD IMPLEM.]]="A",100%*10%*22000,IF(AND(Tabla5[[#This Row],[FACILIDAD IMPLEM.]]="B"),50%*10%*22000,20%*10%*22000))) | Q29: =Tabla5[[#This Row],[IMPACTO AMBIENTAL (Máx. 25%)]]*70%*22000+Tabla5[[#This Row],[IMPACTO ECONÓMICO (Máx. 25%)]]*70%*22000+Tabla5[[#This Row],[IMPACTO SST (Máx. 20%)]]*70%*22000+Tabla5[[#This Row],[IMPACTO PRODUCTIVIDAD (Máx. 25%)]]*70%*22000+Tabla5[[#This Row],[IMPACTO ORDEN Y ASEO (Máx. 5%)]]*70%*22000 -> 0 | R29: =IFERROR(Tabla5[[#This Row],[PUNTOS VALOR INVERSIÓN]]+Tabla5[[#This Row],[PUNTOS ROI ]]+Tabla5[[#This Row],[PUNTOS FACILIDAD IMPLEM. ]]+Tabla5[[#This Row],[PUNTOS IMPACTO ]],"") | S29: 03/09/2024 Descartada. 21/08/2024 Debe ampliar concepto de la idea. 28/08/2024 10:50am Se habló con colaborador, contando con acompañamiento de Crsitian Alzate. El colaborador solicita le concedan un espacio ya que tiene una presentación construída en power point para presentarla. 28/08/2024 Comité aprueba darle un espacio de 15 min en el proximo encuentro del 03/09/2024. 03/09/2024 Luego de sustentación comité considera idea como viable en el ambito de personas naturales, por lo cual no se puntuó, se decide que desde TH se revise la posibilidad de realizar un complemento enfocado en su experiencia y darle algún tipo de reconocimiento.
A30: 73570530 | B30: Jair José Aguilar Mora | C30: 6071 | D30: Producción | E30: Descartada | N30: =IF(Tabla5[[#This Row],[VALOR INVERSIÓN]]="","",IF(Tabla5[[#This Row],[VALOR INVERSIÓN]]<=10000000,100%*10%*22000,IF(AND(Tabla5[[#This Row],[VALOR INVERSIÓN]]>10000000,Tabla5[[#This Row],[VALOR INVERSIÓN]]<=20000000),60%*10%*22000,20%*10%*22000))) | O30: =IF(Tabla5[[#This Row],[ROI (MESES)]]="","",IF(Tabla5[[#This Row],[ROI (MESES)]]="N/A","0",IF(Tabla5[[#This Row],[ROI (MESES)]]="<=3",100%*10%*22000,IF(Tabla5[[#This Row],[ROI (MESES)]]=">3<=6",75%*10%*22000,25%*10%*22000)))) | P30: =IF(Tabla5[[#This Row],[FACILIDAD IMPLEM.]]="","",IF(Tabla5[[#This Row],[FACILIDAD IMPLEM.]]="A",100%*10%*22000,IF(AND(Tabla5[[#This Row],[FACILIDAD IMPLEM.]]="B"),50%*10%*22000,20%*10%*22000))) | Q30: =Tabla5[[#This Row],[IMPACTO AMBIENTAL (Máx. 25%)]]*70%*22000+Tabla5[[#This Row],[IMPACTO ECONÓMICO (Máx. 25%)]]*70%*22000+Tabla5[[#This Row],[IMPACTO SST (Máx. 20%)]]*70%*22000+Tabla5[[#This Row],[IMPACTO PRODUCTIVIDAD (Máx. 25%)]]*70%*22000+Tabla5[[#This Row],[IMPACTO ORDEN Y ASEO (Máx. 5%)]]*70%*22000 -> 0 | R30: =IFERROR(Tabla5[[#This Row],[PUNTOS VALOR INVERSIÓN]]+Tabla5[[#This Row],[PUNTOS ROI ]]+Tabla5[[#This Row],[PUNTOS FACILIDAD IMPLEM. ]]+Tabla5[[#This Row],[PUNTOS IMPACTO ]],"") | S30: 21/08/2024 Descartada. Técnicamente un extractor no retira calor por radiación. Pendiente hablar con operario.
A31: 1001416385 | B31: Duván Arley López Jiménez | C31: 6223 | D31: T.Humano | E31: Descartada | N31: =IF(Tabla5[[#This Row],[VALOR INVERSIÓN]]="","",IF(Tabla5[[#This Row],[VALOR INVERSIÓN]]<=10000000,100%*10%*22000,IF(AND(Tabla5[[#This Row],[VALOR INVERSIÓN]]>10000000,Tabla5[[#This Row],[VALOR INVERSIÓN]]<=20000000),60%*10%*22000,20%*10%*22000))) | O31: =IF(Tabla5[[#This Row],[ROI (MESES)]]="","",IF(Tabla5[[#This Row],[ROI (MESES)]]="N/A","0",IF(Tabla5[[#This Row],[ROI (MESES)]]="<=3",100%*10%*22000,IF(Tabla5[[#This Row],[ROI (MESES)]]=">3<=6",75%*10%*22000,25%*10%*22000)))) | P31: =IF(Tabla5[[#This Row],[FACILIDAD IMPLEM.]]="","",IF(Tabla5[[#This Row],[FACILIDAD IMPLEM.]]="A",100%*10%*22000,IF(AND(Tabla5[[#This Row],[FACILIDAD IMPLEM.]]="B"),50%*10%*22000,20%*10%*22000))) | Q31: =Tabla5[[#This Row],[IMPACTO AMBIENTAL (Máx. 25%)]]*70%*22000+Tabla5[[#This Row],[IMPACTO ECONÓMICO (Máx. 25%)]]*70%*22000+Tabla5[[#This Row],[IMPACTO SST (Máx. 20%)]]*70%*22000+Tabla5[[#This Row],[IMPACTO PRODUCTIVIDAD (Máx. 25%)]]*70%*22000+Tabla5[[#This Row],[IMPACTO ORDEN Y ASEO (Máx. 5%)]]*70%*22000 -> 0 | R31: =IFERROR(Tabla5[[#This Row],[PUNTOS VALOR INVERSIÓN]]+Tabla5[[#This Row],[PUNTOS ROI ]]+Tabla5[[#This Row],[PUNTOS FACILIDAD IMPLEM. ]]+Tabla5[[#This Row],[PUNTOS IMPACTO ]],"") | S31: 28/08/2024 Se debe revisar PNC de máquinas 8 y 17 con Sebastián Gallego para validar la necesidad y viabilidad de esta idea.
A32: 1128479264 | B32: Luis Carlos Ramos Rangel | C32: 6226 | D32: G.Técnica | E32: Descartada | N32: =IF(Tabla5[[#This Row],[VALOR INVERSIÓN]]="","",IF(Tabla5[[#This Row],[VALOR INVERSIÓN]]<=10000000,100%*10%*22000,IF(AND(Tabla5[[#This Row],[VALOR INVERSIÓN]]>10000000,Tabla5[[#This Row],[VALOR INVERSIÓN]]<=20000000),60%*10%*22000,20%*10%*22000))) | O32: =IF(Tabla5[[#This Row],[ROI (MESES)]]="","",IF(Tabla5[[#This Row],[ROI (MESES)]]="N/A","0",IF(Tabla5[[#This Row],[ROI (MESES)]]="<=3",100%*10%*22000,IF(Tabla5[[#This Row],[ROI (MESES)]]=">3<=6",75%*10%*22000,25%*10%*22000)))) | P32: =IF(Tabla5[[#This Row],[FACILIDAD IMPLEM.]]="","",IF(Tabla5[[#This Row],[FACILIDAD IMPLEM.]]="A",100%*10%*22000,IF(AND(Tabla5[[#This Row],[FACILIDAD IMPLEM.]]="B"),50%*10%*22000,20%*10%*22000))) | Q32: =Tabla5[[#This Row],[IMPACTO AMBIENTAL (Máx. 25%)]]*70%*22000+Tabla5[[#This Row],[IMPACTO ECONÓMICO (Máx. 25%)]]*70%*22000+Tabla5[[#This Row],[IMPACTO SST (Máx. 20%)]]*70%*22000+Tabla5[[#This Row],[IMPACTO PRODUCTIVIDAD (Máx. 25%)]]*70%*22000+Tabla5[[#This Row],[IMPACTO ORDEN Y ASEO (Máx. 5%)]]*70%*22000 -> 0 | R32: =IFERROR(Tabla5[[#This Row],[PUNTOS VALOR INVERSIÓN]]+Tabla5[[#This Row],[PUNTOS ROI ]]+Tabla5[[#This Row],[PUNTOS FACILIDAD IMPLEM. ]]+Tabla5[[#This Row],[PUNTOS IMPACTO ]],"") | S32: 28/08/2024 Descartada. La implementación de las OT aún se encuentra en proceso de ajustes y son temas que se están revisando.
A33: 1035919597 | B33: Sebastián Ossa Londoño | C33: 6240 | D33: Producción | E33: Calificada | F33: 100000 | G33: <=3 | H33: A | I33: 0.1 | J33: 0.07 | K33: 0.05 | L33: 0.2 | M33: 0.03 | N33: =IF(Tabla5[[#This Row],[VALOR INVERSIÓN]]="","",IF(Tabla5[[#This Row],[VALOR INVERSIÓN]]<=10000000,100%*10%*22000,IF(AND(Tabla5[[#This Row],[VALOR INVERSIÓN]]>10000000,Tabla5[[#This Row],[VALOR INVERSIÓN]]<=20000000),60%*10%*22000,20%*10%*22000))) -> 2200 | O33: =IF(Tabla5[[#This Row],[ROI (MESES)]]="","",IF(Tabla5[[#This Row],[ROI (MESES)]]="N/A","0",IF(Tabla5[[#This Row],[ROI (MESES)]]="<=3",100%*10%*22000,IF(Tabla5[[#This Row],[ROI (MESES)]]=">3<=6",75%*10%*22000,25%*10%*22000)))) -> 2200 | P33: =IF(Tabla5[[#This Row],[FACILIDAD IMPLEM.]]="","",IF(Tabla5[[#This Row],[FACILIDAD IMPLEM.]]="A",100%*10%*22000,IF(AND(Tabla5[[#This Row],[FACILIDAD IMPLEM.]]="B"),50%*10%*22000,20%*10%*22000))) -> 2200 | Q33: =Tabla5[[#This Row],[IMPACTO AMBIENTAL (Máx. 25%)]]*70%*22000+Tabla5[[#This Row],[IMPACTO ECONÓMICO (Máx. 25%)]]*70%*22000+Tabla5[[#This Row],[IMPACTO SST (Máx. 20%)]]*70%*22000+Tabla5[[#This Row],[IMPACTO PRODUCTIVIDAD (Máx. 25%)]]*70%*22000+Tabla5[[#This Row],[IMPACTO ORDEN Y ASEO (Máx. 5%)]]*70%*22000 -> 6930 | R33: =IFERROR(Tabla5[[#This Row],[PUNTOS VALOR INVERSIÓN]]+Tabla5[[#This Row],[PUNTOS ROI ]]+Tabla5[[#This Row],[PUNTOS FACILIDAD IMPLEM. ]]+Tabla5[[#This Row],[PUNTOS IMPACTO ]],"") -> 13530 | S33: 28/08/2024 Se deben realizar pruebas, seguimiento y validar. componentes químicos. 24/02/2025 Se continuarán buscando alternativas. R. Jhon R. | T33: Técnica G1 | U33: Media | V33: Soldadura fria o pegamento epóxico para los poros de los moldes | W33: Don John solicitara a sebastian continuar con los ensayos de este o un homologo para validar eficiencia | X33: No Implementar | Y33: Descartada
A34: 1128479264 | B34: Luis Carlos Ramos Rangel | C34: 6252 | D34: G.Técnica | E34: Calificada | F34: 1000000 | G34: N/A | H34: A | I34: 0.04 | J34: 0 | K34: 0 | L34: 0 | M34: 0.01 | N34: =IF(Tabla5[[#This Row],[VALOR INVERSIÓN]]="","",IF(Tabla5[[#This Row],[VALOR INVERSIÓN]]<=10000000,100%*10%*22000,IF(AND(Tabla5[[#This Row],[VALOR INVERSIÓN]]>10000000,Tabla5[[#This Row],[VALOR INVERSIÓN]]<=20000000),60%*10%*22000,20%*10%*22000))) -> 2200 | O34: =IF(Tabla5[[#This Row],[ROI (MESES)]]="","",IF(Tabla5[[#This Row],[ROI (MESES)]]="N/A","0",IF(Tabla5[[#This Row],[ROI (MESES)]]="<=3",100%*10%*22000,IF(Tabla5[[#This Row],[ROI (MESES)]]=">3<=6",75%*10%*22000,25%*10%*22000)))) -> 0 | P34: =IF(Tabla5[[#This Row],[FACILIDAD IMPLEM.]]="","",IF(Tabla5[[#This Row],[FACILIDAD IMPLEM.]]="A",100%*10%*22000,IF(AND(Tabla5[[#This Row],[FACILIDAD IMPLEM.]]="B"),50%*10%*22000,20%*10%*22000))) -> 2200 | Q34: =Tabla5[[#This Row],[IMPACTO AMBIENTAL (Máx. 25%)]]*70%*22000+Tabla5[[#This Row],[IMPACTO ECONÓMICO (Máx. 25%)]]*70%*22000+Tabla5[[#This Row],[IMPACTO SST (Máx. 20%)]]*70%*22000+Tabla5[[#This Row],[IMPACTO PRODUCTIVIDAD (Máx. 25%)]]*70%*22000+Tabla5[[#This Row],[IMPACTO ORDEN Y ASEO (Máx. 5%)]]*70%*22000 -> 770 | R34: =IFERROR(Tabla5[[#This Row],[PUNTOS VALOR INVERSIÓN]]+Tabla5[[#This Row],[PUNTOS ROI ]]+Tabla5[[#This Row],[PUNTOS FACILIDAD IMPLEM. ]]+Tabla5[[#This Row],[PUNTOS IMPACTO ]],"") -> 5170 | S34: 28/08/2024 Puntuada | T34: Técnica G2 | U34: No Viable | V34: Recipientes para material contaminado por planta | W34: No se soluciona nigún problema con la propuesta | Y34: Descartada
A35: 1035918433 | B35: Mateo Arango Betancur | C35: 6254 | D35: Producción | E35: Descartada | N35: =IF(Tabla5[[#This Row],[VALOR INVERSIÓN]]="","",IF(Tabla5[[#This Row],[VALOR INVERSIÓN]]<=10000000,100%*10%*22000,IF(AND(Tabla5[[#This Row],[VALOR INVERSIÓN]]>10000000,Tabla5[[#This Row],[VALOR INVERSIÓN]]<=20000000),60%*10%*22000,20%*10%*22000))) | O35: =IF(Tabla5[[#This Row],[ROI (MESES)]]="","",IF(Tabla5[[#This Row],[ROI (MESES)]]="N/A","0",IF(Tabla5[[#This Row],[ROI (MESES)]]="<=3",100%*10%*22000,IF(Tabla5[[#This Row],[ROI (MESES)]]=">3<=6",75%*10%*22000,25%*10%*22000)))) | P35: =IF(Tabla5[[#This Row],[FACILIDAD IMPLEM.]]="","",IF(Tabla5[[#This Row],[FACILIDAD IMPLEM.]]="A",100%*10%*22000,IF(AND(Tabla5[[#This Row],[FACILIDAD IMPLEM.]]="B"),50%*10%*22000,20%*10%*22000))) | Q35: =Tabla5[[#This Row],[IMPACTO AMBIENTAL (Máx. 25%)]]*70%*22000+Tabla5[[#This Row],[IMPACTO ECONÓMICO (Máx. 25%)]]*70%*22000+Tabla5[[#This Row],[IMPACTO SST (Máx. 20%)]]*70%*22000+Tabla5[[#This Row],[IMPACTO PRODUCTIVIDAD (Máx. 25%)]]*70%*22000+Tabla5[[#This Row],[IMPACTO ORDEN Y ASEO (Máx. 5%)]]*70%*22000 -> 0 | R35: =IFERROR(Tabla5[[#This Row],[PUNTOS VALOR INVERSIÓN]]+Tabla5[[#This Row],[PUNTOS ROI ]]+Tabla5[[#This Row],[PUNTOS FACILIDAD IMPLEM. ]]+Tabla5[[#This Row],[PUNTOS IMPACTO ]],"") | S35: 28/08/2024 Se debe validar funcionalidad y eficacia en el proceso. 9/12/2024 Luego de realizar las pruebas, SST la descarta porque se genera material particulado lo cual afectarías las zonas aledañas y se debería hacer un encerramiento, lo cual conlleva mas inversión.
A36: 1065659658 | B36: Roberto Carlos Rodríguez | C36: 6255 | D36: Producción | E36: Calificada | F36: 1000000 | G36: >6 | H36: B | I36: 0 | J36: 0.04 | K36: 0.01 | L36: 0.02 | M36: 0 | N36: =IF(Tabla5[[#This Row],[VALOR INVERSIÓN]]="","",IF(Tabla5[[#This Row],[VALOR INVERSIÓN]]<=10000000,100%*10%*22000,IF(AND(Tabla5[[#This Row],[VALOR INVERSIÓN]]>10000000,Tabla5[[#This Row],[VALOR INVERSIÓN]]<=20000000),60%*10%*22000,20%*10%*22000))) -> 2200 | O36: =IF(Tabla5[[#This Row],[ROI (MESES)]]="","",IF(Tabla5[[#This Row],[ROI (MESES)]]="N/A","0",IF(Tabla5[[#This Row],[ROI (MESES)]]="<=3",100%*10%*22000,IF(Tabla5[[#This Row],[ROI (MESES)]]=">3<=6",75%*10%*22000,25%*10%*22000)))) -> 550 | P36: =IF(Tabla5[[#This Row],[FACILIDAD IMPLEM.]]="","",IF(Tabla5[[#This Row],[FACILIDAD IMPLEM.]]="A",100%*10%*22000,IF(AND(Tabla5[[#This Row],[FACILIDAD IMPLEM.]]="B"),50%*10%*22000,20%*10%*22000))) -> 1100 | Q36: =Tabla5[[#This Row],[IMPACTO AMBIENTAL (Máx. 25%)]]*70%*22000+Tabla5[[#This Row],[IMPACTO ECONÓMICO (Máx. 25%)]]*70%*22000+Tabla5[[#This Row],[IMPACTO SST (Máx. 20%)]]*70%*22000+Tabla5[[#This Row],[IMPACTO PRODUCTIVIDAD (Máx. 25%)]]*70%*22000+Tabla5[[#This Row],[IMPACTO ORDEN Y ASEO (Máx. 5%)]]*70%*22000 -> 1078 | R36: =IFERROR(Tabla5[[#This Row],[PUNTOS VALOR INVERSIÓN]]+Tabla5[[#This Row],[PUNTOS ROI ]]+Tabla5[[#This Row],[PUNTOS FACILIDAD IMPLEM. ]]+Tabla5[[#This Row],[PUNTOS IMPACTO ]],"") -> 4928 | S36: 28/08/2024 Puntuada | T36: Técnica G2 | U36: No Viable | V36: Pines de patineta para regular ajuste de flautas | W36: No es optimo para el proceso. | Y36: Descartada
A37: 17685011 | B37: Alfredo Trujillo Cordoba | C37: 6262 | D37: G.Técnica | E37: Descartada | N37: =IF(Tabla5[[#This Row],[VALOR INVERSIÓN]]="","",IF(Tabla5[[#This Row],[VALOR INVERSIÓN]]<=10000000,100%*10%*22000,IF(AND(Tabla5[[#This Row],[VALOR INVERSIÓN]]>10000000,Tabla5[[#This Row],[VALOR INVERSIÓN]]<=20000000),60%*10%*22000,20%*10%*22000))) | O37: =IF(Tabla5[[#This Row],[ROI (MESES)]]="","",IF(Tabla5[[#This Row],[ROI (MESES)]]="N/A","0",IF(Tabla5[[#This Row],[ROI (MESES)]]="<=3",100%*10%*22000,IF(Tabla5[[#This Row],[ROI (MESES)]]=">3<=6",75%*10%*22000,25%*10%*22000)))) | P37: =IF(Tabla5[[#This Row],[FACILIDAD IMPLEM.]]="","",IF(Tabla5[[#This Row],[FACILIDAD IMPLEM.]]="A",100%*10%*22000,IF(AND(Tabla5[[#This Row],[FACILIDAD IMPLEM.]]="B"),50%*10%*22000,20%*10%*22000))) | Q37: =Tabla5[[#This Row],[IMPACTO AMBIENTAL (Máx. 25%)]]*70%*22000+Tabla5[[#This Row],[IMPACTO ECONÓMICO (Máx. 25%)]]*70%*22000+Tabla5[[#This Row],[IMPACTO SST (Máx. 20%)]]*70%*22000+Tabla5[[#This Row],[IMPACTO PRODUCTIVIDAD (Máx. 25%)]]*70%*22000+Tabla5[[#This Row],[IMPACTO ORDEN Y ASEO (Máx. 5%)]]*70%*22000 -> 0 | R37: =IFERROR(Tabla5[[#This Row],[PUNTOS VALOR INVERSIÓN]]+Tabla5[[#This Row],[PUNTOS ROI ]]+Tabla5[[#This Row],[PUNTOS FACILIDAD IMPLEM. ]]+Tabla5[[#This Row],[PUNTOS IMPACTO ]],"") | S37: 03/09/2024 Validar con Jhony Tuberquia
A38: 17685011 | B38: Alfredo Trujillo Cordoba | C38: 6263 | D38: G.Técnica | E38: Calificada | F38: 10000000 | G38: >6 | H38: A | I38: 0.1 | J38: 0.05 | K38: 0.02 | L38: 0.1 | M38: 0.05 | N38: =IF(Tabla5[[#This Row],[VALOR INVERSIÓN]]="","",IF(Tabla5[[#This Row],[VALOR INVERSIÓN]]<=10000000,100%*10%*22000,IF(AND(Tabla5[[#This Row],[VALOR INVERSIÓN]]>10000000,Tabla5[[#This Row],[VALOR INVERSIÓN]]<=20000000),60%*10%*22000,20%*10%*22000))) -> 2200 | O38: =IF(Tabla5[[#This Row],[ROI (MESES)]]="","",IF(Tabla5[[#This Row],[ROI (MESES)]]="N/A","0",IF(Tabla5[[#This Row],[ROI (MESES)]]="<=3",100%*10%*22000,IF(Tabla5[[#This Row],[ROI (MESES)]]=">3<=6",75%*10%*22000,25%*10%*22000)))) -> 550 | P38: =IF(Tabla5[[#This Row],[FACILIDAD IMPLEM.]]="","",IF(Tabla5[[#This Row],[FACILIDAD IMPLEM.]]="A",100%*10%*22000,IF(AND(Tabla5[[#This Row],[FACILIDAD IMPLEM.]]="B"),50%*10%*22000,20%*10%*22000))) -> 2200 | Q38: =Tabla5[[#This Row],[IMPACTO AMBIENTAL (Máx. 25%)]]*70%*22000+Tabla5[[#This Row],[IMPACTO ECONÓMICO (Máx. 25%)]]*70%*22000+Tabla5[[#This Row],[IMPACTO SST (Máx. 20%)]]*70%*22000+Tabla5[[#This Row],[IMPACTO PRODUCTIVIDAD (Máx. 25%)]]*70%*22000+Tabla5[[#This Row],[IMPACTO ORDEN Y ASEO (Máx. 5%)]]*70%*22000 -> 4928 | R38: =IFERROR(Tabla5[[#This Row],[PUNTOS VALOR INVERSIÓN]]+Tabla5[[#This Row],[PUNTOS ROI ]]+Tabla5[[#This Row],[PUNTOS FACILIDAD IMPLEM. ]]+Tabla5[[#This Row],[PUNTOS IMPACTO ]],"") -> 9878 | S38: 03/09/2024 Validar con Jhony Tuberquia | T38: Técnica G1 | U38: No Viable | V38: Mamparas entre cajas de materia prima | W38: Definir con mantenimiento fabricación | Y38: Descartada
A39: 1045047014 | B39: Juan Carlos Cano Ocampo | C39: 6376 | D39: Producción | E39: Descartada | N39: =IF(Tabla5[[#This Row],[VALOR INVERSIÓN]]="","",IF(Tabla5[[#This Row],[VALOR INVERSIÓN]]<=10000000,100%*10%*22000,IF(AND(Tabla5[[#This Row],[VALOR INVERSIÓN]]>10000000,Tabla5[[#This Row],[VALOR INVERSIÓN]]<=20000000),60%*10%*22000,20%*10%*22000))) | O39: =IF(Tabla5[[#This Row],[ROI (MESES)]]="","",IF(Tabla5[[#This Row],[ROI (MESES)]]="N/A","0",IF(Tabla5[[#This Row],[ROI (MESES)]]="<=3",100%*10%*22000,IF(Tabla5[[#This Row],[ROI (MESES)]]=">3<=6",75%*10%*22000,25%*10%*22000)))) | P39: =IF(Tabla5[[#This Row],[FACILIDAD IMPLEM.]]="","",IF(Tabla5[[#This Row],[FACILIDAD IMPLEM.]]="A",100%*10%*22000,IF(AND(Tabla5[[#This Row],[FACILIDAD IMPLEM.]]="B"),50%*10%*22000,20%*10%*22000))) | Q39: =Tabla5[[#This Row],[IMPACTO AMBIENTAL (Máx. 25%)]]*70%*22000+Tabla5[[#This Row],[IMPACTO ECONÓMICO (Máx. 25%)]]*70%*22000+Tabla5[[#This Row],[IMPACTO SST (Máx. 20%)]]*70%*22000+Tabla5[[#This Row],[IMPACTO PRODUCTIVIDAD (Máx. 25%)]]*70%*22000+Tabla5[[#This Row],[IMPACTO ORDEN Y ASEO (Máx. 5%)]]*70%*22000 -> 0 | R39: =IFERROR(Tabla5[[#This Row],[PUNTOS VALOR INVERSIÓN]]+Tabla5[[#This Row],[PUNTOS ROI ]]+Tabla5[[#This Row],[PUNTOS FACILIDAD IMPLEM. ]]+Tabla5[[#This Row],[PUNTOS IMPACTO ]],"") | S39: 03/09/2024 Descartada. Lo que propone es lo que se hace actualmente desde proceso comercial.
A40: 1128479264 | B40: Luis Carlos Ramos Rangel | C40: 6377 | D40: G.Técnica | E40: Descartada | N40: =IF(Tabla5[[#This Row],[VALOR INVERSIÓN]]="","",IF(Tabla5[[#This Row],[VALOR INVERSIÓN]]<=10000000,100%*10%*22000,IF(AND(Tabla5[[#This Row],[VALOR INVERSIÓN]]>10000000,Tabla5[[#This Row],[VALOR INVERSIÓN]]<=20000000),60%*10%*22000,20%*10%*22000))) | O40: =IF(Tabla5[[#This Row],[ROI (MESES)]]="","",IF(Tabla5[[#This Row],[ROI (MESES)]]="N/A","0",IF(Tabla5[[#This Row],[ROI (MESES)]]="<=3",100%*10%*22000,IF(Tabla5[[#This Row],[ROI (MESES)]]=">3<=6",75%*10%*22000,25%*10%*22000)))) | P40: =IF(Tabla5[[#This Row],[FACILIDAD IMPLEM.]]="","",IF(Tabla5[[#This Row],[FACILIDAD IMPLEM.]]="A",100%*10%*22000,IF(AND(Tabla5[[#This Row],[FACILIDAD IMPLEM.]]="B"),50%*10%*22000,20%*10%*22000))) | Q40: =Tabla5[[#This Row],[IMPACTO AMBIENTAL (Máx. 25%)]]*70%*22000+Tabla5[[#This Row],[IMPACTO ECONÓMICO (Máx. 25%)]]*70%*22000+Tabla5[[#This Row],[IMPACTO SST (Máx. 20%)]]*70%*22000+Tabla5[[#This Row],[IMPACTO PRODUCTIVIDAD (Máx. 25%)]]*70%*22000+Tabla5[[#This Row],[IMPACTO ORDEN Y ASEO (Máx. 5%)]]*70%*22000 -> 0 | R40: =IFERROR(Tabla5[[#This Row],[PUNTOS VALOR INVERSIÓN]]+Tabla5[[#This Row],[PUNTOS ROI ]]+Tabla5[[#This Row],[PUNTOS FACILIDAD IMPLEM. ]]+Tabla5[[#This Row],[PUNTOS IMPACTO ]],"") | S40: 03/09/2024 Descartada. Lo que propone fue una idea surgida e implementada en la zona de respeto.
A41: 3378476 | B41: Román José Dario Briñez Boscán | C41: 6397 | D41: G.Técnica | E41: Descartada | N41: =IF(Tabla5[[#This Row],[VALOR INVERSIÓN]]="","",IF(Tabla5[[#This Row],[VALOR INVERSIÓN]]<=10000000,100%*10%*22000,IF(AND(Tabla5[[#This Row],[VALOR INVERSIÓN]]>10000000,Tabla5[[#This Row],[VALOR INVERSIÓN]]<=20000000),60%*10%*22000,20%*10%*22000))) | O41: =IF(Tabla5[[#This Row],[ROI (MESES)]]="","",IF(Tabla5[[#This Row],[ROI (MESES)]]="N/A","0",IF(Tabla5[[#This Row],[ROI (MESES)]]="<=3",100%*10%*22000,IF(Tabla5[[#This Row],[ROI (MESES)]]=">3<=6",75%*10%*22000,25%*10%*22000)))) | P41: =IF(Tabla5[[#This Row],[FACILIDAD IMPLEM.]]="","",IF(Tabla5[[#This Row],[FACILIDAD IMPLEM.]]="A",100%*10%*22000,IF(AND(Tabla5[[#This Row],[FACILIDAD IMPLEM.]]="B"),50%*10%*22000,20%*10%*22000))) | Q41: =Tabla5[[#This Row],[IMPACTO AMBIENTAL (Máx. 25%)]]*70%*22000+Tabla5[[#This Row],[IMPACTO ECONÓMICO (Máx. 25%)]]*70%*22000+Tabla5[[#This Row],[IMPACTO SST (Máx. 20%)]]*70%*22000+Tabla5[[#This Row],[IMPACTO PRODUCTIVIDAD (Máx. 25%)]]*70%*22000+Tabla5[[#This Row],[IMPACTO ORDEN Y ASEO (Máx. 5%)]]*70%*22000 -> 0 | R41: =IFERROR(Tabla5[[#This Row],[PUNTOS VALOR INVERSIÓN]]+Tabla5[[#This Row],[PUNTOS ROI ]]+Tabla5[[#This Row],[PUNTOS FACILIDAD IMPLEM. ]]+Tabla5[[#This Row],[PUNTOS IMPACTO ]],"") | S41: 03/09/2024 Pendiente validar necesidad, utilidad y viabilidad con Supervisor materias primas y coordinador de PCC.
A42: 1128479264 | B42: Luis Carlos Ramos Rangel | C42: 6398 | D42: G.Técnica | E42: Calificada | F42: 1000000 | G42: N/A | H42: A | I42: 0 | J42: 0 | K42: 0 | L42: 0 | M42: 0 | N42: =IF(Tabla5[[#This Row],[VALOR INVERSIÓN]]="","",IF(Tabla5[[#This Row],[VALOR INVERSIÓN]]<=10000000,100%*10%*22000,IF(AND(Tabla5[[#This Row],[VALOR INVERSIÓN]]>10000000,Tabla5[[#This Row],[VALOR INVERSIÓN]]<=20000000),60%*10%*22000,20%*10%*22000))) -> 2200 | O42: =IF(Tabla5[[#This Row],[ROI (MESES)]]="","",IF(Tabla5[[#This Row],[ROI (MESES)]]="N/A","0",IF(Tabla5[[#This Row],[ROI (MESES)]]="<=3",100%*10%*22000,IF(Tabla5[[#This Row],[ROI (MESES)]]=">3<=6",75%*10%*22000,25%*10%*22000)))) -> 0 | P42: =IF(Tabla5[[#This Row],[FACILIDAD IMPLEM.]]="","",IF(Tabla5[[#This Row],[FACILIDAD IMPLEM.]]="A",100%*10%*22000,IF(AND(Tabla5[[#This Row],[FACILIDAD IMPLEM.]]="B"),50%*10%*22000,20%*10%*22000))) -> 2200 | Q42: =Tabla5[[#This Row],[IMPACTO AMBIENTAL (Máx. 25%)]]*70%*22000+Tabla5[[#This Row],[IMPACTO ECONÓMICO (Máx. 25%)]]*70%*22000+Tabla5[[#This Row],[IMPACTO SST (Máx. 20%)]]*70%*22000+Tabla5[[#This Row],[IMPACTO PRODUCTIVIDAD (Máx. 25%)]]*70%*22000+Tabla5[[#This Row],[IMPACTO ORDEN Y ASEO (Máx. 5%)]]*70%*22000 -> 0 | R42: =IFERROR(Tabla5[[#This Row],[PUNTOS VALOR INVERSIÓN]]+Tabla5[[#This Row],[PUNTOS ROI ]]+Tabla5[[#This Row],[PUNTOS FACILIDAD IMPLEM. ]]+Tabla5[[#This Row],[PUNTOS IMPACTO ]],"") -> 4400 | S42: 03/09/2924 No se alcanzó a evaluar. 10/09/2024 Puntuada | T42: Técnica G2 | U42: No Viable | V42: Cajón para herramientas en máquinas flama | W42: Ya tienen tablero de sombras. | Y42: Descartada
A43: 1037572152 | B43: Jorge Andrés Carvajal | C43: 8972 | D43: Producción | E43: Calificada | F43: 5000000 | G43: <=3 | H43: A | I43: 0 | J43: 0.15 | K43: 0 | L43: 0 | M43: 0 | N43: =IF(Tabla5[[#This Row],[VALOR INVERSIÓN]]="","",IF(Tabla5[[#This Row],[VALOR INVERSIÓN]]<=10000000,100%*10%*22000,IF(AND(Tabla5[[#This Row],[VALOR INVERSIÓN]]>10000000,Tabla5[[#This Row],[VALOR INVERSIÓN]]<=20000000),60%*10%*22000,20%*10%*22000))) -> 2200 | O43: =IF(Tabla5[[#This Row],[ROI (MESES)]]="","",IF(Tabla5[[#This Row],[ROI (MESES)]]="N/A","0",IF(Tabla5[[#This Row],[ROI (MESES)]]="<=3",100%*10%*22000,IF(Tabla5[[#This Row],[ROI (MESES)]]=">3<=6",75%*10%*22000,25%*10%*22000)))) -> 2200 | P43: =IF(Tabla5[[#This Row],[FACILIDAD IMPLEM.]]="","",IF(Tabla5[[#This Row],[FACILIDAD IMPLEM.]]="A",100%*10%*22000,IF(AND(Tabla5[[#This Row],[FACILIDAD IMPLEM.]]="B"),50%*10%*22000,20%*10%*22000))) -> 2200 | Q43: =Tabla5[[#This Row],[IMPACTO AMBIENTAL (Máx. 25%)]]*70%*22000+Tabla5[[#This Row],[IMPACTO ECONÓMICO (Máx. 25%)]]*70%*22000+Tabla5[[#This Row],[IMPACTO SST (Máx. 20%)]]*70%*22000+Tabla5[[#This Row],[IMPACTO PRODUCTIVIDAD (Máx. 25%)]]*70%*22000+Tabla5[[#This Row],[IMPACTO ORDEN Y ASEO (Máx. 5%)]]*70%*22000 -> 2310 | R43: =IFERROR(Tabla5[[#This Row],[PUNTOS VALOR INVERSIÓN]]+Tabla5[[#This Row],[PUNTOS ROI ]]+Tabla5[[#This Row],[PUNTOS FACILIDAD IMPLEM. ]]+Tabla5[[#This Row],[PUNTOS IMPACTO ]],"") -> 8910 | T43: Técnica G1 | U43: Alta | V43: Implementar metodología QRQC (Control de calidad de respuesta rápida) | W43: Metodologia QRQC, coordinar con Jorge la socializacion de la metodologia a TH, producción, calidad, logistica, mantenimiento para definir si es indicado implementar otra metodologia mas | X43: Jorge Carvajal - Gustavo Ossa | Y43: Descartada
A44: 1040515524 | B44: Arnol Miguel Montiel Campos | C44: 6454 | D44: Producción | E44: Descartada | N44: =IF(Tabla5[[#This Row],[VALOR INVERSIÓN]]="","",IF(Tabla5[[#This Row],[VALOR INVERSIÓN]]<=10000000,100%*10%*22000,IF(AND(Tabla5[[#This Row],[VALOR INVERSIÓN]]>10000000,Tabla5[[#This Row],[VALOR INVERSIÓN]]<=20000000),60%*10%*22000,20%*10%*22000))) | O44: =IF(Tabla5[[#This Row],[ROI (MESES)]]="","",IF(Tabla5[[#This Row],[ROI (MESES)]]="N/A","0",IF(Tabla5[[#This Row],[ROI (MESES)]]="<=3",100%*10%*22000,IF(Tabla5[[#This Row],[ROI (MESES)]]=">3<=6",75%*10%*22000,25%*10%*22000)))) | P44: =IF(Tabla5[[#This Row],[FACILIDAD IMPLEM.]]="","",IF(Tabla5[[#This Row],[FACILIDAD IMPLEM.]]="A",100%*10%*22000,IF(AND(Tabla5[[#This Row],[FACILIDAD IMPLEM.]]="B"),50%*10%*22000,20%*10%*22000))) | Q44: =Tabla5[[#This Row],[IMPACTO AMBIENTAL (Máx. 25%)]]*70%*22000+Tabla5[[#This Row],[IMPACTO ECONÓMICO (Máx. 25%)]]*70%*22000+Tabla5[[#This Row],[IMPACTO SST (Máx. 20%)]]*70%*22000+Tabla5[[#This Row],[IMPACTO PRODUCTIVIDAD (Máx. 25%)]]*70%*22000+Tabla5[[#This Row],[IMPACTO ORDEN Y ASEO (Máx. 5%)]]*70%*22000 -> 0 | R44: =IFERROR(Tabla5[[#This Row],[PUNTOS VALOR INVERSIÓN]]+Tabla5[[#This Row],[PUNTOS ROI ]]+Tabla5[[#This Row],[PUNTOS FACILIDAD IMPLEM. ]]+Tabla5[[#This Row],[PUNTOS IMPACTO ]],"") | S44: 10/09/2024 Descartada.
A45: 1040515524 | B45: Arnol Miguel Montiel Campos | C45: 6455 | D45: Producción | E45: Descartada | N45: =IF(Tabla5[[#This Row],[VALOR INVERSIÓN]]="","",IF(Tabla5[[#This Row],[VALOR INVERSIÓN]]<=10000000,100%*10%*22000,IF(AND(Tabla5[[#This Row],[VALOR INVERSIÓN]]>10000000,Tabla5[[#This Row],[VALOR INVERSIÓN]]<=20000000),60%*10%*22000,20%*10%*22000))) | O45: =IF(Tabla5[[#This Row],[ROI (MESES)]]="","",IF(Tabla5[[#This Row],[ROI (MESES)]]="N/A","0",IF(Tabla5[[#This Row],[ROI (MESES)]]="<=3",100%*10%*22000,IF(Tabla5[[#This Row],[ROI (MESES)]]=">3<=6",75%*10%*22000,25%*10%*22000)))) | P45: =IF(Tabla5[[#This Row],[FACILIDAD IMPLEM.]]="","",IF(Tabla5[[#This Row],[FACILIDAD IMPLEM.]]="A",100%*10%*22000,IF(AND(Tabla5[[#This Row],[FACILIDAD IMPLEM.]]="B"),50%*10%*22000,20%*10%*22000))) | Q45: =Tabla5[[#This Row],[IMPACTO AMBIENTAL (Máx. 25%)]]*70%*22000+Tabla5[[#This Row],[IMPACTO ECONÓMICO (Máx. 25%)]]*70%*22000+Tabla5[[#This Row],[IMPACTO SST (Máx. 20%)]]*70%*22000+Tabla5[[#This Row],[IMPACTO PRODUCTIVIDAD (Máx. 25%)]]*70%*22000+Tabla5[[#This Row],[IMPACTO ORDEN Y ASEO (Máx. 5%)]]*70%*22000 -> 0 | R45: =IFERROR(Tabla5[[#This Row],[PUNTOS VALOR INVERSIÓN]]+Tabla5[[#This Row],[PUNTOS ROI ]]+Tabla5[[#This Row],[PUNTOS FACILIDAD IMPLEM. ]]+Tabla5[[#This Row],[PUNTOS IMPACTO ]],"") | S45: 10/09/2024 Descartada.
A46: 1128479264 | B46: Luis Carlos Ramos Rangel | C46: 6495 | D46: G.Técnica | E46: Descartada | N46: =IF(Tabla5[[#This Row],[VALOR INVERSIÓN]]="","",IF(Tabla5[[#This Row],[VALOR INVERSIÓN]]<=10000000,100%*10%*22000,IF(AND(Tabla5[[#This Row],[VALOR INVERSIÓN]]>10000000,Tabla5[[#This Row],[VALOR INVERSIÓN]]<=20000000),60%*10%*22000,20%*10%*22000))) | O46: =IF(Tabla5[[#This Row],[ROI (MESES)]]="","",IF(Tabla5[[#This Row],[ROI (MESES)]]="N/A","0",IF(Tabla5[[#This Row],[ROI (MESES)]]="<=3",100%*10%*22000,IF(Tabla5[[#This Row],[ROI (MESES)]]=">3<=6",75%*10%*22000,25%*10%*22000)))) | P46: =IF(Tabla5[[#This Row],[FACILIDAD IMPLEM.]]="","",IF(Tabla5[[#This Row],[FACILIDAD IMPLEM.]]="A",100%*10%*22000,IF(AND(Tabla5[[#This Row],[FACILIDAD IMPLEM.]]="B"),50%*10%*22000,20%*10%*22000))) | Q46: =Tabla5[[#This Row],[IMPACTO AMBIENTAL (Máx. 25%)]]*70%*22000+Tabla5[[#This Row],[IMPACTO ECONÓMICO (Máx. 25%)]]*70%*22000+Tabla5[[#This Row],[IMPACTO SST (Máx. 20%)]]*70%*22000+Tabla5[[#This Row],[IMPACTO PRODUCTIVIDAD (Máx. 25%)]]*70%*22000+Tabla5[[#This Row],[IMPACTO ORDEN Y ASEO (Máx. 5%)]]*70%*22000 -> 0 | R46: =IFERROR(Tabla5[[#This Row],[PUNTOS VALOR INVERSIÓN]]+Tabla5[[#This Row],[PUNTOS ROI ]]+Tabla5[[#This Row],[PUNTOS FACILIDAD IMPLEM. ]]+Tabla5[[#This Row],[PUNTOS IMPACTO ]],"") | S46: 10/09/2024 Descartada.
A47: 1110516748 | B47: Oscar Alveiro Forero Mogollón | C47: 6631 | D47: Mantenimiento | E47: Calificada | F47: 60000000 | G47: >6 | H47: B | I47: 0 | J47: 0 | K47: 0 | L47: 0 | M47: 0 | N47: =IF(Tabla5[[#This Row],[VALOR INVERSIÓN]]="","",IF(Tabla5[[#This Row],[VALOR INVERSIÓN]]<=10000000,100%*10%*22000,IF(AND(Tabla5[[#This Row],[VALOR INVERSIÓN]]>10000000,Tabla5[[#This Row],[VALOR INVERSIÓN]]<=20000000),60%*10%*22000,20%*10%*22000))) -> 440 | O47: =IF(Tabla5[[#This Row],[ROI (MESES)]]="","",IF(Tabla5[[#This Row],[ROI (MESES)]]="N/A","0",IF(Tabla5[[#This Row],[ROI (MESES)]]="<=3",100%*10%*22000,IF(Tabla5[[#This Row],[ROI (MESES)]]=">3<=6",75%*10%*22000,25%*10%*22000)))) -> 550 | P47: =IF(Tabla5[[#This Row],[FACILIDAD IMPLEM.]]="","",IF(Tabla5[[#This Row],[FACILIDAD IMPLEM.]]="A",100%*10%*22000,IF(AND(Tabla5[[#This Row],[FACILIDAD IMPLEM.]]="B"),50%*10%*22000,20%*10%*22000))) -> 1100 | Q47: =Tabla5[[#This Row],[IMPACTO AMBIENTAL (Máx. 25%)]]*70%*22000+Tabla5[[#This Row],[IMPACTO ECONÓMICO (Máx. 25%)]]*70%*22000+Tabla5[[#This Row],[IMPACTO SST (Máx. 20%)]]*70%*22000+Tabla5[[#This Row],[IMPACTO PRODUCTIVIDAD (Máx. 25%)]]*70%*22000+Tabla5[[#This Row],[IMPACTO ORDEN Y ASEO (Máx. 5%)]]*70%*22000 -> 0 | R47: =IFERROR(Tabla5[[#This Row],[PUNTOS VALOR INVERSIÓN]]+Tabla5[[#This Row],[PUNTOS ROI ]]+Tabla5[[#This Row],[PUNTOS FACILIDAD IMPLEM. ]]+Tabla5[[#This Row],[PUNTOS IMPACTO ]],"") -> 2090 | S47: 18/09/2024 Pendiente que Cristian Cardona valide paros por esta causa, costos de reparación y el costo de implementar la idea, para determinar el impacto económico. | T47: Técnica G2 | U47: No Viable | V47: Control inalambrico para diferenciales | W47: Tiende a desaparecer con proyecto HQ | Y47: Descartada
A48: 1110516748 | B48: Oscar Alveiro Forero Mogollón | C48: 6632 | D48: Mantenimiento | E48: Calificada | F48: 18000000 | G48: >6 | H48: A | I48: 0 | J48: 0.05 | K48: 0 | L48: 0 | M48: 0 | N48: =IF(Tabla5[[#This Row],[VALOR INVERSIÓN]]="","",IF(Tabla5[[#This Row],[VALOR INVERSIÓN]]<=10000000,100%*10%*22000,IF(AND(Tabla5[[#This Row],[VALOR INVERSIÓN]]>10000000,Tabla5[[#This Row],[VALOR INVERSIÓN]]<=20000000),60%*10%*22000,20%*10%*22000))) -> 1320 | O48: =IF(Tabla5[[#This Row],[ROI (MESES)]]="","",IF(Tabla5[[#This Row],[ROI (MESES)]]="N/A","0",IF(Tabla5[[#This Row],[ROI (MESES)]]="<=3",100%*10%*22000,IF(Tabla5[[#This Row],[ROI (MESES)]]=">3<=6",75%*10%*22000,25%*10%*22000)))) -> 550 | P48: =IF(Tabla5[[#This Row],[FACILIDAD IMPLEM.]]="","",IF(Tabla5[[#This Row],[FACILIDAD IMPLEM.]]="A",100%*10%*22000,IF(AND(Tabla5[[#This Row],[FACILIDAD IMPLEM.]]="B"),50%*10%*22000,20%*10%*22000))) -> 2200 | Q48: =Tabla5[[#This Row],[IMPACTO AMBIENTAL (Máx. 25%)]]*70%*22000+Tabla5[[#This Row],[IMPACTO ECONÓMICO (Máx. 25%)]]*70%*22000+Tabla5[[#This Row],[IMPACTO SST (Máx. 20%)]]*70%*22000+Tabla5[[#This Row],[IMPACTO PRODUCTIVIDAD (Máx. 25%)]]*70%*22000+Tabla5[[#This Row],[IMPACTO ORDEN Y ASEO (Máx. 5%)]]*70%*22000 -> 770 | R48: =IFERROR(Tabla5[[#This Row],[PUNTOS VALOR INVERSIÓN]]+Tabla5[[#This Row],[PUNTOS ROI ]]+Tabla5[[#This Row],[PUNTOS FACILIDAD IMPLEM. ]]+Tabla5[[#This Row],[PUNTOS IMPACTO ]],"") -> 4840 | S48: 18/09/2024 Pendiente que Cristian Cardona indague a Oscar sobre los beneficios que expone en la idea. | T48: Técnica G2 | U48: Media | V48: Sensores inductivos para máquinas de horno | W48: Ya se está implementando. | X48: Cristian Cardona | Y48: Implementada
A49: 98553008 | B49: Gustavo Adolfo Galeano Alvarez | C49: 6633 | D49: Mantenimiento | E49: Descartada | N49: =IF(Tabla5[[#This Row],[VALOR INVERSIÓN]]="","",IF(Tabla5[[#This Row],[VALOR INVERSIÓN]]<=10000000,100%*10%*22000,IF(AND(Tabla5[[#This Row],[VALOR INVERSIÓN]]>10000000,Tabla5[[#This Row],[VALOR INVERSIÓN]]<=20000000),60%*10%*22000,20%*10%*22000))) | O49: =IF(Tabla5[[#This Row],[ROI (MESES)]]="","",IF(Tabla5[[#This Row],[ROI (MESES)]]="N/A","0",IF(Tabla5[[#This Row],[ROI (MESES)]]="<=3",100%*10%*22000,IF(Tabla5[[#This Row],[ROI (MESES)]]=">3<=6",75%*10%*22000,25%*10%*22000)))) | P49: =IF(Tabla5[[#This Row],[FACILIDAD IMPLEM.]]="","",IF(Tabla5[[#This Row],[FACILIDAD IMPLEM.]]="A",100%*10%*22000,IF(AND(Tabla5[[#This Row],[FACILIDAD IMPLEM.]]="B"),50%*10%*22000,20%*10%*22000))) | Q49: =Tabla5[[#This Row],[IMPACTO AMBIENTAL (Máx. 25%)]]*70%*22000+Tabla5[[#This Row],[IMPACTO ECONÓMICO (Máx. 25%)]]*70%*22000+Tabla5[[#This Row],[IMPACTO SST (Máx. 20%)]]*70%*22000+Tabla5[[#This Row],[IMPACTO PRODUCTIVIDAD (Máx. 25%)]]*70%*22000+Tabla5[[#This Row],[IMPACTO ORDEN Y ASEO (Máx. 5%)]]*70%*22000 -> 0 | R49: =IFERROR(Tabla5[[#This Row],[PUNTOS VALOR INVERSIÓN]]+Tabla5[[#This Row],[PUNTOS ROI ]]+Tabla5[[#This Row],[PUNTOS FACILIDAD IMPLEM. ]]+Tabla5[[#This Row],[PUNTOS IMPACTO ]],"") | S49: 18/09/2024 Descartada.
A50: 1035918433 | B50: Mateo Arango Betancur | C50: 6696 | D50: Producción | E50: Descartada | N50: =IF(Tabla5[[#This Row],[VALOR INVERSIÓN]]="","",IF(Tabla5[[#This Row],[VALOR INVERSIÓN]]<=10000000,100%*10%*22000,IF(AND(Tabla5[[#This Row],[VALOR INVERSIÓN]]>10000000,Tabla5[[#This Row],[VALOR INVERSIÓN]]<=20000000),60%*10%*22000,20%*10%*22000))) | O50: =IF(Tabla5[[#This Row],[ROI (MESES)]]="","",IF(Tabla5[[#This Row],[ROI (MESES)]]="N/A","0",IF(Tabla5[[#This Row],[ROI (MESES)]]="<=3",100%*10%*22000,IF(Tabla5[[#This Row],[ROI (MESES)]]=">3<=6",75%*10%*22000,25%*10%*22000)))) | P50: =IF(Tabla5[[#This Row],[FACILIDAD IMPLEM.]]="","",IF(Tabla5[[#This Row],[FACILIDAD IMPLEM.]]="A",100%*10%*22000,IF(AND(Tabla5[[#This Row],[FACILIDAD IMPLEM.]]="B"),50%*10%*22000,20%*10%*22000))) | Q50: =Tabla5[[#This Row],[IMPACTO AMBIENTAL (Máx. 25%)]]*70%*22000+Tabla5[[#This Row],[IMPACTO ECONÓMICO (Máx. 25%)]]*70%*22000+Tabla5[[#This Row],[IMPACTO SST (Máx. 20%)]]*70%*22000+Tabla5[[#This Row],[IMPACTO PRODUCTIVIDAD (Máx. 25%)]]*70%*22000+Tabla5[[#This Row],[IMPACTO ORDEN Y ASEO (Máx. 5%)]]*70%*22000 -> 0 | R50: =IFERROR(Tabla5[[#This Row],[PUNTOS VALOR INVERSIÓN]]+Tabla5[[#This Row],[PUNTOS ROI ]]+Tabla5[[#This Row],[PUNTOS FACILIDAD IMPLEM. ]]+Tabla5[[#This Row],[PUNTOS IMPACTO ]],"") | S50: 18/09/2024 Descartada. No es viable la implementación del dispositivo en ese espacio de trabajo, afectaría a los procesos adyacentes, se necesitaría un encerramiento de la zona.
A51: 1040515524 | B51: Arnol Miguel Montiel Campos | C51: 6729 | D51: Producción | E51: Calificada | F51: 600000 | G51: >6 | H51: A | I51: 0 | J51: 0 | K51: 0 | L51: 0 | M51: 0 | N51: =IF(Tabla5[[#This Row],[VALOR INVERSIÓN]]="","",IF(Tabla5[[#This Row],[VALOR INVERSIÓN]]<=10000000,100%*10%*22000,IF(AND(Tabla5[[#This Row],[VALOR INVERSIÓN]]>10000000,Tabla5[[#This Row],[VALOR INVERSIÓN]]<=20000000),60%*10%*22000,20%*10%*22000))) -> 2200 | O51: =IF(Tabla5[[#This Row],[ROI (MESES)]]="","",IF(Tabla5[[#This Row],[ROI (MESES)]]="N/A","0",IF(Tabla5[[#This Row],[ROI (MESES)]]="<=3",100%*10%*22000,IF(Tabla5[[#This Row],[ROI (MESES)]]=">3<=6",75%*10%*22000,25%*10%*22000)))) -> 550 | P51: =IF(Tabla5[[#This Row],[FACILIDAD IMPLEM.]]="","",IF(Tabla5[[#This Row],[FACILIDAD IMPLEM.]]="A",100%*10%*22000,IF(AND(Tabla5[[#This Row],[FACILIDAD IMPLEM.]]="B"),50%*10%*22000,20%*10%*22000))) -> 2200 | Q51: =Tabla5[[#This Row],[IMPACTO AMBIENTAL (Máx. 25%)]]*70%*22000+Tabla5[[#This Row],[IMPACTO ECONÓMICO (Máx. 25%)]]*70%*22000+Tabla5[[#This Row],[IMPACTO SST (Máx. 20%)]]*70%*22000+Tabla5[[#This Row],[IMPACTO PRODUCTIVIDAD (Máx. 25%)]]*70%*22000+Tabla5[[#This Row],[IMPACTO ORDEN Y ASEO (Máx. 5%)]]*70%*22000 -> 0 | R51: =IFERROR(Tabla5[[#This Row],[PUNTOS VALOR INVERSIÓN]]+Tabla5[[#This Row],[PUNTOS ROI ]]+Tabla5[[#This Row],[PUNTOS FACILIDAD IMPLEM. ]]+Tabla5[[#This Row],[PUNTOS IMPACTO ]],"") -> 4950 | S51: 18/09/2024 Puntuada. | T51: Técnica G2 | U51: Baja | V51: Base movil para transporte de productos de mayor volumen | W51: Pendiente validar disponibilidad mantenimiento. | X51: Juan David Rojas | Y51: Implementada
A52: 1059704792 | B52: Jorge Eliecer Calderón Reyes | C52: 5917 | D52: G.Técnica | E52: Calificada | F52: 1000000 | G52: <=3 | H52: C | I52: 0.05 | J52: 0.09 | K52: 0 | L52: 0.06 | M52: 0 | N52: =IF(Tabla5[[#This Row],[VALOR INVERSIÓN]]="","",IF(Tabla5[[#This Row],[VALOR INVERSIÓN]]<=10000000,100%*10%*22000,IF(AND(Tabla5[[#This Row],[VALOR INVERSIÓN]]>10000000,Tabla5[[#This Row],[VALOR INVERSIÓN]]<=20000000),60%*10%*22000,20%*10%*22000))) -> 2200 | O52: =IF(Tabla5[[#This Row],[ROI (MESES)]]="","",IF(Tabla5[[#This Row],[ROI (MESES)]]="N/A","0",IF(Tabla5[[#This Row],[ROI (MESES)]]="<=3",100%*10%*22000,IF(Tabla5[[#This Row],[ROI (MESES)]]=">3<=6",75%*10%*22000,25%*10%*22000)))) -> 2200 | P52: =IF(Tabla5[[#This Row],[FACILIDAD IMPLEM.]]="","",IF(Tabla5[[#This Row],[FACILIDAD IMPLEM.]]="A",100%*10%*22000,IF(AND(Tabla5[[#This Row],[FACILIDAD IMPLEM.]]="B"),50%*10%*22000,20%*10%*22000))) -> 440 | Q52: =Tabla5[[#This Row],[IMPACTO AMBIENTAL (Máx. 25%)]]*70%*22000+Tabla5[[#This Row],[IMPACTO ECONÓMICO (Máx. 25%)]]*70%*22000+Tabla5[[#This Row],[IMPACTO SST (Máx. 20%)]]*70%*22000+Tabla5[[#This Row],[IMPACTO PRODUCTIVIDAD (Máx. 25%)]]*70%*22000+Tabla5[[#This Row],[IMPACTO ORDEN Y ASEO (Máx. 5%)]]*70%*22000 -> 3080 | R52: =IFERROR(Tabla5[[#This Row],[PUNTOS VALOR INVERSIÓN]]+Tabla5[[#This Row],[PUNTOS ROI ]]+Tabla5[[#This Row],[PUNTOS FACILIDAD IMPLEM. ]]+Tabla5[[#This Row],[PUNTOS IMPACTO ]],"") -> 7920 | S52: 14/08/2024 Puntuada | T52: Técnica G1 | U52: Alta | V52: Bitácora de materias primas para flama | W52: Bitacora de materias primas, reunión producción tecnica y calidad para diseñar la tabla. | X52: Jhon Rendón - Sebastián Ossa - Jhony Tuberquia | Y52: En proceso
A53: 1036394175 | B53: Wilson Fernando Ramirez Zuluaga | C53: 6770 | D53: Producción | E53: Descartada | N53: =IF(Tabla5[[#This Row],[VALOR INVERSIÓN]]="","",IF(Tabla5[[#This Row],[VALOR INVERSIÓN]]<=10000000,100%*10%*22000,IF(AND(Tabla5[[#This Row],[VALOR INVERSIÓN]]>10000000,Tabla5[[#This Row],[VALOR INVERSIÓN]]<=20000000),60%*10%*22000,20%*10%*22000))) | O53: =IF(Tabla5[[#This Row],[ROI (MESES)]]="","",IF(Tabla5[[#This Row],[ROI (MESES)]]="N/A","0",IF(Tabla5[[#This Row],[ROI (MESES)]]="<=3",100%*10%*22000,IF(Tabla5[[#This Row],[ROI (MESES)]]=">3<=6",75%*10%*22000,25%*10%*22000)))) | P53: =IF(Tabla5[[#This Row],[FACILIDAD IMPLEM.]]="","",IF(Tabla5[[#This Row],[FACILIDAD IMPLEM.]]="A",100%*10%*22000,IF(AND(Tabla5[[#This Row],[FACILIDAD IMPLEM.]]="B"),50%*10%*22000,20%*10%*22000))) | Q53: =Tabla5[[#This Row],[IMPACTO AMBIENTAL (Máx. 25%)]]*70%*22000+Tabla5[[#This Row],[IMPACTO ECONÓMICO (Máx. 25%)]]*70%*22000+Tabla5[[#This Row],[IMPACTO SST (Máx. 20%)]]*70%*22000+Tabla5[[#This Row],[IMPACTO PRODUCTIVIDAD (Máx. 25%)]]*70%*22000+Tabla5[[#This Row],[IMPACTO ORDEN Y ASEO (Máx. 5%)]]*70%*22000 -> 0 | R53: =IFERROR(Tabla5[[#This Row],[PUNTOS VALOR INVERSIÓN]]+Tabla5[[#This Row],[PUNTOS ROI ]]+Tabla5[[#This Row],[PUNTOS FACILIDAD IMPLEM. ]]+Tabla5[[#This Row],[PUNTOS IMPACTO ]],"") | S53: 18/09/2024 Pendiente que Cristian Cardona valide con el operario la necesidad y funcionalidad de la idea propuesta.
A54: 4116903 | B54: Luis Eduardo Perdomo Rojas | C54: 6826 | D54: Producción | E54: Descartada | N54: =IF(Tabla5[[#This Row],[VALOR INVERSIÓN]]="","",IF(Tabla5[[#This Row],[VALOR INVERSIÓN]]<=10000000,100%*10%*22000,IF(AND(Tabla5[[#This Row],[VALOR INVERSIÓN]]>10000000,Tabla5[[#This Row],[VALOR INVERSIÓN]]<=20000000),60%*10%*22000,20%*10%*22000))) | O54: =IF(Tabla5[[#This Row],[ROI (MESES)]]="","",IF(Tabla5[[#This Row],[ROI (MESES)]]="N/A","0",IF(Tabla5[[#This Row],[ROI (MESES)]]="<=3",100%*10%*22000,IF(Tabla5[[#This Row],[ROI (MESES)]]=">3<=6",75%*10%*22000,25%*10%*22000)))) | P54: =IF(Tabla5[[#This Row],[FACILIDAD IMPLEM.]]="","",IF(Tabla5[[#This Row],[FACILIDAD IMPLEM.]]="A",100%*10%*22000,IF(AND(Tabla5[[#This Row],[FACILIDAD IMPLEM.]]="B"),50%*10%*22000,20%*10%*22000))) | Q54: =Tabla5[[#This Row],[IMPACTO AMBIENTAL (Máx. 25%)]]*70%*22000+Tabla5[[#This Row],[IMPACTO ECONÓMICO (Máx. 25%)]]*70%*22000+Tabla5[[#This Row],[IMPACTO SST (Máx. 20%)]]*70%*22000+Tabla5[[#This Row],[IMPACTO PRODUCTIVIDAD (Máx. 25%)]]*70%*22000+Tabla5[[#This Row],[IMPACTO ORDEN Y ASEO (Máx. 5%)]]*70%*22000 -> 0 | R54: =IFERROR(Tabla5[[#This Row],[PUNTOS VALOR INVERSIÓN]]+Tabla5[[#This Row],[PUNTOS ROI ]]+Tabla5[[#This Row],[PUNTOS FACILIDAD IMPLEM. ]]+Tabla5[[#This Row],[PUNTOS IMPACTO ]],"") | S54: 24/09/2024 Descartada. La idea ya había sido presentada por otro colaborador con radicado #6769
A55: 1128479264 | B55: Luis Carlos Ramos Rangel | C55: 7323 | D55: G.Técnica | E55: Calificada | F55: 1000000 | G55: <=3 | H55: A | I55: 0 | J55: 0.08 | K55: 0 | L55: 0 | M55: 0 | N55: =IF(Tabla5[[#This Row],[VALOR INVERSIÓN]]="","",IF(Tabla5[[#This Row],[VALOR INVERSIÓN]]<=10000000,100%*10%*22000,IF(AND(Tabla5[[#This Row],[VALOR INVERSIÓN]]>10000000,Tabla5[[#This Row],[VALOR INVERSIÓN]]<=20000000),60%*10%*22000,20%*10%*22000))) -> 2200 | O55: =IF(Tabla5[[#This Row],[ROI (MESES)]]="","",IF(Tabla5[[#This Row],[ROI (MESES)]]="N/A","0",IF(Tabla5[[#This Row],[ROI (MESES)]]="<=3",100%*10%*22000,IF(Tabla5[[#This Row],[ROI (MESES)]]=">3<=6",75%*10%*22000,25%*10%*22000)))) -> 2200 | P55: =IF(Tabla5[[#This Row],[FACILIDAD IMPLEM.]]="","",IF(Tabla5[[#This Row],[FACILIDAD IMPLEM.]]="A",100%*10%*22000,IF(AND(Tabla5[[#This Row],[FACILIDAD IMPLEM.]]="B"),50%*10%*22000,20%*10%*22000))) -> 2200 | Q55: =Tabla5[[#This Row],[IMPACTO AMBIENTAL (Máx. 25%)]]*70%*22000+Tabla5[[#This Row],[IMPACTO ECONÓMICO (Máx. 25%)]]*70%*22000+Tabla5[[#This Row],[IMPACTO SST (Máx. 20%)]]*70%*22000+Tabla5[[#This Row],[IMPACTO PRODUCTIVIDAD (Máx. 25%)]]*70%*22000+Tabla5[[#This Row],[IMPACTO ORDEN Y ASEO (Máx. 5%)]]*70%*22000 -> 1232 | R55: =IFERROR(Tabla5[[#This Row],[PUNTOS VALOR INVERSIÓN]]+Tabla5[[#This Row],[PUNTOS ROI ]]+Tabla5[[#This Row],[PUNTOS FACILIDAD IMPLEM. ]]+Tabla5[[#This Row],[PUNTOS IMPACTO ]],"") -> 7832 | T55: Técnica G1 | U55: Alta | V55: Colocar una tobera auxiliar | W55: Que produccion determine si es en todos los tapones o en algunas referencias y cuando este Id, hablar con Luis Ramos (JJ Rendon) , validar si en la prueba estaba el molde sucio o limpio. | X55: Jhon Rendón - Sebastián Ossa | Y55: Implementada
A56: 1128479264 | B56: Luis Carlos Ramos Rangel | C56: 7324 | D56: G.Técnica | E56: Descartada | N56: =IF(Tabla5[[#This Row],[VALOR INVERSIÓN]]="","",IF(Tabla5[[#This Row],[VALOR INVERSIÓN]]<=10000000,100%*10%*22000,IF(AND(Tabla5[[#This Row],[VALOR INVERSIÓN]]>10000000,Tabla5[[#This Row],[VALOR INVERSIÓN]]<=20000000),60%*10%*22000,20%*10%*22000))) | O56: =IF(Tabla5[[#This Row],[ROI (MESES)]]="","",IF(Tabla5[[#This Row],[ROI (MESES)]]="N/A","0",IF(Tabla5[[#This Row],[ROI (MESES)]]="<=3",100%*10%*22000,IF(Tabla5[[#This Row],[ROI (MESES)]]=">3<=6",75%*10%*22000,25%*10%*22000)))) | P56: =IF(Tabla5[[#This Row],[FACILIDAD IMPLEM.]]="","",IF(Tabla5[[#This Row],[FACILIDAD IMPLEM.]]="A",100%*10%*22000,IF(AND(Tabla5[[#This Row],[FACILIDAD IMPLEM.]]="B"),50%*10%*22000,20%*10%*22000))) | Q56: =Tabla5[[#This Row],[IMPACTO AMBIENTAL (Máx. 25%)]]*70%*22000+Tabla5[[#This Row],[IMPACTO ECONÓMICO (Máx. 25%)]]*70%*22000+Tabla5[[#This Row],[IMPACTO SST (Máx. 20%)]]*70%*22000+Tabla5[[#This Row],[IMPACTO PRODUCTIVIDAD (Máx. 25%)]]*70%*22000+Tabla5[[#This Row],[IMPACTO ORDEN Y ASEO (Máx. 5%)]]*70%*22000 -> 0 | R56: =IFERROR(Tabla5[[#This Row],[PUNTOS VALOR INVERSIÓN]]+Tabla5[[#This Row],[PUNTOS ROI ]]+Tabla5[[#This Row],[PUNTOS FACILIDAD IMPLEM. ]]+Tabla5[[#This Row],[PUNTOS IMPACTO ]],"")
A57: 1020104155 | B57: Julián Yafeth Hernandez Montes | C57: 7325 | D57: Producción | E57: Calificada | F57: 50000000 | G57: >6 | H57: B | I57: 0 | J57: 0.03 | K57: 0 | L57: 0 | M57: 0.03 | N57: =IF(Tabla5[[#This Row],[VALOR INVERSIÓN]]="","",IF(Tabla5[[#This Row],[VALOR INVERSIÓN]]<=10000000,100%*10%*22000,IF(AND(Tabla5[[#This Row],[VALOR INVERSIÓN]]>10000000,Tabla5[[#This Row],[VALOR INVERSIÓN]]<=20000000),60%*10%*22000,20%*10%*22000))) -> 440 | O57: =IF(Tabla5[[#This Row],[ROI (MESES)]]="","",IF(Tabla5[[#This Row],[ROI (MESES)]]="N/A","0",IF(Tabla5[[#This Row],[ROI (MESES)]]="<=3",100%*10%*22000,IF(Tabla5[[#This Row],[ROI (MESES)]]=">3<=6",75%*10%*22000,25%*10%*22000)))) -> 550 | P57: =IF(Tabla5[[#This Row],[FACILIDAD IMPLEM.]]="","",IF(Tabla5[[#This Row],[FACILIDAD IMPLEM.]]="A",100%*10%*22000,IF(AND(Tabla5[[#This Row],[FACILIDAD IMPLEM.]]="B"),50%*10%*22000,20%*10%*22000))) -> 1100 | Q57: =Tabla5[[#This Row],[IMPACTO AMBIENTAL (Máx. 25%)]]*70%*22000+Tabla5[[#This Row],[IMPACTO ECONÓMICO (Máx. 25%)]]*70%*22000+Tabla5[[#This Row],[IMPACTO SST (Máx. 20%)]]*70%*22000+Tabla5[[#This Row],[IMPACTO PRODUCTIVIDAD (Máx. 25%)]]*70%*22000+Tabla5[[#This Row],[IMPACTO ORDEN Y ASEO (Máx. 5%)]]*70%*22000 -> 924 | R57: =IFERROR(Tabla5[[#This Row],[PUNTOS VALOR INVERSIÓN]]+Tabla5[[#This Row],[PUNTOS ROI ]]+Tabla5[[#This Row],[PUNTOS FACILIDAD IMPLEM. ]]+Tabla5[[#This Row],[PUNTOS IMPACTO ]],"") -> 3014 | T57: Técnica G2 | U57: No Viable | V57: Almacenar repigmentado en silo | W57: No presta adecuada función por el espacio y las condicones de cargue y descargue | Y57: Descartada
A58: 1128479796 | B58: Juan Guillermo Bedoya | C58: 7326 | D58: Producción | E58: Calificada | F58: 50000000 | G58: >6 | H58: B | I58: 0 | J58: 0 | K58: 0.15 | L58: 0 | M58: 0 | N58: =IF(Tabla5[[#This Row],[VALOR INVERSIÓN]]="","",IF(Tabla5[[#This Row],[VALOR INVERSIÓN]]<=10000000,100%*10%*22000,IF(AND(Tabla5[[#This Row],[VALOR INVERSIÓN]]>10000000,Tabla5[[#This Row],[VALOR INVERSIÓN]]<=20000000),60%*10%*22000,20%*10%*22000))) -> 440 | O58: =IF(Tabla5[[#This Row],[ROI (MESES)]]="","",IF(Tabla5[[#This Row],[ROI (MESES)]]="N/A","0",IF(Tabla5[[#This Row],[ROI (MESES)]]="<=3",100%*10%*22000,IF(Tabla5[[#This Row],[ROI (MESES)]]=">3<=6",75%*10%*22000,25%*10%*22000)))) -> 550 | P58: =IF(Tabla5[[#This Row],[FACILIDAD IMPLEM.]]="","",IF(Tabla5[[#This Row],[FACILIDAD IMPLEM.]]="A",100%*10%*22000,IF(AND(Tabla5[[#This Row],[FACILIDAD IMPLEM.]]="B"),50%*10%*22000,20%*10%*22000))) -> 1100 | Q58: =Tabla5[[#This Row],[IMPACTO AMBIENTAL (Máx. 25%)]]*70%*22000+Tabla5[[#This Row],[IMPACTO ECONÓMICO (Máx. 25%)]]*70%*22000+Tabla5[[#This Row],[IMPACTO SST (Máx. 20%)]]*70%*22000+Tabla5[[#This Row],[IMPACTO PRODUCTIVIDAD (Máx. 25%)]]*70%*22000+Tabla5[[#This Row],[IMPACTO ORDEN Y ASEO (Máx. 5%)]]*70%*22000 -> 2310 | R58: =IFERROR(Tabla5[[#This Row],[PUNTOS VALOR INVERSIÓN]]+Tabla5[[#This Row],[PUNTOS ROI ]]+Tabla5[[#This Row],[PUNTOS FACILIDAD IMPLEM. ]]+Tabla5[[#This Row],[PUNTOS IMPACTO ]],"") -> 4400 | T58: Técnica G2 | U58: No Viable | V58: Sensores de movimiento en máquinas de flama | W58: Proyecto HQ mitiga esos riesgos, adicional a las máquinas se les instalaron guardas. | Y58: Descartada
A59: 1065659658 | B59: Roberto Carlos Rodríguez | C59: 6399 | D59: Producción | E59: Calificada | F59: 1000000 | G59: <=3 | H59: B | I59: 0.14 | J59: 0.1 | K59: 0 | L59: 0 | M59: 0 | N59: =IF(Tabla5[[#This Row],[VALOR INVERSIÓN]]="","",IF(Tabla5[[#This Row],[VALOR INVERSIÓN]]<=10000000,100%*10%*22000,IF(AND(Tabla5[[#This Row],[VALOR INVERSIÓN]]>10000000,Tabla5[[#This Row],[VALOR INVERSIÓN]]<=20000000),60%*10%*22000,20%*10%*22000))) -> 2200 | O59: =IF(Tabla5[[#This Row],[ROI (MESES)]]="","",IF(Tabla5[[#This Row],[ROI (MESES)]]="N/A","0",IF(Tabla5[[#This Row],[ROI (MESES)]]="<=3",100%*10%*22000,IF(Tabla5[[#This Row],[ROI (MESES)]]=">3<=6",75%*10%*22000,25%*10%*22000)))) -> 2200 | P59: =IF(Tabla5[[#This Row],[FACILIDAD IMPLEM.]]="","",IF(Tabla5[[#This Row],[FACILIDAD IMPLEM.]]="A",100%*10%*22000,IF(AND(Tabla5[[#This Row],[FACILIDAD IMPLEM.]]="B"),50%*10%*22000,20%*10%*22000))) -> 1100 | Q59: =Tabla5[[#This Row],[IMPACTO AMBIENTAL (Máx. 25%)]]*70%*22000+Tabla5[[#This Row],[IMPACTO ECONÓMICO (Máx. 25%)]]*70%*22000+Tabla5[[#This Row],[IMPACTO SST (Máx. 20%)]]*70%*22000+Tabla5[[#This Row],[IMPACTO PRODUCTIVIDAD (Máx. 25%)]]*70%*22000+Tabla5[[#This Row],[IMPACTO ORDEN Y ASEO (Máx. 5%)]]*70%*22000 -> 3696 | R59: =IFERROR(Tabla5[[#This Row],[PUNTOS VALOR INVERSIÓN]]+Tabla5[[#This Row],[PUNTOS ROI ]]+Tabla5[[#This Row],[PUNTOS FACILIDAD IMPLEM. ]]+Tabla5[[#This Row],[PUNTOS IMPACTO ]],"") -> 9196 | S59: 03/09/2924 No se alcanzó a evaluar. 10/09/2024 Puntuada | T59: Técnica G1 | U59: Alta | V59: Reutilización de estopa | W59: Ya se implemento el ecouso, pendiente resultado de analisis de reduccion de costos | X59: Gustavo Ossa - Julián Giraldo | Y59: En proceso
A60: 1001415647 | B60: Wilder Duvan Atehortua Iral | C60: 7426 | D60: Producción | E60: Descartada | N60: =IF(Tabla5[[#This Row],[VALOR INVERSIÓN]]="","",IF(Tabla5[[#This Row],[VALOR INVERSIÓN]]<=10000000,100%*10%*22000,IF(AND(Tabla5[[#This Row],[VALOR INVERSIÓN]]>10000000,Tabla5[[#This Row],[VALOR INVERSIÓN]]<=20000000),60%*10%*22000,20%*10%*22000))) | O60: =IF(Tabla5[[#This Row],[ROI (MESES)]]="","",IF(Tabla5[[#This Row],[ROI (MESES)]]="N/A","0",IF(Tabla5[[#This Row],[ROI (MESES)]]="<=3",100%*10%*22000,IF(Tabla5[[#This Row],[ROI (MESES)]]=">3<=6",75%*10%*22000,25%*10%*22000)))) | P60: =IF(Tabla5[[#This Row],[FACILIDAD IMPLEM.]]="","",IF(Tabla5[[#This Row],[FACILIDAD IMPLEM.]]="A",100%*10%*22000,IF(AND(Tabla5[[#This Row],[FACILIDAD IMPLEM.]]="B"),50%*10%*22000,20%*10%*22000))) | Q60: =Tabla5[[#This Row],[IMPACTO AMBIENTAL (Máx. 25%)]]*70%*22000+Tabla5[[#This Row],[IMPACTO ECONÓMICO (Máx. 25%)]]*70%*22000+Tabla5[[#This Row],[IMPACTO SST (Máx. 20%)]]*70%*22000+Tabla5[[#This Row],[IMPACTO PRODUCTIVIDAD (Máx. 25%)]]*70%*22000+Tabla5[[#This Row],[IMPACTO ORDEN Y ASEO (Máx. 5%)]]*70%*22000 -> 0 | R60: =IFERROR(Tabla5[[#This Row],[PUNTOS VALOR INVERSIÓN]]+Tabla5[[#This Row],[PUNTOS ROI ]]+Tabla5[[#This Row],[PUNTOS FACILIDAD IMPLEM. ]]+Tabla5[[#This Row],[PUNTOS IMPACTO ]],"") | S60: Ya se habia presentado por otro colaborador
A61: 1001415647 | B61: Wilder Duvan Atehortua Iral | C61: 7427 | D61: Producción | E61: Descartada | N61: =IF(Tabla5[[#This Row],[VALOR INVERSIÓN]]="","",IF(Tabla5[[#This Row],[VALOR INVERSIÓN]]<=10000000,100%*10%*22000,IF(AND(Tabla5[[#This Row],[VALOR INVERSIÓN]]>10000000,Tabla5[[#This Row],[VALOR INVERSIÓN]]<=20000000),60%*10%*22000,20%*10%*22000))) | O61: =IF(Tabla5[[#This Row],[ROI (MESES)]]="","",IF(Tabla5[[#This Row],[ROI (MESES)]]="N/A","0",IF(Tabla5[[#This Row],[ROI (MESES)]]="<=3",100%*10%*22000,IF(Tabla5[[#This Row],[ROI (MESES)]]=">3<=6",75%*10%*22000,25%*10%*22000)))) | P61: =IF(Tabla5[[#This Row],[FACILIDAD IMPLEM.]]="","",IF(Tabla5[[#This Row],[FACILIDAD IMPLEM.]]="A",100%*10%*22000,IF(AND(Tabla5[[#This Row],[FACILIDAD IMPLEM.]]="B"),50%*10%*22000,20%*10%*22000))) | Q61: =Tabla5[[#This Row],[IMPACTO AMBIENTAL (Máx. 25%)]]*70%*22000+Tabla5[[#This Row],[IMPACTO ECONÓMICO (Máx. 25%)]]*70%*22000+Tabla5[[#This Row],[IMPACTO SST (Máx. 20%)]]*70%*22000+Tabla5[[#This Row],[IMPACTO PRODUCTIVIDAD (Máx. 25%)]]*70%*22000+Tabla5[[#This Row],[IMPACTO ORDEN Y ASEO (Máx. 5%)]]*70%*22000 -> 0 | R61: =IFERROR(Tabla5[[#This Row],[PUNTOS VALOR INVERSIÓN]]+Tabla5[[#This Row],[PUNTOS ROI ]]+Tabla5[[#This Row],[PUNTOS FACILIDAD IMPLEM. ]]+Tabla5[[#This Row],[PUNTOS IMPACTO ]],"")
A62: 1015276535 | B62: Esteban Sánchez Montoya | C62: 7428 | D62: TI | E62: Calificada | F62: 6000000 | G62: >6 | H62: A | I62: 0 | J62: 0 | K62: 0 | L62: 0 | M62: 0 | N62: =IF(Tabla5[[#This Row],[VALOR INVERSIÓN]]="","",IF(Tabla5[[#This Row],[VALOR INVERSIÓN]]<=10000000,100%*10%*22000,IF(AND(Tabla5[[#This Row],[VALOR INVERSIÓN]]>10000000,Tabla5[[#This Row],[VALOR INVERSIÓN]]<=20000000),60%*10%*22000,20%*10%*22000))) -> 2200 | O62: =IF(Tabla5[[#This Row],[ROI (MESES)]]="","",IF(Tabla5[[#This Row],[ROI (MESES)]]="N/A","0",IF(Tabla5[[#This Row],[ROI (MESES)]]="<=3",100%*10%*22000,IF(Tabla5[[#This Row],[ROI (MESES)]]=">3<=6",75%*10%*22000,25%*10%*22000)))) -> 550 | P62: =IF(Tabla5[[#This Row],[FACILIDAD IMPLEM.]]="","",IF(Tabla5[[#This Row],[FACILIDAD IMPLEM.]]="A",100%*10%*22000,IF(AND(Tabla5[[#This Row],[FACILIDAD IMPLEM.]]="B"),50%*10%*22000,20%*10%*22000))) -> 2200 | Q62: =Tabla5[[#This Row],[IMPACTO AMBIENTAL (Máx. 25%)]]*70%*22000+Tabla5[[#This Row],[IMPACTO ECONÓMICO (Máx. 25%)]]*70%*22000+Tabla5[[#This Row],[IMPACTO SST (Máx. 20%)]]*70%*22000+Tabla5[[#This Row],[IMPACTO PRODUCTIVIDAD (Máx. 25%)]]*70%*22000+Tabla5[[#This Row],[IMPACTO ORDEN Y ASEO (Máx. 5%)]]*70%*22000 -> 0 | R62: =IFERROR(Tabla5[[#This Row],[PUNTOS VALOR INVERSIÓN]]+Tabla5[[#This Row],[PUNTOS ROI ]]+Tabla5[[#This Row],[PUNTOS FACILIDAD IMPLEM. ]]+Tabla5[[#This Row],[PUNTOS IMPACTO ]],"") -> 4950 | T62: Comercial | U62: No Viable | V62: Impresora 3D | Y62: Descartada
A63: 1015276535 | B63: Esteban Sánchez Montoya | C63: 7429 | D63: TI | E63: Descartada | N63: =IF(Tabla5[[#This Row],[VALOR INVERSIÓN]]="","",IF(Tabla5[[#This Row],[VALOR INVERSIÓN]]<=10000000,100%*10%*22000,IF(AND(Tabla5[[#This Row],[VALOR INVERSIÓN]]>10000000,Tabla5[[#This Row],[VALOR INVERSIÓN]]<=20000000),60%*10%*22000,20%*10%*22000))) | O63: =IF(Tabla5[[#This Row],[ROI (MESES)]]="","",IF(Tabla5[[#This Row],[ROI (MESES)]]="N/A","0",IF(Tabla5[[#This Row],[ROI (MESES)]]="<=3",100%*10%*22000,IF(Tabla5[[#This Row],[ROI (MESES)]]=">3<=6",75%*10%*22000,25%*10%*22000)))) | P63: =IF(Tabla5[[#This Row],[FACILIDAD IMPLEM.]]="","",IF(Tabla5[[#This Row],[FACILIDAD IMPLEM.]]="A",100%*10%*22000,IF(AND(Tabla5[[#This Row],[FACILIDAD IMPLEM.]]="B"),50%*10%*22000,20%*10%*22000))) | Q63: =Tabla5[[#This Row],[IMPACTO AMBIENTAL (Máx. 25%)]]*70%*22000+Tabla5[[#This Row],[IMPACTO ECONÓMICO (Máx. 25%)]]*70%*22000+Tabla5[[#This Row],[IMPACTO SST (Máx. 20%)]]*70%*22000+Tabla5[[#This Row],[IMPACTO PRODUCTIVIDAD (Máx. 25%)]]*70%*22000+Tabla5[[#This Row],[IMPACTO ORDEN Y ASEO (Máx. 5%)]]*70%*22000 -> 0 | R63: =IFERROR(Tabla5[[#This Row],[PUNTOS VALOR INVERSIÓN]]+Tabla5[[#This Row],[PUNTOS ROI ]]+Tabla5[[#This Row],[PUNTOS FACILIDAD IMPLEM. ]]+Tabla5[[#This Row],[PUNTOS IMPACTO ]],"")
A64: 1065659658 | B64: Roberto Carlos Rodríguez | C64: 7430 | D64: Producción | E64: Descartada | N64: =IF(Tabla5[[#This Row],[VALOR INVERSIÓN]]="","",IF(Tabla5[[#This Row],[VALOR INVERSIÓN]]<=10000000,100%*10%*22000,IF(AND(Tabla5[[#This Row],[VALOR INVERSIÓN]]>10000000,Tabla5[[#This Row],[VALOR INVERSIÓN]]<=20000000),60%*10%*22000,20%*10%*22000))) | O64: =IF(Tabla5[[#This Row],[ROI (MESES)]]="","",IF(Tabla5[[#This Row],[ROI (MESES)]]="N/A","0",IF(Tabla5[[#This Row],[ROI (MESES)]]="<=3",100%*10%*22000,IF(Tabla5[[#This Row],[ROI (MESES)]]=">3<=6",75%*10%*22000,25%*10%*22000)))) | P64: =IF(Tabla5[[#This Row],[FACILIDAD IMPLEM.]]="","",IF(Tabla5[[#This Row],[FACILIDAD IMPLEM.]]="A",100%*10%*22000,IF(AND(Tabla5[[#This Row],[FACILIDAD IMPLEM.]]="B"),50%*10%*22000,20%*10%*22000))) | Q64: =Tabla5[[#This Row],[IMPACTO AMBIENTAL (Máx. 25%)]]*70%*22000+Tabla5[[#This Row],[IMPACTO ECONÓMICO (Máx. 25%)]]*70%*22000+Tabla5[[#This Row],[IMPACTO SST (Máx. 20%)]]*70%*22000+Tabla5[[#This Row],[IMPACTO PRODUCTIVIDAD (Máx. 25%)]]*70%*22000+Tabla5[[#This Row],[IMPACTO ORDEN Y ASEO (Máx. 5%)]]*70%*22000 -> 0 | R64: =IFERROR(Tabla5[[#This Row],[PUNTOS VALOR INVERSIÓN]]+Tabla5[[#This Row],[PUNTOS ROI ]]+Tabla5[[#This Row],[PUNTOS FACILIDAD IMPLEM. ]]+Tabla5[[#This Row],[PUNTOS IMPACTO ]],"")
A65: 71801338 | B65: Edwin Yobany Valbuena Monsalve | C65: 7431 | D65: Producción | E65: Calificada | F65: 100000000 | G65: >6 | H65: B | I65: 0 | J65: 0 | K65: 0.07 | L65: 0 | M65: 0.03 | N65: =IF(Tabla5[[#This Row],[VALOR INVERSIÓN]]="","",IF(Tabla5[[#This Row],[VALOR INVERSIÓN]]<=10000000,100%*10%*22000,IF(AND(Tabla5[[#This Row],[VALOR INVERSIÓN]]>10000000,Tabla5[[#This Row],[VALOR INVERSIÓN]]<=20000000),60%*10%*22000,20%*10%*22000))) -> 440 | O65: =IF(Tabla5[[#This Row],[ROI (MESES)]]="","",IF(Tabla5[[#This Row],[ROI (MESES)]]="N/A","0",IF(Tabla5[[#This Row],[ROI (MESES)]]="<=3",100%*10%*22000,IF(Tabla5[[#This Row],[ROI (MESES)]]=">3<=6",75%*10%*22000,25%*10%*22000)))) -> 550 | P65: =IF(Tabla5[[#This Row],[FACILIDAD IMPLEM.]]="","",IF(Tabla5[[#This Row],[FACILIDAD IMPLEM.]]="A",100%*10%*22000,IF(AND(Tabla5[[#This Row],[FACILIDAD IMPLEM.]]="B"),50%*10%*22000,20%*10%*22000))) -> 1100 | Q65: =Tabla5[[#This Row],[IMPACTO AMBIENTAL (Máx. 25%)]]*70%*22000+Tabla5[[#This Row],[IMPACTO ECONÓMICO (Máx. 25%)]]*70%*22000+Tabla5[[#This Row],[IMPACTO SST (Máx. 20%)]]*70%*22000+Tabla5[[#This Row],[IMPACTO PRODUCTIVIDAD (Máx. 25%)]]*70%*22000+Tabla5[[#This Row],[IMPACTO ORDEN Y ASEO (Máx. 5%)]]*70%*22000 -> 1540 | R65: =IFERROR(Tabla5[[#This Row],[PUNTOS VALOR INVERSIÓN]]+Tabla5[[#This Row],[PUNTOS ROI ]]+Tabla5[[#This Row],[PUNTOS FACILIDAD IMPLEM. ]]+Tabla5[[#This Row],[PUNTOS IMPACTO ]],"") -> 3630 | T65: Comercial | U65: No Viable | V65: Mezanine en zona de materia prima | W65: La idea esta en proceso con el objetivo de acondicionar materias primas y moldes para lograr una logistica adecuada con la nueva pulverizadora. Se considera no viable ya que se hará uso de estanterías para ordenar el área | Y65: Descartada
A66: 1127940223 | B66: Carlos Eduardo Gonzalez Alvarado | C66: 7451 | D66: TI | E66: Calificada | F66: 50000000 | G66: >6 | H66: B | I66: 0.12 | J66: 0.05 | K66: 0 | L66: 0 | M66: 0.02 | N66: =IF(Tabla5[[#This Row],[VALOR INVERSIÓN]]="","",IF(Tabla5[[#This Row],[VALOR INVERSIÓN]]<=10000000,100%*10%*22000,IF(AND(Tabla5[[#This Row],[VALOR INVERSIÓN]]>10000000,Tabla5[[#This Row],[VALOR INVERSIÓN]]<=20000000),60%*10%*22000,20%*10%*22000))) -> 440 | O66: =IF(Tabla5[[#This Row],[ROI (MESES)]]="","",IF(Tabla5[[#This Row],[ROI (MESES)]]="N/A","0",IF(Tabla5[[#This Row],[ROI (MESES)]]="<=3",100%*10%*22000,IF(Tabla5[[#This Row],[ROI (MESES)]]=">3<=6",75%*10%*22000,25%*10%*22000)))) -> 550 | P66: =IF(Tabla5[[#This Row],[FACILIDAD IMPLEM.]]="","",IF(Tabla5[[#This Row],[FACILIDAD IMPLEM.]]="A",100%*10%*22000,IF(AND(Tabla5[[#This Row],[FACILIDAD IMPLEM.]]="B"),50%*10%*22000,20%*10%*22000))) -> 1100 | Q66: =Tabla5[[#This Row],[IMPACTO AMBIENTAL (Máx. 25%)]]*70%*22000+Tabla5[[#This Row],[IMPACTO ECONÓMICO (Máx. 25%)]]*70%*22000+Tabla5[[#This Row],[IMPACTO SST (Máx. 20%)]]*70%*22000+Tabla5[[#This Row],[IMPACTO PRODUCTIVIDAD (Máx. 25%)]]*70%*22000+Tabla5[[#This Row],[IMPACTO ORDEN Y ASEO (Máx. 5%)]]*70%*22000 -> 2926 | R66: =IFERROR(Tabla5[[#This Row],[PUNTOS VALOR INVERSIÓN]]+Tabla5[[#This Row],[PUNTOS ROI ]]+Tabla5[[#This Row],[PUNTOS FACILIDAD IMPLEM. ]]+Tabla5[[#This Row],[PUNTOS IMPACTO ]],"") -> 5016 | T66: Técnica G2 | U66: No Viable | V66: Máquina de marcación laser para productos | W66: Desde calidad se está evaluado sello tipo riel con calor, además es muy costoso y su manipulación genera riesgos a los colobaoradores. | Y66: Descartada
A67: 4116903 | B67: Luis Eduardo Perdomo Rojas | C67: 7452 | D67: Producción | E67: Calificada | F67: 250000 | G67: >3<=6 | H67: A | I67: 0 | J67: 0 | K67: 0 | L67: 0 | M67: 0 | N67: =IF(Tabla5[[#This Row],[VALOR INVERSIÓN]]="","",IF(Tabla5[[#This Row],[VALOR INVERSIÓN]]<=10000000,100%*10%*22000,IF(AND(Tabla5[[#This Row],[VALOR INVERSIÓN]]>10000000,Tabla5[[#This Row],[VALOR INVERSIÓN]]<=20000000),60%*10%*22000,20%*10%*22000))) -> 2200 | O67: =IF(Tabla5[[#This Row],[ROI (MESES)]]="","",IF(Tabla5[[#This Row],[ROI (MESES)]]="N/A","0",IF(Tabla5[[#This Row],[ROI (MESES)]]="<=3",100%*10%*22000,IF(Tabla5[[#This Row],[ROI (MESES)]]=">3<=6",75%*10%*22000,25%*10%*22000)))) -> 1650 | P67: =IF(Tabla5[[#This Row],[FACILIDAD IMPLEM.]]="","",IF(Tabla5[[#This Row],[FACILIDAD IMPLEM.]]="A",100%*10%*22000,IF(AND(Tabla5[[#This Row],[FACILIDAD IMPLEM.]]="B"),50%*10%*22000,20%*10%*22000))) -> 2200 | Q67: =Tabla5[[#This Row],[IMPACTO AMBIENTAL (Máx. 25%)]]*70%*22000+Tabla5[[#This Row],[IMPACTO ECONÓMICO (Máx. 25%)]]*70%*22000+Tabla5[[#This Row],[IMPACTO SST (Máx. 20%)]]*70%*22000+Tabla5[[#This Row],[IMPACTO PRODUCTIVIDAD (Máx. 25%)]]*70%*22000+Tabla5[[#This Row],[IMPACTO ORDEN Y ASEO (Máx. 5%)]]*70%*22000 -> 0 | R67: =IFERROR(Tabla5[[#This Row],[PUNTOS VALOR INVERSIÓN]]+Tabla5[[#This Row],[PUNTOS ROI ]]+Tabla5[[#This Row],[PUNTOS FACILIDAD IMPLEM. ]]+Tabla5[[#This Row],[PUNTOS IMPACTO ]],"") -> 6050 | T67: Técnica G1 | U67: Baja | V67: Cautin para los poros pequeños en soldadura | W67: Solicitar a mantenimiento el prestamo de un cautin para que el colaborador Luis Perdomo haga la prueba e informe el resultado, para que identificar la apariencia. | X67: Sebastián Ossa | Y67: Sin empezar
A68: 70878043 | B68: Luis Octavio Acevedo | C68: 7453 | D68: Logística | E68: Descartada | N68: =IF(Tabla5[[#This Row],[VALOR INVERSIÓN]]="","",IF(Tabla5[[#This Row],[VALOR INVERSIÓN]]<=10000000,100%*10%*22000,IF(AND(Tabla5[[#This Row],[VALOR INVERSIÓN]]>10000000,Tabla5[[#This Row],[VALOR INVERSIÓN]]<=20000000),60%*10%*22000,20%*10%*22000))) | O68: =IF(Tabla5[[#This Row],[ROI (MESES)]]="","",IF(Tabla5[[#This Row],[ROI (MESES)]]="N/A","0",IF(Tabla5[[#This Row],[ROI (MESES)]]="<=3",100%*10%*22000,IF(Tabla5[[#This Row],[ROI (MESES)]]=">3<=6",75%*10%*22000,25%*10%*22000)))) | P68: =IF(Tabla5[[#This Row],[FACILIDAD IMPLEM.]]="","",IF(Tabla5[[#This Row],[FACILIDAD IMPLEM.]]="A",100%*10%*22000,IF(AND(Tabla5[[#This Row],[FACILIDAD IMPLEM.]]="B"),50%*10%*22000,20%*10%*22000))) | Q68: =Tabla5[[#This Row],[IMPACTO AMBIENTAL (Máx. 25%)]]*70%*22000+Tabla5[[#This Row],[IMPACTO ECONÓMICO (Máx. 25%)]]*70%*22000+Tabla5[[#This Row],[IMPACTO SST (Máx. 20%)]]*70%*22000+Tabla5[[#This Row],[IMPACTO PRODUCTIVIDAD (Máx. 25%)]]*70%*22000+Tabla5[[#This Row],[IMPACTO ORDEN Y ASEO (Máx. 5%)]]*70%*22000 -> 0 | R68: =IFERROR(Tabla5[[#This Row],[PUNTOS VALOR INVERSIÓN]]+Tabla5[[#This Row],[PUNTOS ROI ]]+Tabla5[[#This Row],[PUNTOS FACILIDAD IMPLEM. ]]+Tabla5[[#This Row],[PUNTOS IMPACTO ]],"") | S68: Ya se está implementando
A69: 1035912149 | B69: Ferney Hernando Hernandez B. | C69: 7454 | D69: Logística | E69: Descartada | N69: =IF(Tabla5[[#This Row],[VALOR INVERSIÓN]]="","",IF(Tabla5[[#This Row],[VALOR INVERSIÓN]]<=10000000,100%*10%*22000,IF(AND(Tabla5[[#This Row],[VALOR INVERSIÓN]]>10000000,Tabla5[[#This Row],[VALOR INVERSIÓN]]<=20000000),60%*10%*22000,20%*10%*22000))) | O69: =IF(Tabla5[[#This Row],[ROI (MESES)]]="","",IF(Tabla5[[#This Row],[ROI (MESES)]]="N/A","0",IF(Tabla5[[#This Row],[ROI (MESES)]]="<=3",100%*10%*22000,IF(Tabla5[[#This Row],[ROI (MESES)]]=">3<=6",75%*10%*22000,25%*10%*22000)))) | P69: =IF(Tabla5[[#This Row],[FACILIDAD IMPLEM.]]="","",IF(Tabla5[[#This Row],[FACILIDAD IMPLEM.]]="A",100%*10%*22000,IF(AND(Tabla5[[#This Row],[FACILIDAD IMPLEM.]]="B"),50%*10%*22000,20%*10%*22000))) | Q69: =Tabla5[[#This Row],[IMPACTO AMBIENTAL (Máx. 25%)]]*70%*22000+Tabla5[[#This Row],[IMPACTO ECONÓMICO (Máx. 25%)]]*70%*22000+Tabla5[[#This Row],[IMPACTO SST (Máx. 20%)]]*70%*22000+Tabla5[[#This Row],[IMPACTO PRODUCTIVIDAD (Máx. 25%)]]*70%*22000+Tabla5[[#This Row],[IMPACTO ORDEN Y ASEO (Máx. 5%)]]*70%*22000 -> 0 | R69: =IFERROR(Tabla5[[#This Row],[PUNTOS VALOR INVERSIÓN]]+Tabla5[[#This Row],[PUNTOS ROI ]]+Tabla5[[#This Row],[PUNTOS FACILIDAD IMPLEM. ]]+Tabla5[[#This Row],[PUNTOS IMPACTO ]],"")
A70: 1035912149 | B70: Ferney Hernando Hernandez B. | C70: 7455 | D70: Logística | E70: Descartada | N70: =IF(Tabla5[[#This Row],[VALOR INVERSIÓN]]="","",IF(Tabla5[[#This Row],[VALOR INVERSIÓN]]<=10000000,100%*10%*22000,IF(AND(Tabla5[[#This Row],[VALOR INVERSIÓN]]>10000000,Tabla5[[#This Row],[VALOR INVERSIÓN]]<=20000000),60%*10%*22000,20%*10%*22000))) | O70: =IF(Tabla5[[#This Row],[ROI (MESES)]]="","",IF(Tabla5[[#This Row],[ROI (MESES)]]="N/A","0",IF(Tabla5[[#This Row],[ROI (MESES)]]="<=3",100%*10%*22000,IF(Tabla5[[#This Row],[ROI (MESES)]]=">3<=6",75%*10%*22000,25%*10%*22000)))) | P70: =IF(Tabla5[[#This Row],[FACILIDAD IMPLEM.]]="","",IF(Tabla5[[#This Row],[FACILIDAD IMPLEM.]]="A",100%*10%*22000,IF(AND(Tabla5[[#This Row],[FACILIDAD IMPLEM.]]="B"),50%*10%*22000,20%*10%*22000))) | Q70: =Tabla5[[#This Row],[IMPACTO AMBIENTAL (Máx. 25%)]]*70%*22000+Tabla5[[#This Row],[IMPACTO ECONÓMICO (Máx. 25%)]]*70%*22000+Tabla5[[#This Row],[IMPACTO SST (Máx. 20%)]]*70%*22000+Tabla5[[#This Row],[IMPACTO PRODUCTIVIDAD (Máx. 25%)]]*70%*22000+Tabla5[[#This Row],[IMPACTO ORDEN Y ASEO (Máx. 5%)]]*70%*22000 -> 0 | R70: =IFERROR(Tabla5[[#This Row],[PUNTOS VALOR INVERSIÓN]]+Tabla5[[#This Row],[PUNTOS ROI ]]+Tabla5[[#This Row],[PUNTOS FACILIDAD IMPLEM. ]]+Tabla5[[#This Row],[PUNTOS IMPACTO ]],"")
A71: 71365644 | B71: Hernan Dario Miranda Ramírez | C71: 7456 | D71: Logística | E71: Descartada | N71: =IF(Tabla5[[#This Row],[VALOR INVERSIÓN]]="","",IF(Tabla5[[#This Row],[VALOR INVERSIÓN]]<=10000000,100%*10%*22000,IF(AND(Tabla5[[#This Row],[VALOR INVERSIÓN]]>10000000,Tabla5[[#This Row],[VALOR INVERSIÓN]]<=20000000),60%*10%*22000,20%*10%*22000))) | O71: =IF(Tabla5[[#This Row],[ROI (MESES)]]="","",IF(Tabla5[[#This Row],[ROI (MESES)]]="N/A","0",IF(Tabla5[[#This Row],[ROI (MESES)]]="<=3",100%*10%*22000,IF(Tabla5[[#This Row],[ROI (MESES)]]=">3<=6",75%*10%*22000,25%*10%*22000)))) | P71: =IF(Tabla5[[#This Row],[FACILIDAD IMPLEM.]]="","",IF(Tabla5[[#This Row],[FACILIDAD IMPLEM.]]="A",100%*10%*22000,IF(AND(Tabla5[[#This Row],[FACILIDAD IMPLEM.]]="B"),50%*10%*22000,20%*10%*22000))) | Q71: =Tabla5[[#This Row],[IMPACTO AMBIENTAL (Máx. 25%)]]*70%*22000+Tabla5[[#This Row],[IMPACTO ECONÓMICO (Máx. 25%)]]*70%*22000+Tabla5[[#This Row],[IMPACTO SST (Máx. 20%)]]*70%*22000+Tabla5[[#This Row],[IMPACTO PRODUCTIVIDAD (Máx. 25%)]]*70%*22000+Tabla5[[#This Row],[IMPACTO ORDEN Y ASEO (Máx. 5%)]]*70%*22000 -> 0 | R71: =IFERROR(Tabla5[[#This Row],[PUNTOS VALOR INVERSIÓN]]+Tabla5[[#This Row],[PUNTOS ROI ]]+Tabla5[[#This Row],[PUNTOS FACILIDAD IMPLEM. ]]+Tabla5[[#This Row],[PUNTOS IMPACTO ]],"")
A72: 71365644 | B72: Hernan Dario Miranda Ramírez | C72: 7457 | D72: Logística | E72: Descartada | N72: =IF(Tabla5[[#This Row],[VALOR INVERSIÓN]]="","",IF(Tabla5[[#This Row],[VALOR INVERSIÓN]]<=10000000,100%*10%*22000,IF(AND(Tabla5[[#This Row],[VALOR INVERSIÓN]]>10000000,Tabla5[[#This Row],[VALOR INVERSIÓN]]<=20000000),60%*10%*22000,20%*10%*22000))) | O72: =IF(Tabla5[[#This Row],[ROI (MESES)]]="","",IF(Tabla5[[#This Row],[ROI (MESES)]]="N/A","0",IF(Tabla5[[#This Row],[ROI (MESES)]]="<=3",100%*10%*22000,IF(Tabla5[[#This Row],[ROI (MESES)]]=">3<=6",75%*10%*22000,25%*10%*22000)))) | P72: =IF(Tabla5[[#This Row],[FACILIDAD IMPLEM.]]="","",IF(Tabla5[[#This Row],[FACILIDAD IMPLEM.]]="A",100%*10%*22000,IF(AND(Tabla5[[#This Row],[FACILIDAD IMPLEM.]]="B"),50%*10%*22000,20%*10%*22000))) | Q72: =Tabla5[[#This Row],[IMPACTO AMBIENTAL (Máx. 25%)]]*70%*22000+Tabla5[[#This Row],[IMPACTO ECONÓMICO (Máx. 25%)]]*70%*22000+Tabla5[[#This Row],[IMPACTO SST (Máx. 20%)]]*70%*22000+Tabla5[[#This Row],[IMPACTO PRODUCTIVIDAD (Máx. 25%)]]*70%*22000+Tabla5[[#This Row],[IMPACTO ORDEN Y ASEO (Máx. 5%)]]*70%*22000 -> 0 | R72: =IFERROR(Tabla5[[#This Row],[PUNTOS VALOR INVERSIÓN]]+Tabla5[[#This Row],[PUNTOS ROI ]]+Tabla5[[#This Row],[PUNTOS FACILIDAD IMPLEM. ]]+Tabla5[[#This Row],[PUNTOS IMPACTO ]],"")
A73: 71365644 | B73: Hernan Dario Miranda Ramírez | C73: 7458 | D73: Logística | E73: Descartada | N73: =IF(Tabla5[[#This Row],[VALOR INVERSIÓN]]="","",IF(Tabla5[[#This Row],[VALOR INVERSIÓN]]<=10000000,100%*10%*22000,IF(AND(Tabla5[[#This Row],[VALOR INVERSIÓN]]>10000000,Tabla5[[#This Row],[VALOR INVERSIÓN]]<=20000000),60%*10%*22000,20%*10%*22000))) | O73: =IF(Tabla5[[#This Row],[ROI (MESES)]]="","",IF(Tabla5[[#This Row],[ROI (MESES)]]="N/A","0",IF(Tabla5[[#This Row],[ROI (MESES)]]="<=3",100%*10%*22000,IF(Tabla5[[#This Row],[ROI (MESES)]]=">3<=6",75%*10%*22000,25%*10%*22000)))) | P73: =IF(Tabla5[[#This Row],[FACILIDAD IMPLEM.]]="","",IF(Tabla5[[#This Row],[FACILIDAD IMPLEM.]]="A",100%*10%*22000,IF(AND(Tabla5[[#This Row],[FACILIDAD IMPLEM.]]="B"),50%*10%*22000,20%*10%*22000))) | Q73: =Tabla5[[#This Row],[IMPACTO AMBIENTAL (Máx. 25%)]]*70%*22000+Tabla5[[#This Row],[IMPACTO ECONÓMICO (Máx. 25%)]]*70%*22000+Tabla5[[#This Row],[IMPACTO SST (Máx. 20%)]]*70%*22000+Tabla5[[#This Row],[IMPACTO PRODUCTIVIDAD (Máx. 25%)]]*70%*22000+Tabla5[[#This Row],[IMPACTO ORDEN Y ASEO (Máx. 5%)]]*70%*22000 -> 0 | R73: =IFERROR(Tabla5[[#This Row],[PUNTOS VALOR INVERSIÓN]]+Tabla5[[#This Row],[PUNTOS ROI ]]+Tabla5[[#This Row],[PUNTOS FACILIDAD IMPLEM. ]]+Tabla5[[#This Row],[PUNTOS IMPACTO ]],"")
A74: 1193138307 | B74: Cristian Carvajal Rios | C74: 7459 | D74: Logística | E74: Descartada | N74: =IF(Tabla5[[#This Row],[VALOR INVERSIÓN]]="","",IF(Tabla5[[#This Row],[VALOR INVERSIÓN]]<=10000000,100%*10%*22000,IF(AND(Tabla5[[#This Row],[VALOR INVERSIÓN]]>10000000,Tabla5[[#This Row],[VALOR INVERSIÓN]]<=20000000),60%*10%*22000,20%*10%*22000))) | O74: =IF(Tabla5[[#This Row],[ROI (MESES)]]="","",IF(Tabla5[[#This Row],[ROI (MESES)]]="N/A","0",IF(Tabla5[[#This Row],[ROI (MESES)]]="<=3",100%*10%*22000,IF(Tabla5[[#This Row],[ROI (MESES)]]=">3<=6",75%*10%*22000,25%*10%*22000)))) | P74: =IF(Tabla5[[#This Row],[FACILIDAD IMPLEM.]]="","",IF(Tabla5[[#This Row],[FACILIDAD IMPLEM.]]="A",100%*10%*22000,IF(AND(Tabla5[[#This Row],[FACILIDAD IMPLEM.]]="B"),50%*10%*22000,20%*10%*22000))) | Q74: =Tabla5[[#This Row],[IMPACTO AMBIENTAL (Máx. 25%)]]*70%*22000+Tabla5[[#This Row],[IMPACTO ECONÓMICO (Máx. 25%)]]*70%*22000+Tabla5[[#This Row],[IMPACTO SST (Máx. 20%)]]*70%*22000+Tabla5[[#This Row],[IMPACTO PRODUCTIVIDAD (Máx. 25%)]]*70%*22000+Tabla5[[#This Row],[IMPACTO ORDEN Y ASEO (Máx. 5%)]]*70%*22000 -> 0 | R74: =IFERROR(Tabla5[[#This Row],[PUNTOS VALOR INVERSIÓN]]+Tabla5[[#This Row],[PUNTOS ROI ]]+Tabla5[[#This Row],[PUNTOS FACILIDAD IMPLEM. ]]+Tabla5[[#This Row],[PUNTOS IMPACTO ]],"")
A75: 1035915507 | B75: Pedro Alejandro Ruiz Orrego | C75: 7460 | D75: Logística | E75: Descartada | N75: =IF(Tabla5[[#This Row],[VALOR INVERSIÓN]]="","",IF(Tabla5[[#This Row],[VALOR INVERSIÓN]]<=10000000,100%*10%*22000,IF(AND(Tabla5[[#This Row],[VALOR INVERSIÓN]]>10000000,Tabla5[[#This Row],[VALOR INVERSIÓN]]<=20000000),60%*10%*22000,20%*10%*22000))) | O75: =IF(Tabla5[[#This Row],[ROI (MESES)]]="","",IF(Tabla5[[#This Row],[ROI (MESES)]]="N/A","0",IF(Tabla5[[#This Row],[ROI (MESES)]]="<=3",100%*10%*22000,IF(Tabla5[[#This Row],[ROI (MESES)]]=">3<=6",75%*10%*22000,25%*10%*22000)))) | P75: =IF(Tabla5[[#This Row],[FACILIDAD IMPLEM.]]="","",IF(Tabla5[[#This Row],[FACILIDAD IMPLEM.]]="A",100%*10%*22000,IF(AND(Tabla5[[#This Row],[FACILIDAD IMPLEM.]]="B"),50%*10%*22000,20%*10%*22000))) | Q75: =Tabla5[[#This Row],[IMPACTO AMBIENTAL (Máx. 25%)]]*70%*22000+Tabla5[[#This Row],[IMPACTO ECONÓMICO (Máx. 25%)]]*70%*22000+Tabla5[[#This Row],[IMPACTO SST (Máx. 20%)]]*70%*22000+Tabla5[[#This Row],[IMPACTO PRODUCTIVIDAD (Máx. 25%)]]*70%*22000+Tabla5[[#This Row],[IMPACTO ORDEN Y ASEO (Máx. 5%)]]*70%*22000 -> 0 | R75: =IFERROR(Tabla5[[#This Row],[PUNTOS VALOR INVERSIÓN]]+Tabla5[[#This Row],[PUNTOS ROI ]]+Tabla5[[#This Row],[PUNTOS FACILIDAD IMPLEM. ]]+Tabla5[[#This Row],[PUNTOS IMPACTO ]],"") | S75: Explicarle al colaborador la situación actual procesos
A76: 1037607312 | B76: Fraiman Posada | C76: 7461 | D76: Producción | E76: Descartada | N76: =IF(Tabla5[[#This Row],[VALOR INVERSIÓN]]="","",IF(Tabla5[[#This Row],[VALOR INVERSIÓN]]<=10000000,100%*10%*22000,IF(AND(Tabla5[[#This Row],[VALOR INVERSIÓN]]>10000000,Tabla5[[#This Row],[VALOR INVERSIÓN]]<=20000000),60%*10%*22000,20%*10%*22000))) | O76: =IF(Tabla5[[#This Row],[ROI (MESES)]]="","",IF(Tabla5[[#This Row],[ROI (MESES)]]="N/A","0",IF(Tabla5[[#This Row],[ROI (MESES)]]="<=3",100%*10%*22000,IF(Tabla5[[#This Row],[ROI (MESES)]]=">3<=6",75%*10%*22000,25%*10%*22000)))) | P76: =IF(Tabla5[[#This Row],[FACILIDAD IMPLEM.]]="","",IF(Tabla5[[#This Row],[FACILIDAD IMPLEM.]]="A",100%*10%*22000,IF(AND(Tabla5[[#This Row],[FACILIDAD IMPLEM.]]="B"),50%*10%*22000,20%*10%*22000))) | Q76: =Tabla5[[#This Row],[IMPACTO AMBIENTAL (Máx. 25%)]]*70%*22000+Tabla5[[#This Row],[IMPACTO ECONÓMICO (Máx. 25%)]]*70%*22000+Tabla5[[#This Row],[IMPACTO SST (Máx. 20%)]]*70%*22000+Tabla5[[#This Row],[IMPACTO PRODUCTIVIDAD (Máx. 25%)]]*70%*22000+Tabla5[[#This Row],[IMPACTO ORDEN Y ASEO (Máx. 5%)]]*70%*22000 -> 0 | R76: =IFERROR(Tabla5[[#This Row],[PUNTOS VALOR INVERSIÓN]]+Tabla5[[#This Row],[PUNTOS ROI ]]+Tabla5[[#This Row],[PUNTOS FACILIDAD IMPLEM. ]]+Tabla5[[#This Row],[PUNTOS IMPACTO ]],"")
A77: 1001029657 | B77: Jorge David Robledo Ibarguen | C77: 7462 | D77: Producción | E77: Descartada | N77: =IF(Tabla5[[#This Row],[VALOR INVERSIÓN]]="","",IF(Tabla5[[#This Row],[VALOR INVERSIÓN]]<=10000000,100%*10%*22000,IF(AND(Tabla5[[#This Row],[VALOR INVERSIÓN]]>10000000,Tabla5[[#This Row],[VALOR INVERSIÓN]]<=20000000),60%*10%*22000,20%*10%*22000))) | O77: =IF(Tabla5[[#This Row],[ROI (MESES)]]="","",IF(Tabla5[[#This Row],[ROI (MESES)]]="N/A","0",IF(Tabla5[[#This Row],[ROI (MESES)]]="<=3",100%*10%*22000,IF(Tabla5[[#This Row],[ROI (MESES)]]=">3<=6",75%*10%*22000,25%*10%*22000)))) | P77: =IF(Tabla5[[#This Row],[FACILIDAD IMPLEM.]]="","",IF(Tabla5[[#This Row],[FACILIDAD IMPLEM.]]="A",100%*10%*22000,IF(AND(Tabla5[[#This Row],[FACILIDAD IMPLEM.]]="B"),50%*10%*22000,20%*10%*22000))) | Q77: =Tabla5[[#This Row],[IMPACTO AMBIENTAL (Máx. 25%)]]*70%*22000+Tabla5[[#This Row],[IMPACTO ECONÓMICO (Máx. 25%)]]*70%*22000+Tabla5[[#This Row],[IMPACTO SST (Máx. 20%)]]*70%*22000+Tabla5[[#This Row],[IMPACTO PRODUCTIVIDAD (Máx. 25%)]]*70%*22000+Tabla5[[#This Row],[IMPACTO ORDEN Y ASEO (Máx. 5%)]]*70%*22000 -> 0 | R77: =IFERROR(Tabla5[[#This Row],[PUNTOS VALOR INVERSIÓN]]+Tabla5[[#This Row],[PUNTOS ROI ]]+Tabla5[[#This Row],[PUNTOS FACILIDAD IMPLEM. ]]+Tabla5[[#This Row],[PUNTOS IMPACTO ]],"")
A78: 71801338 | B78: Edwin Yobany Valbuena Monsalve | C78: 7521 | D78: Producción | E78: Calificada | F78: 30000000 | G78: >6 | H78: B | I78: 0 | J78: 0 | K78: 0 | L78: 0 | M78: 0.03 | N78: =IF(Tabla5[[#This Row],[VALOR INVERSIÓN]]="","",IF(Tabla5[[#This Row],[VALOR INVERSIÓN]]<=10000000,100%*10%*22000,IF(AND(Tabla5[[#This Row],[VALOR INVERSIÓN]]>10000000,Tabla5[[#This Row],[VALOR INVERSIÓN]]<=20000000),60%*10%*22000,20%*10%*22000))) -> 440 | O78: =IF(Tabla5[[#This Row],[ROI (MESES)]]="","",IF(Tabla5[[#This Row],[ROI (MESES)]]="N/A","0",IF(Tabla5[[#This Row],[ROI (MESES)]]="<=3",100%*10%*22000,IF(Tabla5[[#This Row],[ROI (MESES)]]=">3<=6",75%*10%*22000,25%*10%*22000)))) -> 550 | P78: =IF(Tabla5[[#This Row],[FACILIDAD IMPLEM.]]="","",IF(Tabla5[[#This Row],[FACILIDAD IMPLEM.]]="A",100%*10%*22000,IF(AND(Tabla5[[#This Row],[FACILIDAD IMPLEM.]]="B"),50%*10%*22000,20%*10%*22000))) -> 1100 | Q78: =Tabla5[[#This Row],[IMPACTO AMBIENTAL (Máx. 25%)]]*70%*22000+Tabla5[[#This Row],[IMPACTO ECONÓMICO (Máx. 25%)]]*70%*22000+Tabla5[[#This Row],[IMPACTO SST (Máx. 20%)]]*70%*22000+Tabla5[[#This Row],[IMPACTO PRODUCTIVIDAD (Máx. 25%)]]*70%*22000+Tabla5[[#This Row],[IMPACTO ORDEN Y ASEO (Máx. 5%)]]*70%*22000 -> 462 | R78: =IFERROR(Tabla5[[#This Row],[PUNTOS VALOR INVERSIÓN]]+Tabla5[[#This Row],[PUNTOS ROI ]]+Tabla5[[#This Row],[PUNTOS FACILIDAD IMPLEM. ]]+Tabla5[[#This Row],[PUNTOS IMPACTO ]],"") -> 2552 | T78: Técnica G2 | U78: No Viable | V78: Reubicación molino en zona reciclaje | W78: Altera correcto flujo del proceso y requeriría inversión alta para adecuación | Y78: Descartada
A79: 1000306801 | B79: Santiago Pacheco Mosquera | C79: 7522 | D79: Producción | E79: Descartada | N79: =IF(Tabla5[[#This Row],[VALOR INVERSIÓN]]="","",IF(Tabla5[[#This Row],[VALOR INVERSIÓN]]<=10000000,100%*10%*22000,IF(AND(Tabla5[[#This Row],[VALOR INVERSIÓN]]>10000000,Tabla5[[#This Row],[VALOR INVERSIÓN]]<=20000000),60%*10%*22000,20%*10%*22000))) | O79: =IF(Tabla5[[#This Row],[ROI (MESES)]]="","",IF(Tabla5[[#This Row],[ROI (MESES)]]="N/A","0",IF(Tabla5[[#This Row],[ROI (MESES)]]="<=3",100%*10%*22000,IF(Tabla5[[#This Row],[ROI (MESES)]]=">3<=6",75%*10%*22000,25%*10%*22000)))) | P79: =IF(Tabla5[[#This Row],[FACILIDAD IMPLEM.]]="","",IF(Tabla5[[#This Row],[FACILIDAD IMPLEM.]]="A",100%*10%*22000,IF(AND(Tabla5[[#This Row],[FACILIDAD IMPLEM.]]="B"),50%*10%*22000,20%*10%*22000))) | Q79: =Tabla5[[#This Row],[IMPACTO AMBIENTAL (Máx. 25%)]]*70%*22000+Tabla5[[#This Row],[IMPACTO ECONÓMICO (Máx. 25%)]]*70%*22000+Tabla5[[#This Row],[IMPACTO SST (Máx. 20%)]]*70%*22000+Tabla5[[#This Row],[IMPACTO PRODUCTIVIDAD (Máx. 25%)]]*70%*22000+Tabla5[[#This Row],[IMPACTO ORDEN Y ASEO (Máx. 5%)]]*70%*22000 -> 0 | R79: =IFERROR(Tabla5[[#This Row],[PUNTOS VALOR INVERSIÓN]]+Tabla5[[#This Row],[PUNTOS ROI ]]+Tabla5[[#This Row],[PUNTOS FACILIDAD IMPLEM. ]]+Tabla5[[#This Row],[PUNTOS IMPACTO ]],"") | S79: Repetida
A80: 1000306801 | B80: Santiago Pacheco Mosquera | C80: 7523 | D80: Producción | E80: Calificada | F80: 5000000 | G80: N/A | H80: A | I80: 0 | J80: 0.05 | K80: 0 | L80: 0 | M80: 0.03 | N80: =IF(Tabla5[[#This Row],[VALOR INVERSIÓN]]="","",IF(Tabla5[[#This Row],[VALOR INVERSIÓN]]<=10000000,100%*10%*22000,IF(AND(Tabla5[[#This Row],[VALOR INVERSIÓN]]>10000000,Tabla5[[#This Row],[VALOR INVERSIÓN]]<=20000000),60%*10%*22000,20%*10%*22000))) -> 2200 | O80: =IF(Tabla5[[#This Row],[ROI (MESES)]]="","",IF(Tabla5[[#This Row],[ROI (MESES)]]="N/A","0",IF(Tabla5[[#This Row],[ROI (MESES)]]="<=3",100%*10%*22000,IF(Tabla5[[#This Row],[ROI (MESES)]]=">3<=6",75%*10%*22000,25%*10%*22000)))) -> 0 | P80: =IF(Tabla5[[#This Row],[FACILIDAD IMPLEM.]]="","",IF(Tabla5[[#This Row],[FACILIDAD IMPLEM.]]="A",100%*10%*22000,IF(AND(Tabla5[[#This Row],[FACILIDAD IMPLEM.]]="B"),50%*10%*22000,20%*10%*22000))) -> 2200 | Q80: =Tabla5[[#This Row],[IMPACTO AMBIENTAL (Máx. 25%)]]*70%*22000+Tabla5[[#This Row],[IMPACTO ECONÓMICO (Máx. 25%)]]*70%*22000+Tabla5[[#This Row],[IMPACTO SST (Máx. 20%)]]*70%*22000+Tabla5[[#This Row],[IMPACTO PRODUCTIVIDAD (Máx. 25%)]]*70%*22000+Tabla5[[#This Row],[IMPACTO ORDEN Y ASEO (Máx. 5%)]]*70%*22000 -> 1232 | R80: =IFERROR(Tabla5[[#This Row],[PUNTOS VALOR INVERSIÓN]]+Tabla5[[#This Row],[PUNTOS ROI ]]+Tabla5[[#This Row],[PUNTOS FACILIDAD IMPLEM. ]]+Tabla5[[#This Row],[PUNTOS IMPACTO ]],"") -> 5632 | T80: Técnica G1 | U80: No Viable | V80: Instalacion de poste separador guia, para evitar el paso del personal no autorizado a la zona de MP | W80: Esta pendiente instalar la barrera fisica, ya se ubicó el pc y un letrero de señalización - Se descarta barrera, por circulación de montacarga. | Y80: Descartada
A81: 1000306801 | B81: Santiago Pacheco Mosquera | C81: 7524 | D81: Producción | E81: Descartada | N81: =IF(Tabla5[[#This Row],[VALOR INVERSIÓN]]="","",IF(Tabla5[[#This Row],[VALOR INVERSIÓN]]<=10000000,100%*10%*22000,IF(AND(Tabla5[[#This Row],[VALOR INVERSIÓN]]>10000000,Tabla5[[#This Row],[VALOR INVERSIÓN]]<=20000000),60%*10%*22000,20%*10%*22000))) | O81: =IF(Tabla5[[#This Row],[ROI (MESES)]]="","",IF(Tabla5[[#This Row],[ROI (MESES)]]="N/A","0",IF(Tabla5[[#This Row],[ROI (MESES)]]="<=3",100%*10%*22000,IF(Tabla5[[#This Row],[ROI (MESES)]]=">3<=6",75%*10%*22000,25%*10%*22000)))) | P81: =IF(Tabla5[[#This Row],[FACILIDAD IMPLEM.]]="","",IF(Tabla5[[#This Row],[FACILIDAD IMPLEM.]]="A",100%*10%*22000,IF(AND(Tabla5[[#This Row],[FACILIDAD IMPLEM.]]="B"),50%*10%*22000,20%*10%*22000))) | R81: =IFERROR(Tabla5[[#This Row],[PUNTOS VALOR INVERSIÓN]]+Tabla5[[#This Row],[PUNTOS ROI ]]+Tabla5[[#This Row],[PUNTOS FACILIDAD IMPLEM. ]]+Tabla5[[#This Row],[PUNTOS IMPACTO ]],"") | S81: Repetida
A82: 15258043 | B82: Joaquin Albeiro Contreras Alvarez | C82: 7525 | D82: Producción | E82: Descartada | N82: =IF(Tabla5[[#This Row],[VALOR INVERSIÓN]]="","",IF(Tabla5[[#This Row],[VALOR INVERSIÓN]]<=10000000,100%*10%*22000,IF(AND(Tabla5[[#This Row],[VALOR INVERSIÓN]]>10000000,Tabla5[[#This Row],[VALOR INVERSIÓN]]<=20000000),60%*10%*22000,20%*10%*22000))) | O82: =IF(Tabla5[[#This Row],[ROI (MESES)]]="","",IF(Tabla5[[#This Row],[ROI (MESES)]]="N/A","0",IF(Tabla5[[#This Row],[ROI (MESES)]]="<=3",100%*10%*22000,IF(Tabla5[[#This Row],[ROI (MESES)]]=">3<=6",75%*10%*22000,25%*10%*22000)))) | P82: =IF(Tabla5[[#This Row],[FACILIDAD IMPLEM.]]="","",IF(Tabla5[[#This Row],[FACILIDAD IMPLEM.]]="A",100%*10%*22000,IF(AND(Tabla5[[#This Row],[FACILIDAD IMPLEM.]]="B"),50%*10%*22000,20%*10%*22000))) | Q82: =Tabla5[[#This Row],[IMPACTO AMBIENTAL (Máx. 25%)]]*70%*22000+Tabla5[[#This Row],[IMPACTO ECONÓMICO (Máx. 25%)]]*70%*22000+Tabla5[[#This Row],[IMPACTO SST (Máx. 20%)]]*70%*22000+Tabla5[[#This Row],[IMPACTO PRODUCTIVIDAD (Máx. 25%)]]*70%*22000+Tabla5[[#This Row],[IMPACTO ORDEN Y ASEO (Máx. 5%)]]*70%*22000 -> 0 | R82: =IFERROR(Tabla5[[#This Row],[PUNTOS VALOR INVERSIÓN]]+Tabla5[[#This Row],[PUNTOS ROI ]]+Tabla5[[#This Row],[PUNTOS FACILIDAD IMPLEM. ]]+Tabla5[[#This Row],[PUNTOS IMPACTO ]],"")
A83: 15258043 | B83: Joaquin Albeiro Contreras Alvarez | C83: 7526 | D83: Producción | E83: Calificada | F83: 3000000 | G83: N/A | H83: A | I83: 0 | J83: 0 | K83: 0.09 | L83: 0 | M83: 0.02 | N83: =IF(Tabla5[[#This Row],[VALOR INVERSIÓN]]="","",IF(Tabla5[[#This Row],[VALOR INVERSIÓN]]<=10000000,100%*10%*22000,IF(AND(Tabla5[[#This Row],[VALOR INVERSIÓN]]>10000000,Tabla5[[#This Row],[VALOR INVERSIÓN]]<=20000000),60%*10%*22000,20%*10%*22000))) -> 2200 | O83: =IF(Tabla5[[#This Row],[ROI (MESES)]]="","",IF(Tabla5[[#This Row],[ROI (MESES)]]="N/A","0",IF(Tabla5[[#This Row],[ROI (MESES)]]="<=3",100%*10%*22000,IF(Tabla5[[#This Row],[ROI (MESES)]]=">3<=6",75%*10%*22000,25%*10%*22000)))) -> 0 | P83: =IF(Tabla5[[#This Row],[FACILIDAD IMPLEM.]]="","",IF(Tabla5[[#This Row],[FACILIDAD IMPLEM.]]="A",100%*10%*22000,IF(AND(Tabla5[[#This Row],[FACILIDAD IMPLEM.]]="B"),50%*10%*22000,20%*10%*22000))) -> 2200 | Q83: =Tabla5[[#This Row],[IMPACTO AMBIENTAL (Máx. 25%)]]*70%*22000+Tabla5[[#This Row],[IMPACTO ECONÓMICO (Máx. 25%)]]*70%*22000+Tabla5[[#This Row],[IMPACTO SST (Máx. 20%)]]*70%*22000+Tabla5[[#This Row],[IMPACTO PRODUCTIVIDAD (Máx. 25%)]]*70%*22000+Tabla5[[#This Row],[IMPACTO ORDEN Y ASEO (Máx. 5%)]]*70%*22000 -> 1694 | R83: =IFERROR(Tabla5[[#This Row],[PUNTOS VALOR INVERSIÓN]]+Tabla5[[#This Row],[PUNTOS ROI ]]+Tabla5[[#This Row],[PUNTOS FACILIDAD IMPLEM. ]]+Tabla5[[#This Row],[PUNTOS IMPACTO ]],"") -> 6094 | T83: Técnica G1 | U83: Media | V83: Base para moldes grandes para mejorar el desplazamiento | W83: Pedir apoyo a Juan David Rojas que los diseñe y se mandes a hacer por fuera. | X83: Juan David Rojas - Cristian Cardona | Y83: Implementada
A84: 1007330306 | B84: Juan Pablo Orozco Yepes | C84: 7527 | D84: Logística | E84: Descartada | N84: =IF(Tabla5[[#This Row],[VALOR INVERSIÓN]]="","",IF(Tabla5[[#This Row],[VALOR INVERSIÓN]]<=10000000,100%*10%*22000,IF(AND(Tabla5[[#This Row],[VALOR INVERSIÓN]]>10000000,Tabla5[[#This Row],[VALOR INVERSIÓN]]<=20000000),60%*10%*22000,20%*10%*22000))) | O84: =IF(Tabla5[[#This Row],[ROI (MESES)]]="","",IF(Tabla5[[#This Row],[ROI (MESES)]]="N/A","0",IF(Tabla5[[#This Row],[ROI (MESES)]]="<=3",100%*10%*22000,IF(Tabla5[[#This Row],[ROI (MESES)]]=">3<=6",75%*10%*22000,25%*10%*22000)))) | P84: =IF(Tabla5[[#This Row],[FACILIDAD IMPLEM.]]="","",IF(Tabla5[[#This Row],[FACILIDAD IMPLEM.]]="A",100%*10%*22000,IF(AND(Tabla5[[#This Row],[FACILIDAD IMPLEM.]]="B"),50%*10%*22000,20%*10%*22000))) | Q84: =Tabla5[[#This Row],[IMPACTO AMBIENTAL (Máx. 25%)]]*70%*22000+Tabla5[[#This Row],[IMPACTO ECONÓMICO (Máx. 25%)]]*70%*22000+Tabla5[[#This Row],[IMPACTO SST (Máx. 20%)]]*70%*22000+Tabla5[[#This Row],[IMPACTO PRODUCTIVIDAD (Máx. 25%)]]*70%*22000+Tabla5[[#This Row],[IMPACTO ORDEN Y ASEO (Máx. 5%)]]*70%*22000 -> 0 | R84: =IFERROR(Tabla5[[#This Row],[PUNTOS VALOR INVERSIÓN]]+Tabla5[[#This Row],[PUNTOS ROI ]]+Tabla5[[#This Row],[PUNTOS FACILIDAD IMPLEM. ]]+Tabla5[[#This Row],[PUNTOS IMPACTO ]],"")
A85: 1007330306 | B85: Juan Pablo Orozco Yepes | C85: 7528 | D85: Logística | E85: Descartada | N85: =IF(Tabla5[[#This Row],[VALOR INVERSIÓN]]="","",IF(Tabla5[[#This Row],[VALOR INVERSIÓN]]<=10000000,100%*10%*22000,IF(AND(Tabla5[[#This Row],[VALOR INVERSIÓN]]>10000000,Tabla5[[#This Row],[VALOR INVERSIÓN]]<=20000000),60%*10%*22000,20%*10%*22000))) | O85: =IF(Tabla5[[#This Row],[ROI (MESES)]]="","",IF(Tabla5[[#This Row],[ROI (MESES)]]="N/A","0",IF(Tabla5[[#This Row],[ROI (MESES)]]="<=3",100%*10%*22000,IF(Tabla5[[#This Row],[ROI (MESES)]]=">3<=6",75%*10%*22000,25%*10%*22000)))) | P85: =IF(Tabla5[[#This Row],[FACILIDAD IMPLEM.]]="","",IF(Tabla5[[#This Row],[FACILIDAD IMPLEM.]]="A",100%*10%*22000,IF(AND(Tabla5[[#This Row],[FACILIDAD IMPLEM.]]="B"),50%*10%*22000,20%*10%*22000))) | Q85: =Tabla5[[#This Row],[IMPACTO AMBIENTAL (Máx. 25%)]]*70%*22000+Tabla5[[#This Row],[IMPACTO ECONÓMICO (Máx. 25%)]]*70%*22000+Tabla5[[#This Row],[IMPACTO SST (Máx. 20%)]]*70%*22000+Tabla5[[#This Row],[IMPACTO PRODUCTIVIDAD (Máx. 25%)]]*70%*22000+Tabla5[[#This Row],[IMPACTO ORDEN Y ASEO (Máx. 5%)]]*70%*22000 -> 0 | R85: =IFERROR(Tabla5[[#This Row],[PUNTOS VALOR INVERSIÓN]]+Tabla5[[#This Row],[PUNTOS ROI ]]+Tabla5[[#This Row],[PUNTOS FACILIDAD IMPLEM. ]]+Tabla5[[#This Row],[PUNTOS IMPACTO ]],"")
A86: 71742028 | B86: Juan Alejandro Atehortua Gañan | C86: 7529 | D86: Producción | E86: Descartada | N86: =IF(Tabla5[[#This Row],[VALOR INVERSIÓN]]="","",IF(Tabla5[[#This Row],[VALOR INVERSIÓN]]<=10000000,100%*10%*22000,IF(AND(Tabla5[[#This Row],[VALOR INVERSIÓN]]>10000000,Tabla5[[#This Row],[VALOR INVERSIÓN]]<=20000000),60%*10%*22000,20%*10%*22000))) | O86: =IF(Tabla5[[#This Row],[ROI (MESES)]]="","",IF(Tabla5[[#This Row],[ROI (MESES)]]="N/A","0",IF(Tabla5[[#This Row],[ROI (MESES)]]="<=3",100%*10%*22000,IF(Tabla5[[#This Row],[ROI (MESES)]]=">3<=6",75%*10%*22000,25%*10%*22000)))) | P86: =IF(Tabla5[[#This Row],[FACILIDAD IMPLEM.]]="","",IF(Tabla5[[#This Row],[FACILIDAD IMPLEM.]]="A",100%*10%*22000,IF(AND(Tabla5[[#This Row],[FACILIDAD IMPLEM.]]="B"),50%*10%*22000,20%*10%*22000))) | Q86: =Tabla5[[#This Row],[IMPACTO AMBIENTAL (Máx. 25%)]]*70%*22000+Tabla5[[#This Row],[IMPACTO ECONÓMICO (Máx. 25%)]]*70%*22000+Tabla5[[#This Row],[IMPACTO SST (Máx. 20%)]]*70%*22000+Tabla5[[#This Row],[IMPACTO PRODUCTIVIDAD (Máx. 25%)]]*70%*22000+Tabla5[[#This Row],[IMPACTO ORDEN Y ASEO (Máx. 5%)]]*70%*22000 -> 0 | R86: =IFERROR(Tabla5[[#This Row],[PUNTOS VALOR INVERSIÓN]]+Tabla5[[#This Row],[PUNTOS ROI ]]+Tabla5[[#This Row],[PUNTOS FACILIDAD IMPLEM. ]]+Tabla5[[#This Row],[PUNTOS IMPACTO ]],"")
A87: 71273030 | B87: Esteban Castaño Salazar | C87: 7530 | D87: TI | E87: Descartada | N87: =IF(Tabla5[[#This Row],[VALOR INVERSIÓN]]="","",IF(Tabla5[[#This Row],[VALOR INVERSIÓN]]<=10000000,100%*10%*22000,IF(AND(Tabla5[[#This Row],[VALOR INVERSIÓN]]>10000000,Tabla5[[#This Row],[VALOR INVERSIÓN]]<=20000000),60%*10%*22000,20%*10%*22000))) | O87: =IF(Tabla5[[#This Row],[ROI (MESES)]]="","",IF(Tabla5[[#This Row],[ROI (MESES)]]="N/A","0",IF(Tabla5[[#This Row],[ROI (MESES)]]="<=3",100%*10%*22000,IF(Tabla5[[#This Row],[ROI (MESES)]]=">3<=6",75%*10%*22000,25%*10%*22000)))) | P87: =IF(Tabla5[[#This Row],[FACILIDAD IMPLEM.]]="","",IF(Tabla5[[#This Row],[FACILIDAD IMPLEM.]]="A",100%*10%*22000,IF(AND(Tabla5[[#This Row],[FACILIDAD IMPLEM.]]="B"),50%*10%*22000,20%*10%*22000))) | Q87: =Tabla5[[#This Row],[IMPACTO AMBIENTAL (Máx. 25%)]]*70%*22000+Tabla5[[#This Row],[IMPACTO ECONÓMICO (Máx. 25%)]]*70%*22000+Tabla5[[#This Row],[IMPACTO SST (Máx. 20%)]]*70%*22000+Tabla5[[#This Row],[IMPACTO PRODUCTIVIDAD (Máx. 25%)]]*70%*22000+Tabla5[[#This Row],[IMPACTO ORDEN Y ASEO (Máx. 5%)]]*70%*22000 -> 0 | R87: =IFERROR(Tabla5[[#This Row],[PUNTOS VALOR INVERSIÓN]]+Tabla5[[#This Row],[PUNTOS ROI ]]+Tabla5[[#This Row],[PUNTOS FACILIDAD IMPLEM. ]]+Tabla5[[#This Row],[PUNTOS IMPACTO ]],"")
A88: 1013557593 | B88: Jesus Alberto Zapata Rueda | C88: 7531 | D88: Logística | E88: Descartada | N88: =IF(Tabla5[[#This Row],[VALOR INVERSIÓN]]="","",IF(Tabla5[[#This Row],[VALOR INVERSIÓN]]<=10000000,100%*10%*22000,IF(AND(Tabla5[[#This Row],[VALOR INVERSIÓN]]>10000000,Tabla5[[#This Row],[VALOR INVERSIÓN]]<=20000000),60%*10%*22000,20%*10%*22000))) | O88: =IF(Tabla5[[#This Row],[ROI (MESES)]]="","",IF(Tabla5[[#This Row],[ROI (MESES)]]="N/A","0",IF(Tabla5[[#This Row],[ROI (MESES)]]="<=3",100%*10%*22000,IF(Tabla5[[#This Row],[ROI (MESES)]]=">3<=6",75%*10%*22000,25%*10%*22000)))) | P88: =IF(Tabla5[[#This Row],[FACILIDAD IMPLEM.]]="","",IF(Tabla5[[#This Row],[FACILIDAD IMPLEM.]]="A",100%*10%*22000,IF(AND(Tabla5[[#This Row],[FACILIDAD IMPLEM.]]="B"),50%*10%*22000,20%*10%*22000))) | Q88: =Tabla5[[#This Row],[IMPACTO AMBIENTAL (Máx. 25%)]]*70%*22000+Tabla5[[#This Row],[IMPACTO ECONÓMICO (Máx. 25%)]]*70%*22000+Tabla5[[#This Row],[IMPACTO SST (Máx. 20%)]]*70%*22000+Tabla5[[#This Row],[IMPACTO PRODUCTIVIDAD (Máx. 25%)]]*70%*22000+Tabla5[[#This Row],[IMPACTO ORDEN Y ASEO (Máx. 5%)]]*70%*22000 -> 0 | R88: =IFERROR(Tabla5[[#This Row],[PUNTOS VALOR INVERSIÓN]]+Tabla5[[#This Row],[PUNTOS ROI ]]+Tabla5[[#This Row],[PUNTOS FACILIDAD IMPLEM. ]]+Tabla5[[#This Row],[PUNTOS IMPACTO ]],"")
A89: 1036697118 | B89: Darwin Acevedo Alzate | C89: 7532 | D89: Logística | E89: Descartada | N89: =IF(Tabla5[[#This Row],[VALOR INVERSIÓN]]="","",IF(Tabla5[[#This Row],[VALOR INVERSIÓN]]<=10000000,100%*10%*22000,IF(AND(Tabla5[[#This Row],[VALOR INVERSIÓN]]>10000000,Tabla5[[#This Row],[VALOR INVERSIÓN]]<=20000000),60%*10%*22000,20%*10%*22000))) | O89: =IF(Tabla5[[#This Row],[ROI (MESES)]]="","",IF(Tabla5[[#This Row],[ROI (MESES)]]="N/A","0",IF(Tabla5[[#This Row],[ROI (MESES)]]="<=3",100%*10%*22000,IF(Tabla5[[#This Row],[ROI (MESES)]]=">3<=6",75%*10%*22000,25%*10%*22000)))) | P89: =IF(Tabla5[[#This Row],[FACILIDAD IMPLEM.]]="","",IF(Tabla5[[#This Row],[FACILIDAD IMPLEM.]]="A",100%*10%*22000,IF(AND(Tabla5[[#This Row],[FACILIDAD IMPLEM.]]="B"),50%*10%*22000,20%*10%*22000))) | Q89: =Tabla5[[#This Row],[IMPACTO AMBIENTAL (Máx. 25%)]]*70%*22000+Tabla5[[#This Row],[IMPACTO ECONÓMICO (Máx. 25%)]]*70%*22000+Tabla5[[#This Row],[IMPACTO SST (Máx. 20%)]]*70%*22000+Tabla5[[#This Row],[IMPACTO PRODUCTIVIDAD (Máx. 25%)]]*70%*22000+Tabla5[[#This Row],[IMPACTO ORDEN Y ASEO (Máx. 5%)]]*70%*22000 -> 0 | R89: =IFERROR(Tabla5[[#This Row],[PUNTOS VALOR INVERSIÓN]]+Tabla5[[#This Row],[PUNTOS ROI ]]+Tabla5[[#This Row],[PUNTOS FACILIDAD IMPLEM. ]]+Tabla5[[#This Row],[PUNTOS IMPACTO ]],"")
A90: 1036697118 | B90: Darwin Acevedo Alzate | C90: 7533 | D90: Logística | E90: Descartada | N90: =IF(Tabla5[[#This Row],[VALOR INVERSIÓN]]="","",IF(Tabla5[[#This Row],[VALOR INVERSIÓN]]<=10000000,100%*10%*22000,IF(AND(Tabla5[[#This Row],[VALOR INVERSIÓN]]>10000000,Tabla5[[#This Row],[VALOR INVERSIÓN]]<=20000000),60%*10%*22000,20%*10%*22000))) | O90: =IF(Tabla5[[#This Row],[ROI (MESES)]]="","",IF(Tabla5[[#This Row],[ROI (MESES)]]="N/A","0",IF(Tabla5[[#This Row],[ROI (MESES)]]="<=3",100%*10%*22000,IF(Tabla5[[#This Row],[ROI (MESES)]]=">3<=6",75%*10%*22000,25%*10%*22000)))) | P90: =IF(Tabla5[[#This Row],[FACILIDAD IMPLEM.]]="","",IF(Tabla5[[#This Row],[FACILIDAD IMPLEM.]]="A",100%*10%*22000,IF(AND(Tabla5[[#This Row],[FACILIDAD IMPLEM.]]="B"),50%*10%*22000,20%*10%*22000))) | Q90: =Tabla5[[#This Row],[IMPACTO AMBIENTAL (Máx. 25%)]]*70%*22000+Tabla5[[#This Row],[IMPACTO ECONÓMICO (Máx. 25%)]]*70%*22000+Tabla5[[#This Row],[IMPACTO SST (Máx. 20%)]]*70%*22000+Tabla5[[#This Row],[IMPACTO PRODUCTIVIDAD (Máx. 25%)]]*70%*22000+Tabla5[[#This Row],[IMPACTO ORDEN Y ASEO (Máx. 5%)]]*70%*22000 -> 0 | R90: =IFERROR(Tabla5[[#This Row],[PUNTOS VALOR INVERSIÓN]]+Tabla5[[#This Row],[PUNTOS ROI ]]+Tabla5[[#This Row],[PUNTOS FACILIDAD IMPLEM. ]]+Tabla5[[#This Row],[PUNTOS IMPACTO ]],"")
A91: 1035919859 | B91: Juliana Acevedo Carvajal | C91: 7534 | D91: Logística | E91: Descartada | N91: =IF(Tabla5[[#This Row],[VALOR INVERSIÓN]]="","",IF(Tabla5[[#This Row],[VALOR INVERSIÓN]]<=10000000,100%*10%*22000,IF(AND(Tabla5[[#This Row],[VALOR INVERSIÓN]]>10000000,Tabla5[[#This Row],[VALOR INVERSIÓN]]<=20000000),60%*10%*22000,20%*10%*22000))) | O91: =IF(Tabla5[[#This Row],[ROI (MESES)]]="","",IF(Tabla5[[#This Row],[ROI (MESES)]]="N/A","0",IF(Tabla5[[#This Row],[ROI (MESES)]]="<=3",100%*10%*22000,IF(Tabla5[[#This Row],[ROI (MESES)]]=">3<=6",75%*10%*22000,25%*10%*22000)))) | P91: =IF(Tabla5[[#This Row],[FACILIDAD IMPLEM.]]="","",IF(Tabla5[[#This Row],[FACILIDAD IMPLEM.]]="A",100%*10%*22000,IF(AND(Tabla5[[#This Row],[FACILIDAD IMPLEM.]]="B"),50%*10%*22000,20%*10%*22000))) | Q91: =Tabla5[[#This Row],[IMPACTO AMBIENTAL (Máx. 25%)]]*70%*22000+Tabla5[[#This Row],[IMPACTO ECONÓMICO (Máx. 25%)]]*70%*22000+Tabla5[[#This Row],[IMPACTO SST (Máx. 20%)]]*70%*22000+Tabla5[[#This Row],[IMPACTO PRODUCTIVIDAD (Máx. 25%)]]*70%*22000+Tabla5[[#This Row],[IMPACTO ORDEN Y ASEO (Máx. 5%)]]*70%*22000 -> 0 | R91: =IFERROR(Tabla5[[#This Row],[PUNTOS VALOR INVERSIÓN]]+Tabla5[[#This Row],[PUNTOS ROI ]]+Tabla5[[#This Row],[PUNTOS FACILIDAD IMPLEM. ]]+Tabla5[[#This Row],[PUNTOS IMPACTO ]],"")
A92: 1147692351 | B92: Gilder Andres Guzman Palomeque | C92: 7535 | D92: Logística | E92: Descartada | N92: =IF(Tabla5[[#This Row],[VALOR INVERSIÓN]]="","",IF(Tabla5[[#This Row],[VALOR INVERSIÓN]]<=10000000,100%*10%*22000,IF(AND(Tabla5[[#This Row],[VALOR INVERSIÓN]]>10000000,Tabla5[[#This Row],[VALOR INVERSIÓN]]<=20000000),60%*10%*22000,20%*10%*22000))) | O92: =IF(Tabla5[[#This Row],[ROI (MESES)]]="","",IF(Tabla5[[#This Row],[ROI (MESES)]]="N/A","0",IF(Tabla5[[#This Row],[ROI (MESES)]]="<=3",100%*10%*22000,IF(Tabla5[[#This Row],[ROI (MESES)]]=">3<=6",75%*10%*22000,25%*10%*22000)))) | P92: =IF(Tabla5[[#This Row],[FACILIDAD IMPLEM.]]="","",IF(Tabla5[[#This Row],[FACILIDAD IMPLEM.]]="A",100%*10%*22000,IF(AND(Tabla5[[#This Row],[FACILIDAD IMPLEM.]]="B"),50%*10%*22000,20%*10%*22000))) | Q92: =Tabla5[[#This Row],[IMPACTO AMBIENTAL (Máx. 25%)]]*70%*22000+Tabla5[[#This Row],[IMPACTO ECONÓMICO (Máx. 25%)]]*70%*22000+Tabla5[[#This Row],[IMPACTO SST (Máx. 20%)]]*70%*22000+Tabla5[[#This Row],[IMPACTO PRODUCTIVIDAD (Máx. 25%)]]*70%*22000+Tabla5[[#This Row],[IMPACTO ORDEN Y ASEO (Máx. 5%)]]*70%*22000 -> 0 | R92: =IFERROR(Tabla5[[#This Row],[PUNTOS VALOR INVERSIÓN]]+Tabla5[[#This Row],[PUNTOS ROI ]]+Tabla5[[#This Row],[PUNTOS FACILIDAD IMPLEM. ]]+Tabla5[[#This Row],[PUNTOS IMPACTO ]],"")
A93: 1214747832 | B93: Jeison Fernando Salazar Castañeda | C93: 7536 | D93: Logística | E93: Descartada | N93: =IF(Tabla5[[#This Row],[VALOR INVERSIÓN]]="","",IF(Tabla5[[#This Row],[VALOR INVERSIÓN]]<=10000000,100%*10%*22000,IF(AND(Tabla5[[#This Row],[VALOR INVERSIÓN]]>10000000,Tabla5[[#This Row],[VALOR INVERSIÓN]]<=20000000),60%*10%*22000,20%*10%*22000))) | O93: =IF(Tabla5[[#This Row],[ROI (MESES)]]="","",IF(Tabla5[[#This Row],[ROI (MESES)]]="N/A","0",IF(Tabla5[[#This Row],[ROI (MESES)]]="<=3",100%*10%*22000,IF(Tabla5[[#This Row],[ROI (MESES)]]=">3<=6",75%*10%*22000,25%*10%*22000)))) | P93: =IF(Tabla5[[#This Row],[FACILIDAD IMPLEM.]]="","",IF(Tabla5[[#This Row],[FACILIDAD IMPLEM.]]="A",100%*10%*22000,IF(AND(Tabla5[[#This Row],[FACILIDAD IMPLEM.]]="B"),50%*10%*22000,20%*10%*22000))) | Q93: =Tabla5[[#This Row],[IMPACTO AMBIENTAL (Máx. 25%)]]*70%*22000+Tabla5[[#This Row],[IMPACTO ECONÓMICO (Máx. 25%)]]*70%*22000+Tabla5[[#This Row],[IMPACTO SST (Máx. 20%)]]*70%*22000+Tabla5[[#This Row],[IMPACTO PRODUCTIVIDAD (Máx. 25%)]]*70%*22000+Tabla5[[#This Row],[IMPACTO ORDEN Y ASEO (Máx. 5%)]]*70%*22000 -> 0 | R93: =IFERROR(Tabla5[[#This Row],[PUNTOS VALOR INVERSIÓN]]+Tabla5[[#This Row],[PUNTOS ROI ]]+Tabla5[[#This Row],[PUNTOS FACILIDAD IMPLEM. ]]+Tabla5[[#This Row],[PUNTOS IMPACTO ]],"")
A94: 1036967118 | B94: Darwin Acevedo Alzate | C94: 7537 | D94: Logística | E94: Descartada | N94: =IF(Tabla5[[#This Row],[VALOR INVERSIÓN]]="","",IF(Tabla5[[#This Row],[VALOR INVERSIÓN]]<=10000000,100%*10%*22000,IF(AND(Tabla5[[#This Row],[VALOR INVERSIÓN]]>10000000,Tabla5[[#This Row],[VALOR INVERSIÓN]]<=20000000),60%*10%*22000,20%*10%*22000))) | O94: =IF(Tabla5[[#This Row],[ROI (MESES)]]="","",IF(Tabla5[[#This Row],[ROI (MESES)]]="N/A","0",IF(Tabla5[[#This Row],[ROI (MESES)]]="<=3",100%*10%*22000,IF(Tabla5[[#This Row],[ROI (MESES)]]=">3<=6",75%*10%*22000,25%*10%*22000)))) | P94: =IF(Tabla5[[#This Row],[FACILIDAD IMPLEM.]]="","",IF(Tabla5[[#This Row],[FACILIDAD IMPLEM.]]="A",100%*10%*22000,IF(AND(Tabla5[[#This Row],[FACILIDAD IMPLEM.]]="B"),50%*10%*22000,20%*10%*22000))) | Q94: =Tabla5[[#This Row],[IMPACTO AMBIENTAL (Máx. 25%)]]*70%*22000+Tabla5[[#This Row],[IMPACTO ECONÓMICO (Máx. 25%)]]*70%*22000+Tabla5[[#This Row],[IMPACTO SST (Máx. 20%)]]*70%*22000+Tabla5[[#This Row],[IMPACTO PRODUCTIVIDAD (Máx. 25%)]]*70%*22000+Tabla5[[#This Row],[IMPACTO ORDEN Y ASEO (Máx. 5%)]]*70%*22000 -> 0 | R94: =IFERROR(Tabla5[[#This Row],[PUNTOS VALOR INVERSIÓN]]+Tabla5[[#This Row],[PUNTOS ROI ]]+Tabla5[[#This Row],[PUNTOS FACILIDAD IMPLEM. ]]+Tabla5[[#This Row],[PUNTOS IMPACTO ]],"")
A95: 1013557593 | B95: Jesus Alberto Zapata Rueda | C95: 7538 | D95: Logística | E95: Descartada | N95: =IF(Tabla5[[#This Row],[VALOR INVERSIÓN]]="","",IF(Tabla5[[#This Row],[VALOR INVERSIÓN]]<=10000000,100%*10%*22000,IF(AND(Tabla5[[#This Row],[VALOR INVERSIÓN]]>10000000,Tabla5[[#This Row],[VALOR INVERSIÓN]]<=20000000),60%*10%*22000,20%*10%*22000))) | O95: =IF(Tabla5[[#This Row],[ROI (MESES)]]="","",IF(Tabla5[[#This Row],[ROI (MESES)]]="N/A","0",IF(Tabla5[[#This Row],[ROI (MESES)]]="<=3",100%*10%*22000,IF(Tabla5[[#This Row],[ROI (MESES)]]=">3<=6",75%*10%*22000,25%*10%*22000)))) | P95: =IF(Tabla5[[#This Row],[FACILIDAD IMPLEM.]]="","",IF(Tabla5[[#This Row],[FACILIDAD IMPLEM.]]="A",100%*10%*22000,IF(AND(Tabla5[[#This Row],[FACILIDAD IMPLEM.]]="B"),50%*10%*22000,20%*10%*22000))) | Q95: =Tabla5[[#This Row],[IMPACTO AMBIENTAL (Máx. 25%)]]*70%*22000+Tabla5[[#This Row],[IMPACTO ECONÓMICO (Máx. 25%)]]*70%*22000+Tabla5[[#This Row],[IMPACTO SST (Máx. 20%)]]*70%*22000+Tabla5[[#This Row],[IMPACTO PRODUCTIVIDAD (Máx. 25%)]]*70%*22000+Tabla5[[#This Row],[IMPACTO ORDEN Y ASEO (Máx. 5%)]]*70%*22000 -> 0 | R95: =IFERROR(Tabla5[[#This Row],[PUNTOS VALOR INVERSIÓN]]+Tabla5[[#This Row],[PUNTOS ROI ]]+Tabla5[[#This Row],[PUNTOS FACILIDAD IMPLEM. ]]+Tabla5[[#This Row],[PUNTOS IMPACTO ]],"")
A96: 1035919859 | B96: Juliana Acevedo Carvajal | C96: 7539 | D96: Logística | E96: Descartada | N96: =IF(Tabla5[[#This Row],[VALOR INVERSIÓN]]="","",IF(Tabla5[[#This Row],[VALOR INVERSIÓN]]<=10000000,100%*10%*22000,IF(AND(Tabla5[[#This Row],[VALOR INVERSIÓN]]>10000000,Tabla5[[#This Row],[VALOR INVERSIÓN]]<=20000000),60%*10%*22000,20%*10%*22000))) | O96: =IF(Tabla5[[#This Row],[ROI (MESES)]]="","",IF(Tabla5[[#This Row],[ROI (MESES)]]="N/A","0",IF(Tabla5[[#This Row],[ROI (MESES)]]="<=3",100%*10%*22000,IF(Tabla5[[#This Row],[ROI (MESES)]]=">3<=6",75%*10%*22000,25%*10%*22000)))) | P96: =IF(Tabla5[[#This Row],[FACILIDAD IMPLEM.]]="","",IF(Tabla5[[#This Row],[FACILIDAD IMPLEM.]]="A",100%*10%*22000,IF(AND(Tabla5[[#This Row],[FACILIDAD IMPLEM.]]="B"),50%*10%*22000,20%*10%*22000))) | Q96: =Tabla5[[#This Row],[IMPACTO AMBIENTAL (Máx. 25%)]]*70%*22000+Tabla5[[#This Row],[IMPACTO ECONÓMICO (Máx. 25%)]]*70%*22000+Tabla5[[#This Row],[IMPACTO SST (Máx. 20%)]]*70%*22000+Tabla5[[#This Row],[IMPACTO PRODUCTIVIDAD (Máx. 25%)]]*70%*22000+Tabla5[[#This Row],[IMPACTO ORDEN Y ASEO (Máx. 5%)]]*70%*22000 -> 0 | R96: =IFERROR(Tabla5[[#This Row],[PUNTOS VALOR INVERSIÓN]]+Tabla5[[#This Row],[PUNTOS ROI ]]+Tabla5[[#This Row],[PUNTOS FACILIDAD IMPLEM. ]]+Tabla5[[#This Row],[PUNTOS IMPACTO ]],"")
A97: 1000567397 | B97: Alejandro Mazo | C97: 7540 | D97: Producción | E97: Descartada | N97: =IF(Tabla5[[#This Row],[VALOR INVERSIÓN]]="","",IF(Tabla5[[#This Row],[VALOR INVERSIÓN]]<=10000000,100%*10%*22000,IF(AND(Tabla5[[#This Row],[VALOR INVERSIÓN]]>10000000,Tabla5[[#This Row],[VALOR INVERSIÓN]]<=20000000),60%*10%*22000,20%*10%*22000))) | O97: =IF(Tabla5[[#This Row],[ROI (MESES)]]="","",IF(Tabla5[[#This Row],[ROI (MESES)]]="N/A","0",IF(Tabla5[[#This Row],[ROI (MESES)]]="<=3",100%*10%*22000,IF(Tabla5[[#This Row],[ROI (MESES)]]=">3<=6",75%*10%*22000,25%*10%*22000)))) | P97: =IF(Tabla5[[#This Row],[FACILIDAD IMPLEM.]]="","",IF(Tabla5[[#This Row],[FACILIDAD IMPLEM.]]="A",100%*10%*22000,IF(AND(Tabla5[[#This Row],[FACILIDAD IMPLEM.]]="B"),50%*10%*22000,20%*10%*22000))) | Q97: =Tabla5[[#This Row],[IMPACTO AMBIENTAL (Máx. 25%)]]*70%*22000+Tabla5[[#This Row],[IMPACTO ECONÓMICO (Máx. 25%)]]*70%*22000+Tabla5[[#This Row],[IMPACTO SST (Máx. 20%)]]*70%*22000+Tabla5[[#This Row],[IMPACTO PRODUCTIVIDAD (Máx. 25%)]]*70%*22000+Tabla5[[#This Row],[IMPACTO ORDEN Y ASEO (Máx. 5%)]]*70%*22000 -> 0 | R97: =IFERROR(Tabla5[[#This Row],[PUNTOS VALOR INVERSIÓN]]+Tabla5[[#This Row],[PUNTOS ROI ]]+Tabla5[[#This Row],[PUNTOS FACILIDAD IMPLEM. ]]+Tabla5[[#This Row],[PUNTOS IMPACTO ]],"") | S97: 09/12/2024 Notificado
A98: 1073676872 | B98: Miguel Angel Ocampo Isaza | C98: 7541 | D98: Producción | E98: Calificada | F98: 1200000 | G98: N/A | H98: A | I98: 0 | J98: 0 | K98: 0.05 | L98: 0.07 | M98: 0 | N98: =IF(Tabla5[[#This Row],[VALOR INVERSIÓN]]="","",IF(Tabla5[[#This Row],[VALOR INVERSIÓN]]<=10000000,100%*10%*22000,IF(AND(Tabla5[[#This Row],[VALOR INVERSIÓN]]>10000000,Tabla5[[#This Row],[VALOR INVERSIÓN]]<=20000000),60%*10%*22000,20%*10%*22000))) -> 2200 | O98: =IF(Tabla5[[#This Row],[ROI (MESES)]]="","",IF(Tabla5[[#This Row],[ROI (MESES)]]="N/A","0",IF(Tabla5[[#This Row],[ROI (MESES)]]="<=3",100%*10%*22000,IF(Tabla5[[#This Row],[ROI (MESES)]]=">3<=6",75%*10%*22000,25%*10%*22000)))) -> 0 | P98: =IF(Tabla5[[#This Row],[FACILIDAD IMPLEM.]]="","",IF(Tabla5[[#This Row],[FACILIDAD IMPLEM.]]="A",100%*10%*22000,IF(AND(Tabla5[[#This Row],[FACILIDAD IMPLEM.]]="B"),50%*10%*22000,20%*10%*22000))) -> 2200 | Q98: =Tabla5[[#This Row],[IMPACTO AMBIENTAL (Máx. 25%)]]*70%*22000+Tabla5[[#This Row],[IMPACTO ECONÓMICO (Máx. 25%)]]*70%*22000+Tabla5[[#This Row],[IMPACTO SST (Máx. 20%)]]*70%*22000+Tabla5[[#This Row],[IMPACTO PRODUCTIVIDAD (Máx. 25%)]]*70%*22000+Tabla5[[#This Row],[IMPACTO ORDEN Y ASEO (Máx. 5%)]]*70%*22000 -> 1848 | R98: =IFERROR(Tabla5[[#This Row],[PUNTOS VALOR INVERSIÓN]]+Tabla5[[#This Row],[PUNTOS ROI ]]+Tabla5[[#This Row],[PUNTOS FACILIDAD IMPLEM. ]]+Tabla5[[#This Row],[PUNTOS IMPACTO ]],"") -> 6248 | T98: Técnica G1 | U98: Media | V98: Linterna para casco | W98: Cotizar linterna elastica que sirva para poneser en la cabeza o en el casco | X98: Descartada | Y98: Descartada
A99: 1040741865 | B99: Johan Esteban Florez Yepes | C99: 7542 | D99: Producción | E99: Descartada | N99: =IF(Tabla5[[#This Row],[VALOR INVERSIÓN]]="","",IF(Tabla5[[#This Row],[VALOR INVERSIÓN]]<=10000000,100%*10%*22000,IF(AND(Tabla5[[#This Row],[VALOR INVERSIÓN]]>10000000,Tabla5[[#This Row],[VALOR INVERSIÓN]]<=20000000),60%*10%*22000,20%*10%*22000))) | O99: =IF(Tabla5[[#This Row],[ROI (MESES)]]="","",IF(Tabla5[[#This Row],[ROI (MESES)]]="N/A","0",IF(Tabla5[[#This Row],[ROI (MESES)]]="<=3",100%*10%*22000,IF(Tabla5[[#This Row],[ROI (MESES)]]=">3<=6",75%*10%*22000,25%*10%*22000)))) | P99: =IF(Tabla5[[#This Row],[FACILIDAD IMPLEM.]]="","",IF(Tabla5[[#This Row],[FACILIDAD IMPLEM.]]="A",100%*10%*22000,IF(AND(Tabla5[[#This Row],[FACILIDAD IMPLEM.]]="B"),50%*10%*22000,20%*10%*22000))) | Q99: =Tabla5[[#This Row],[IMPACTO AMBIENTAL (Máx. 25%)]]*70%*22000+Tabla5[[#This Row],[IMPACTO ECONÓMICO (Máx. 25%)]]*70%*22000+Tabla5[[#This Row],[IMPACTO SST (Máx. 20%)]]*70%*22000+Tabla5[[#This Row],[IMPACTO PRODUCTIVIDAD (Máx. 25%)]]*70%*22000+Tabla5[[#This Row],[IMPACTO ORDEN Y ASEO (Máx. 5%)]]*70%*22000 -> 0 | R99: =IFERROR(Tabla5[[#This Row],[PUNTOS VALOR INVERSIÓN]]+Tabla5[[#This Row],[PUNTOS ROI ]]+Tabla5[[#This Row],[PUNTOS FACILIDAD IMPLEM. ]]+Tabla5[[#This Row],[PUNTOS IMPACTO ]],"")
A100: 1000567397 | B100: Alejandro Mazo | C100: 7543 | D100: Producción | E100: Descartada | N100: =IF(Tabla5[[#This Row],[VALOR INVERSIÓN]]="","",IF(Tabla5[[#This Row],[VALOR INVERSIÓN]]<=10000000,100%*10%*22000,IF(AND(Tabla5[[#This Row],[VALOR INVERSIÓN]]>10000000,Tabla5[[#This Row],[VALOR INVERSIÓN]]<=20000000),60%*10%*22000,20%*10%*22000))) | O100: =IF(Tabla5[[#This Row],[ROI (MESES)]]="","",IF(Tabla5[[#This Row],[ROI (MESES)]]="N/A","0",IF(Tabla5[[#This Row],[ROI (MESES)]]="<=3",100%*10%*22000,IF(Tabla5[[#This Row],[ROI (MESES)]]=">3<=6",75%*10%*22000,25%*10%*22000)))) | P100: =IF(Tabla5[[#This Row],[FACILIDAD IMPLEM.]]="","",IF(Tabla5[[#This Row],[FACILIDAD IMPLEM.]]="A",100%*10%*22000,IF(AND(Tabla5[[#This Row],[FACILIDAD IMPLEM.]]="B"),50%*10%*22000,20%*10%*22000))) | Q100: =Tabla5[[#This Row],[IMPACTO AMBIENTAL (Máx. 25%)]]*70%*22000+Tabla5[[#This Row],[IMPACTO ECONÓMICO (Máx. 25%)]]*70%*22000+Tabla5[[#This Row],[IMPACTO SST (Máx. 20%)]]*70%*22000+Tabla5[[#This Row],[IMPACTO PRODUCTIVIDAD (Máx. 25%)]]*70%*22000+Tabla5[[#This Row],[IMPACTO ORDEN Y ASEO (Máx. 5%)]]*70%*22000 -> 0 | R100: =IFERROR(Tabla5[[#This Row],[PUNTOS VALOR INVERSIÓN]]+Tabla5[[#This Row],[PUNTOS ROI ]]+Tabla5[[#This Row],[PUNTOS FACILIDAD IMPLEM. ]]+Tabla5[[#This Row],[PUNTOS IMPACTO ]],"") | S100: 09/12/2025 Notificado
A101: 71311035 | B101: Duverney Oquendo | C101: 7544 | D101: Producción | E101: Descartada | N101: =IF(Tabla5[[#This Row],[VALOR INVERSIÓN]]="","",IF(Tabla5[[#This Row],[VALOR INVERSIÓN]]<=10000000,100%*10%*22000,IF(AND(Tabla5[[#This Row],[VALOR INVERSIÓN]]>10000000,Tabla5[[#This Row],[VALOR INVERSIÓN]]<=20000000),60%*10%*22000,20%*10%*22000))) | O101: =IF(Tabla5[[#This Row],[ROI (MESES)]]="","",IF(Tabla5[[#This Row],[ROI (MESES)]]="N/A","0",IF(Tabla5[[#This Row],[ROI (MESES)]]="<=3",100%*10%*22000,IF(Tabla5[[#This Row],[ROI (MESES)]]=">3<=6",75%*10%*22000,25%*10%*22000)))) | P101: =IF(Tabla5[[#This Row],[FACILIDAD IMPLEM.]]="","",IF(Tabla5[[#This Row],[FACILIDAD IMPLEM.]]="A",100%*10%*22000,IF(AND(Tabla5[[#This Row],[FACILIDAD IMPLEM.]]="B"),50%*10%*22000,20%*10%*22000))) | Q101: =Tabla5[[#This Row],[IMPACTO AMBIENTAL (Máx. 25%)]]*70%*22000+Tabla5[[#This Row],[IMPACTO ECONÓMICO (Máx. 25%)]]*70%*22000+Tabla5[[#This Row],[IMPACTO SST (Máx. 20%)]]*70%*22000+Tabla5[[#This Row],[IMPACTO PRODUCTIVIDAD (Máx. 25%)]]*70%*22000+Tabla5[[#This Row],[IMPACTO ORDEN Y ASEO (Máx. 5%)]]*70%*22000 -> 0 | R101: =IFERROR(Tabla5[[#This Row],[PUNTOS VALOR INVERSIÓN]]+Tabla5[[#This Row],[PUNTOS ROI ]]+Tabla5[[#This Row],[PUNTOS FACILIDAD IMPLEM. ]]+Tabla5[[#This Row],[PUNTOS IMPACTO ]],"") | S101: No es útil
...

Sheet Puntos acumulados
A1: Nombre | B1: Cantidad Ideas | C1: Suma de Puntos | D1: Proceso
A2: Luis Carlos Ramos Rangel | B2: 10 | C2: 36498 | D2: =VLOOKUP(A2,'Tabla Calif. Puntos'!$B:$D,3,0) -> G.Técnica
A3: Paola Johana Restrepo Rios | B3: 7 | C3: 34870 | D3: =VLOOKUP(A3,'Tabla Calif. Puntos'!$B:$D,3,0) -> Comercial
A4: Sebastián Ossa Londoño | B4: 2 | C4: 23518 | D4: =VLOOKUP(A4,'Tabla Calif. Puntos'!$B:$D,3,0) -> Producción
A5: Jorge Andrés Carvajal | B5: 6 | C5: 21208 | D5: =VLOOKUP(A5,'Tabla Calif. Puntos'!$B:$D,3,0) -> Producción
A6: Jorge Eliecer Calderón Reyes | B6: 2 | C6: 16280 | D6: =VLOOKUP(A6,'Tabla Calif. Puntos'!$B:$D,3,0) -> G.Técnica
A7: Juan Camilo Agudelo Muñoz | B7: 2 | C7: 14190 | D7: =VLOOKUP(A7,'Tabla Calif. Puntos'!$B:$D,3,0) -> TI
A8: Roberto Carlos Rodríguez | B8: 3 | C8: 14124 | D8: =VLOOKUP(A8,'Tabla Calif. Puntos'!$B:$D,3,0) -> Producción
A9: Diego Uribe Castellanos | B9: 1 | C9: 13222 | D9: =VLOOKUP(A9,'Tabla Calif. Puntos'!$B:$D,3,0) -> G.Técnica
A10: Carlos Alberto Cardona Mira | B10: 3 | C10: 11704 | D10: =VLOOKUP(A10,'Tabla Calif. Puntos'!$B:$D,3,0) -> Comercial
A11: Jhon Jairo Villamizar Gutierrez | B11: 2 | C11: 10703 | D11: =VLOOKUP(A11,'Tabla Calif. Puntos'!$B:$D,3,0) -> Mantenimiento
A12: Alfredo Trujillo Cordoba | B12: 3 | C12: 9878 | D12: =VLOOKUP(A12,'Tabla Calif. Puntos'!$B:$D,3,0) -> G.Técnica
A13: Robert Smit Correa Conde | B13: 1 | C13: 9834 | D13: =VLOOKUP(A13,'Tabla Calif. Puntos'!$B:$D,3,0) -> Producción
... A56: Gustavo Adolfo Galeano Alvarez | B56: 1 | C56: 0 | D56: =VLOOKUP(A56,'Tabla Calif. Puntos'!$B:$D,3,0) -> Mantenimiento
A57: Juan Carlos Cano Ocampo | B57: 2 | C57: 0 | D57: G.Técnica
A58: Victoria Arciniegas Arteaga | B58: 2 | C58: 0 | D58: =VLOOKUP(A58,'Tabla Calif. Puntos'!$B:$D,3,0) -> G.Administrativa
A59: Fraiman Posada | B59: 1 | C59: 0 | D59: =VLOOKUP(A59,'Tabla Calif. Puntos'!$B:$D,3,0) -> Producción
A60: Jair José Aguilar Mora | B60: 1 | C60: 0 | D60: =VLOOKUP(A60,'Tabla Calif. Puntos'!$B:$D,3,0) -> Producción
A61: Hernan Dario Miranda Ramírez | B61: 3 | C61: 0 | D61: =VLOOKUP(A61,'Tabla Calif. Puntos'!$B:$D,3,0) -> Logística
A62: Jorge Andrés Aguilar | B62: 1 | C62: 0 | D62: =VLOOKUP(A62,'Tabla Calif. Puntos'!$B:$D,3,0) -> Producción
A63: Jenifer Mesa Castaño | B63: 1 | C63: 0 | D63: =VLOOKUP(A63,'Tabla Calif. Puntos'!$B:$D,3,0) -> Producción
A64: Darwin Acevedo Alzate | B64: 3 | C64: 0 | D64: =VLOOKUP(A64,'Tabla Calif. Puntos'!$B:$D,3,0) -> Logística
A65: Norma Lucia Balcazar Posada | B65: 1 | C65: 0 | D65: =VLOOKUP(A65,'Tabla Calif. Puntos'!$B:$D,3,0) -> Financiera
A66: Luis Octavio Acevedo | B66: 1 | C66: 0 | D66: =VLOOKUP(A66,'Tabla Calif. Puntos'!$B:$D,3,0) -> Logística
A67: Jesus Alberto Zapata Rueda | B67: 3 | C67: 0 | D67: =VLOOKUP(A67,'Tabla Calif. Puntos'!$B:$D,3,0) -> Logística
A68: Luisa Fernanda Carmona Ortiz | B68: 1 | C68: 0 | D68: =VLOOKUP(A68,'Tabla Calif. Puntos'!$B:$D,3,0) -> Comercial
A69: Pedro Alejandro Ruiz Orrego | B69: 1 | C69: 0 | D69: =VLOOKUP(A69,'Tabla Calif. Puntos'!$B:$D,3,0) -> Logística
... A83: José Julián Betancur Estrada | B83: 3 | C83: 0 | D83: =VLOOKUP(A83,'Tabla Calif. Puntos'!$B:$D,3,0) -> Producción
A84: Alejandro Mazo | B84: 2 | C84: 0 | D84: G.Técnica
A85: Juan Alejandro Atehortua Gañan | B85: 1 | C85: 0 | D85: =VLOOKUP(A85,'Tabla Calif. Puntos'!$B:$D,3,0) -> Producción
A86: Total general | B86: 170 | C86: 434797

Sheet Tabla Premios
A1: Premio | B1: Valor | C1: Cantidad | D1: Total | E1: Valor Punto | F1: Puntos
A2: Viaje para 2 personas San Andrés incluye ingreso a la isla | B2: 4500000 | C2: 1 | D2: =B2*C2 -> 4500000 | E2: 50 | F2: =Tabla2[[#This Row],[Valor]]/Tabla2[[#This Row],[Valor Punto]] -> 90000
A3: Computador Portatil 14" | B3: 2500000 | C3: 1 | D3: =B3*C3 -> 2500000 | E3: 35 | F3: =Tabla2[[#This Row],[Valor]]/Tabla2[[#This Row],[Valor Punto]] -> 71428.571
A4: Televisor 50" | B4: 1650000 | C4: 1 | D4: =B4*C4 -> 1650000 | E4: 25 | F4: =Tabla2[[#This Row],[Valor]]/Tabla2[[#This Row],[Valor Punto]] -> 66000
A5: Air fryer | B5: 450000 | C5: 1 | D5: =B5*C5 -> 450000 | E5: 9 | F5: =Tabla2[[#This Row],[Valor]]/Tabla2[[#This Row],[Valor Punto]] -> 50000
A6: Día de sol santorini | B6: 300000 | C6: 2 | D6: =B6*C6 -> 600000 | E6: 6 | F6: =Tabla2[[#This Row],[Valor]]/Tabla2[[#This Row],[Valor Punto]] -> 50000
A7: Día de sol guatapé | B7: 300000 | C7: 1 | D7: =B7*C7 -> 300000 | E7: 6 | F7: =Tabla2[[#This Row],[Valor]]/Tabla2[[#This Row],[Valor Punto]] -> 50000
A8: Parlante | B8: 250000 | C8: 1 | D8: =B8*C8 -> 250000 | E8: 6 | F8: =Tabla2[[#This Row],[Valor]]/Tabla2[[#This Row],[Valor Punto]] -> 41666.667
A9: Audífonos | B9: 250000 | C9: 1 | D9: =B9*C9 -> 250000 | E9: 6 | F9: =Tabla2[[#This Row],[Valor]]/Tabla2[[#This Row],[Valor Punto]] -> 41666.667
A10: Tour de miradores | B10: 160000 | C10: 1 | D10: =B10*C10 -> 160000 | E10: 5 | F10: =Tabla2[[#This Row],[Valor]]/Tabla2[[#This Row],[Valor Punto]] -> 32000
A11: Ancheta carne | B11: 150000 | C11: 1 | D11: =B11*C11 -> 150000 | E11: 5 | F11: =Tabla2[[#This Row],[Valor]]/Tabla2[[#This Row],[Valor Punto]] -> 30000
A12: Bono parque norte | B12: 150000 | C12: 1 | D12: =B12*C12 -> 150000 | E12: 5 | F12: =Tabla2[[#This Row],[Valor]]/Tabla2[[#This Row],[Valor Punto]] -> 30000
A13: Bono clásico medellín nacional | B13: 150000 | C13: 1 | D13: =B13*C13 -> 150000 | E13: 5 | F13: =Tabla2[[#This Row],[Valor]]/Tabla2[[#This Row],[Valor Punto]] -> 30000
... A26: Recarga datos | B26: 40000 | C26: 2 | D26: =B26*C26 -> 80000 | E26: 4 | F26: =Tabla2[[#This Row],[Valor]]/Tabla2[[#This Row],[Valor Punto]] -> 10000
A27: Efectivo por liquidación
A28: Total | B28: =SUBTOTAL(109,Tabla2[Valor]) -> 11770000 | D28: =SUBTOTAL(109,Tabla2[Total]) -> 12500000

Sheet Redención Puntos
A1: DOCUMENTO | B1: NOMBRE | C1: PREMIO REDIMIDO | D1: VALOR | E1: FECHA | F1: PUNTOS ACUMULADOS | G1: PUNTOS REDIMIDOS | H1: PUNTOS RESTANTES | I1: ENTREGA
A2: 1059704792 | B2: =VLOOKUP(Tabla3[[#This Row],[DOCUMENTO]],Tabla5[[#All],[DOCUMENTO]:[NOMBRE]],2,0) -> Jorge Eliecer Calderón Reyes | C2: Efectivo por liquidación | D2: 60000 | E2: 45565 | F2: =SUMIF(Tabla5[[DOCUMENTO]:[PUNTOS TOTALES]],Tabla3[[#This Row],[DOCUMENTO]],Tabla5[PUNTOS TOTALES]) -> 16280 | G2: 15000 | H2: =Tabla3[[#This Row],[PUNTOS ACUMULADOS]]-Tabla3[[#This Row],[PUNTOS REDIMIDOS]] -> 1280 | I2: Nómina
A3: 1065659658 | B3: =VLOOKUP(Tabla3[[#This Row],[DOCUMENTO]],Tabla5[[#All],[DOCUMENTO]:[NOMBRE]],2,0) -> Roberto Carlos Rodríguez | C3: Efectivo por liquidación | D3: 50000 | E3: 45597 | F3: =SUMIF(Tabla5[[DOCUMENTO]:[PUNTOS TOTALES]],Tabla3[[#This Row],[DOCUMENTO]],Tabla5[PUNTOS TOTALES]) -> 14124 | G3: 13000 | H3: =Tabla3[[#This Row],[PUNTOS ACUMULADOS]]-Tabla3[[#This Row],[PUNTOS REDIMIDOS]] -> 1124 | I3: Nómina
A4: 1037572152 | B4: =VLOOKUP(Tabla3[[#This Row],[DOCUMENTO]],Tabla5[[#All],[DOCUMENTO]:[NOMBRE]],2,0) -> Jorge Andrés Carvajal | C4: Bono creps | D4: 100000 | E4: 45784 | F4: =SUMIF(Tabla5[[DOCUMENTO]:[PUNTOS TOTALES]],Tabla3[[#This Row],[DOCUMENTO]],Tabla5[PUNTOS TOTALES]) -> 21208 | G4: 20000 | H4: =Tabla3[[#This Row],[PUNTOS ACUMULADOS]]-Tabla3[[#This Row],[PUNTOS REDIMIDOS]] -> 1208 | I4: Maria Alejandra Aguirre
A5: 1035919597 | B5: =VLOOKUP(Tabla3[[#This Row],[DOCUMENTO]],Tabla5[[#All],[DOCUMENTO]:[NOMBRE]],2,0) -> Sebastián Ossa Londoño | C5: Bono creps | D5: 100000 | E5: 45784 | F5: =SUMIF(Tabla5[[DOCUMENTO]:[PUNTOS TOTALES]],Tabla3[[#This Row],[DOCUMENTO]],Tabla5[PUNTOS TOTALES]) -> 23518 | G5: 20000 | H5: =Tabla3[[#This Row],[PUNTOS ACUMULADOS]]-Tabla3[[#This Row],[PUNTOS REDIMIDOS]] -> 3518 | I5: Maria Alejandra Aguirre
A6: 1000751888 | B6: =VLOOKUP(Tabla3[[#This Row],[DOCUMENTO]],Tabla5[[#All],[DOCUMENTO]:[NOMBRE]],2,0) -> Juan Camilo Agudelo Muñoz | C6: Bono D1 | D6: 50000 | E6: 45814 | F6: =SUMIF(Tabla5[[DOCUMENTO]:[PUNTOS TOTALES]],Tabla3[[#This Row],[DOCUMENTO]],Tabla5[PUNTOS TOTALES]) -> 14190 | G6: 13000 | H6: =Tabla3[[#This Row],[PUNTOS ACUMULADOS]]-Tabla3[[#This Row],[PUNTOS REDIMIDOS]] -> 1190 | I6: Luis Felipe Zapata Valencia
A7: 1005346180 | B7: =VLOOKUP(Tabla3[[#This Row],[DOCUMENTO]],Tabla5[[#All],[DOCUMENTO]:[NOMBRE]],2,0) -> Diego Uribe Castellanos | C7: Bono D1 | D7: 50000 | E7: 45814 | F7: =SUMIF(Tabla5[[DOCUMENTO]:[PUNTOS TOTALES]],Tabla3[[#This Row],[DOCUMENTO]],Tabla5[PUNTOS TOTALES]) -> 13222 | G7: 13000 | H7: =Tabla3[[#This Row],[PUNTOS ACUMULADOS]]-Tabla3[[#This Row],[PUNTOS REDIMIDOS]] -> 222 | I7: Luis Felipe Zapata Valencia
A8: 71690439 | B8: =VLOOKUP(Tabla3[[#This Row],[DOCUMENTO]],Tabla5[[#All],[DOCUMENTO]:[NOMBRE]],2,0) -> Jhon Jairo Villamizar Gutierrez | C8: Bono D1 | D8: 40000 | E8: 45814 | F8: =SUMIF(Tabla5[[DOCUMENTO]:[PUNTOS TOTALES]],Tabla3[[#This Row],[DOCUMENTO]],Tabla5[PUNTOS TOTALES]) -> 10703 | G8: 10000 | H8: =Tabla3[[#This Row],[PUNTOS ACUMULADOS]]-Tabla3[[#This Row],[PUNTOS REDIMIDOS]] -> 703 | I8: Luis Felipe Zapata Valencia
A9: 41942365 | B9: =VLOOKUP(Tabla3[[#This Row],[DOCUMENTO]],Tabla5[[#All],[DOCUMENTO]:[NOMBRE]],2,0) -> Paola Johana Restrepo Rios | C9: Bono D1 | D9: 160000 | E9: 45821 | F9: =SUMIF(Tabla5[[DOCUMENTO]:[PUNTOS TOTALES]],Tabla3[[#This Row],[DOCUMENTO]],Tabla5[PUNTOS TOTALES]) -> 34870 | G9: 32000 | H9: =Tabla3[[#This Row],[PUNTOS ACUMULADOS]]-Tabla3[[#This Row],[PUNTOS REDIMIDOS]] -> 2870 | I9: Luis Felipe Zapata Valencia
A10: 1128479264 | B10: =VLOOKUP(Tabla3[[#This Row],[DOCUMENTO]],Tabla5[[#All],[DOCUMENTO]:[NOMBRE]],2,0) -> Luis Carlos Ramos Rangel | C10: Bono D1 | D10: 160000 | E10: 45819 | F10: =SUMIF(Tabla5[[DOCUMENTO]:[PUNTOS TOTALES]],Tabla3[[#This Row],[DOCUMENTO]],Tabla5[PUNTOS TOTALES]) -> 36498 | G10: 32000 | H10: =Tabla3[[#This Row],[PUNTOS ACUMULADOS]]-Tabla3[[#This Row],[PUNTOS REDIMIDOS]] -> 4498 | I10: Valentina Caruso
A11: 75080238 | B11: =VLOOKUP(Tabla3[[#This Row],[DOCUMENTO]],Tabla5[[#All],[DOCUMENTO]:[NOMBRE]],2,0) -> Carlos Alberto Cardona Mira | C11: Bono D1 | D11: 40000 | E11: 45932 | F11: =SUMIF(Tabla5[[DOCUMENTO]:[PUNTOS TOTALES]],Tabla3[[#This Row],[DOCUMENTO]],Tabla5[PUNTOS TOTALES]) -> 11704 | G11: 10000 | H11: =Tabla3[[#This Row],[PUNTOS ACUMULADOS]]-Tabla3[[#This Row],[PUNTOS REDIMIDOS]] -> 1704 | I11: Valentina Caruso
A12: Total | D12: =SUBTOTAL(109,D2:D11) -> 810000 | I12: =SUBTOTAL(103,Tabla3[ENTREGA]) -> 10

Sheet Notificaciones
D1: REGISTRO NOTIFICACIONES
B3: PUNTOS POR IDEAS
A4: FESTIVOS | B4: DOCUMENTO | C4: NOMBRE | D4: RADICADO | E4: CELULAR | F4: FECHA RADICADO | G4: FECHA NOT. IDEA RECIBIDA | H4: FECHA NOT. PUNTOS ACUMULADOS | I4: DIAS TRANS. TOTALES
A5: 45474 | B5: 1001812262 | C5: José Julián Betancur Estrada | D5: 4866 | E5: 3218098350 | F5: 45476 | G5: 45489 | H5: 45504 | I5: =IFERROR(#REF!+#REF!,"")
A6: 45511 | B6: 71175113 | C6: Diego León Vásques Cortés | D6: 4951 | E6: 3108223356 | F6: 45481 | G6: 45489 | H6: 45498 | I6: =IFERROR(#REF!+#REF!,"")
A7: 45523 | B7: 1035919597 | C7: Sebastián Ossa Londoño | D7: 5368 | E7: 3148754310 | F7: 45496 | G7: 45498 | H7: 45498 | I7: =IFERROR(#REF!+#REF!,"")
A8: 45579 | B8: 1000751888 | C8: Juan Camilo Agudelo Muñoz | D8: 5427 | E8: 3117569630 | F8: 45498 | G8: 45498 | H8: 45505 | I8: =IFERROR(#REF!+#REF!,"")
A9: 45600 | B9: 1035913083 | C9: Maria Teresa Ríos Zapata | D9: 5469 | E9: 3217479290 | F9: 45498 | G9: 45499 | H9: 45614 | I9: =IFERROR(#REF!+#REF!,"")
A10: 45607 | B10: 1110570952 | C10: Andrés Felipe Ortega Rodríguez | D10: 5470 | E10: 3103328757 | F10: 45498 | G10: 45499 | H10: 45505 | I10: =IFERROR(#REF!+#REF!,"")
A11: 45651 | B11: 1059704792 | C11: Jorge Eliecer Calderón Reyes | D11: 5917 | E11: 3146359632 | F11: 45517 | G11: 45518 | H11: 45519 | I11: =IFERROR(#REF!+#REF!,"")
B12: 1059704792 | C12: Jorge Eliecer Calderón Reyes | D12: 5918 | E12: 3146359632 | F12: 45517 | G12: 45518 | H12: 45519 | I12: =IFERROR(#REF!+#REF!,"")
B13: 17685011 | C13: Alfredo Trujillo Cordoba | D13: 6263 | E13: 3163616098 | F13: 45533 | G13: 45533 | H13: 45646 | I13: =IFERROR(#REF!+#REF!,"")
B14: 1035918433 | C14: Mateo Arango Betancur | D14: 6254 | E14: 3244074165 | F14: 45532 | G14: 45533 | H14: 45646 | I14: =IFERROR(#REF!+#REF!,"")
B15: 1000751888 | C15: Juan Camilo Agudelo Muñoz | D15: 5983 | E15: 3117569630 | F15: 45519 | G15: 45519 | H15: 45638 | I15: =IFERROR(#REF!+#REF!,"")
B16: 1005346180 | C16: Diego Uribe Castellanos | D16: 6026 | E16: 3045578181 | F16: 45520 | G16: 45524 | H16: 45525 | I16: =IFERROR(#REF!+#REF!,"")
B17: 1045047014 | C17: Juan Carlos Cano Ocampo | D17: 6057 | E17: 3136876634 | F17: 45524 | G17: 45525 | H17: 45622 | I17: =IFERROR(#REF!+#REF!,"")
B18: 73570530 | C18: Jair José Aguilar Mora | D18: 6071 | E18: 3204228533 | F18: 45525 | G18: 45525 | H18: 45622 | I18: =IFERROR(#REF!+#REF!,"")
B19: 1001416385 | C19: Duván Arley López Jiménez | D19: 6223 | E19: 3008869275 | F19: 45531 | G19: 45532 | H19: 45622 | I19: =IFERROR(#REF!+#REF!,"")
B20: 1128479264 | C20: Luis Carlos Ramos Rangel | D20: 6226 | E20: 3163137199 | F20: 45531 | G20: 45532 | H20: 45622 | I20: =IFERROR(#REF!+#REF!,"")
B21: 17685011 | C21: Alfredo Trujillo Cordoba | D21: 8201 | E21: 3163616098 | F21: 45602 | G21: 45611 | H21: 45720 | I21: =IFERROR(#REF!+#REF!,"")
B22: 1128479264 | C22: Luis Carlos Ramos Rangel | D22: 6252 | E22: 3163137199 | F22: 45532 | G22: 45533 | H22: 45533 | I22: =IFERROR(#REF!+#REF!,"")
B23: 1035910024 | C23: Leonela Garcia Rios | D23: 8054 | E23: 3117288733 | F23: 45597 | G23: 45614 | H23: 45720 | I23: =IFERROR(#REF!+#REF!,"")
... B174: 1110570952 | C174: Andrés Felipe Ortega Rodríguez | D174: 977 | E174: 3103328757 | F174: 45688 | G174: 45692 | H174: 45716 | I174: =IFERROR(#REF!+#REF!,"")
B175: Total | D175: =SUBTOTAL(103,Notificaciones[RADICADO]) -> 170
